Workbook

Sheet 39-6-OZ
B2: STOCK CARD- REF.NO | U2: YRAR | V2: 2023
B3: THE EMPIRE JUTE MILL | R3: HESSIAN
B4: DESCRIPTION OF GOODS:- HESSIAN CLOTH 39-6 OZ/40 8X7 | R4: SACKING
A5: NATURE OF PACKING :- 1/B 2000 YDS | R5: YARN
D6: OPENING BALANCE | G6: RECEIPT | I6: TOTAL | K6: ISSUES | M6: GROSS WT | O6: CLOSING BALLACE | Q6: REMARKS | R6: NET WGT. PER BALE | S6: 331.695
D7: NO.OF | E7: WEIGHT IN | G7: NO.OF | H7: WEIGHT IN | I7: NO.OF | J7: WEIGHT IN | K7: NO.OF | L7: NET WT | O7: NO.OF | P7: WEIGHT IN | R7: P.SHEET WGT | S7: 2.488
B8: DATE | D8: BALE | E8: KGS | G8: BALE | I8: BALE | J8: KGS | K8: BALE | L8: KGS | N8: PACK SHEET | O8: BALE | P8: KGS | R8: TOTAL WGT | S8: =S6+S7 -> 334.183
B9: 1 | D9: 43 | E9: =$S$8*D9/1000 -> 14.369869 | G9: 16 | H9: =G9*S$8/1000 -> 5.346928 | I9: =D9+G9 -> 59 | J9: =$S$8*I9/1000 -> 19.716797 | L9: =K9*S$6/1000 -> 0 | M9: =K9*S$8/1000 -> 0 | N9: =K9*S$7/1000 -> 0 | O9: =I9-K9 -> 59 | P9: =$S$8*O9/1000 -> 19.716797
B10: 2 | D10: =+O9 -> 59 | E10: =$S$8*D10/1000 -> 19.716797 | G10: 7 | H10: =G10*S$8/1000 -> 2.339281 | I10: =D10+G10 -> 66 | J10: =$S$8*I10/1000 -> 22.056078 | L10: =K10*S$6/1000 -> 0 | M10: =K10*S$8/1000 -> 0 | N10: =K10*S$7/1000 -> 0 | O10: =I10-K10 -> 66 | P10: =$S$8*O10/1000 -> 22.056078
B11: 3 | D11: =+O10 -> 66 | E11: =$S$8*D11/1000 -> 22.056078 | G11: 7 | H11: =G11*S$8/1000 -> 2.339281 | I11: =D11+G11 -> 73 | J11: =$S$8*I11/1000 -> 24.395359 | L11: =K11*S$6/1000 -> 0 | M11: =K11*S$8/1000 -> 0 | N11: =K11*S$7/1000 -> 0 | O11: =I11-K11 -> 73 | P11: =$S$8*O11/1000 -> 24.395359
B12: 4 | D12: =+O11 -> 73 | E12: =$S$8*D12/1000 -> 24.395359 | G12: 9 | H12: =G12*S$8/1000 -> 3.007647 | I12: =D12+G12 -> 82 | J12: =$S$8*I12/1000 -> 27.403006 | L12: =K12*S$6/1000 -> 0 | M12: =K12*S$8/1000 -> 0 | N12: =K12*S$7/1000 -> 0 | O12: =I12-K12 -> 82 | P12: =$S$8*O12/1000 -> 27.403006
B13: 5 | D13: =+O12 -> 82 | E13: =$S$8*D13/1000 -> 27.403006 | G13: 16 | H13: =G13*S$8/1000 -> 5.346928 | I13: =D13+G13 -> 98 | J13: =$S$8*I13/1000 -> 32.749934 | K13: 3 | L13: =K13*S$6/1000 -> 0.995085 | M13: =K13*S$8/1000 -> 1.002549 | N13: =K13*S$7/1000 -> 0.007464 | O13: =I13-K13 -> 95 | P13: =$S$8*O13/1000 -> 31.747385
B14: 6 | D14: =+O13 -> 95 | E14: =$S$8*D14/1000 -> 31.747385 | G14: 6 | H14: =G14*S$8/1000 -> 2.005098 | I14: =D14+G14 -> 101 | J14: =$S$8*I14/1000 -> 33.752483 | L14: =K14*S$6/1000 -> 0 | M14: =K14*S$8/1000 -> 0 | N14: =K14*S$7/1000 -> 0 | O14: =I14-K14 -> 101 | P14: =$S$8*O14/1000 -> 33.752483
B15: 7 | D15: =+O14 -> 101 | E15: =$S$8*D15/1000 -> 33.752483 | G15: 0 | H15: =G15*S$8/1000 -> 0 | I15: =D15+G15 -> 101 | J15: =$S$8*I15/1000 -> 33.752483 | L15: =K15*S$6/1000 -> 0 | M15: =K15*S$8/1000 -> 0 | N15: =K15*S$7/1000 -> 0 | O15: =I15-K15 -> 101 | P15: =$S$8*O15/1000 -> 33.752483
B16: 8 | D16: =+O15 -> 101 | E16: =$S$8*D16/1000 -> 33.752483 | G16: 0 | H16: =G16*S$8/1000 -> 0 | I16: =D16+G16 -> 101 | J16: =$S$8*I16/1000 -> 33.752483 | L16: =K16*S$6/1000 -> 0 | M16: =K16*S$8/1000 -> 0 | N16: =K16*S$7/1000 -> 0 | O16: =I16-K16 -> 101 | P16: =$S$8*O16/1000 -> 33.752483
B17: 9 | D17: =+O16 -> 101 | E17: =$S$8*D17/1000 -> 33.752483 | G17: 8 | H17: =G17*S$8/1000 -> 2.673464 | I17: =D17+G17 -> 109 | J17: =$S$8*I17/1000 -> 36.425947 | L17: =K17*S$6/1000 -> 0 | M17: =K17*S$8/1000 -> 0 | N17: =K17*S$7/1000 -> 0 | O17: =I17-K17 -> 109 | P17: =$S$8*O17/1000 -> 36.425947
B18: 10 | D18: =+O17 -> 109 | E18: =$S$8*D18/1000 -> 36.425947 | H18: =G18*S$8/1000 -> 0 | I18: =D18+G18 -> 109 | J18: =$S$8*I18/1000 -> 36.425947 | L18: =K18*S$6/1000 -> 0 | M18: =K18*S$8/1000 -> 0 | N18: =K18*S$7/1000 -> 0 | O18: =I18-K18 -> 109 | P18: =$S$8*O18/1000 -> 36.425947
B19: 11 | D19: =+O18 -> 109 | E19: =$S$8*D19/1000 -> 36.425947 | H19: =G19*S$8/1000 -> 0 | I19: =D19+G19 -> 109 | J19: =$S$8*I19/1000 -> 36.425947 | L19: =K19*S$6/1000 -> 0 | M19: =K19*S$8/1000 -> 0 | N19: =K19*S$7/1000 -> 0 | O19: =I19-K19 -> 109 | P19: =$S$8*O19/1000 -> 36.425947
B20: 12 | D20: =+O19 -> 109 | E20: =$S$8*D20/1000 -> 36.425947 | G20: 1 | H20: =G20*S$8/1000 -> 0.334183 | I20: =D20+G20 -> 110 | J20: =$S$8*I20/1000 -> 36.76013 | L20: =K20*S$6/1000 -> 0 | M20: =K20*S$8/1000 -> 0 | N20: =K20*S$7/1000 -> 0 | O20: =I20-K20 -> 110 | P20: =$S$8*O20/1000 -> 36.76013
B21: 13 | D21: =+O20 -> 110 | E21: =$S$8*D21/1000 -> 36.76013 | H21: =G21*S$8/1000 -> 0 | I21: =D21+G21 -> 110 | J21: =$S$8*I21/1000 -> 36.76013 | L21: =K21*S$6/1000 -> 0 | M21: =K21*S$8/1000 -> 0 | N21: =K21*S$7/1000 -> 0 | O21: =I21-K21 -> 110 | P21: =$S$8*O21/1000 -> 36.76013
B22: 14 | D22: =+O21 -> 110 | E22: =$S$8*D22/1000 -> 36.76013 | H22: =G22*S$8/1000 -> 0 | I22: =D22+G22 -> 110 | J22: =$S$8*I22/1000 -> 36.76013 | L22: =K22*S$6/1000 -> 0 | M22: =K22*S$8/1000 -> 0 | N22: =K22*S$7/1000 -> 0 | O22: =I22-K22 -> 110 | P22: =$S$8*O22/1000 -> 36.76013 | S22: 1000
B23: 15 | D23: =+O22 -> 110 | E23: =$S$8*D23/1000 -> 36.76013 | H23: =G23*S$8/1000 -> 0 | I23: =D23+G23 -> 110 | J23: =$S$8*I23/1000 -> 36.76013 | L23: =K23*S$6/1000 -> 0 | M23: =K23*S$8/1000 -> 0 | N23: =K23*S$7/1000 -> 0 | O23: =I23-K23 -> 110 | P23: =$S$8*O23/1000 -> 36.76013
B24: 16 | D24: =+O23 -> 110 | E24: =$S$8*D24/1000 -> 36.76013 | G24: 2 | H24: =G24*S$8/1000 -> 0.668366 | I24: =D24+G24 -> 112 | J24: =$S$8*I24/1000 -> 37.428496 | K24: 112 | L24: =K24*S$6/1000 -> 37.14984 | M24: =K24*S$8/1000 -> 37.428496 | N24: =K24*S$7/1000 -> 0.278656 | O24: =I24-K24 -> 0 | P24: =$S$8*O24/1000 -> 0 | R24: 7.5 | S24: 39 | U24: 6 | V24: 40 | X24: 28.35 | Y24: 2000
B25: 17 | D25: =+O24 -> 0 | E25: =$S$8*D25/1000 -> 0 | H25: =G25*S$8/1000 -> 0 | I25: =D25+G25 -> 0 | J25: =$S$8*I25/1000 -> 0 | L25: =K25*S$6/1000 -> 0 | M25: =K25*S$8/1000 -> 0 | N25: =K25*S$7/1000 -> 0 | O25: =I25-K25 -> 0 | P25: =$S$8*O25/1000 -> 0 | S25: =S24*U24/V24*X24*Y24/S22 -> 331.695
B26: 18 | D26: =+O25 -> 0 | E26: =$S$8*D26/1000 -> 0 | H26: =G26*S$8/1000 -> 0 | I26: =D26+G26 -> 0 | J26: =$S$8*I26/1000 -> 0 | L26: =K26*S$6/1000 -> 0 | M26: =K26*S$8/1000 -> 0 | N26: =K26*S$7/1000 -> 0 | O26: =I26-K26 -> 0 | P26: =$S$8*O26/1000 -> 0 | S26: =S25*R24/S22 -> 2.4877125
B27: 19 | D27: =+O26 -> 0 | E27: =$S$8*D27/1000 -> 0 | H27: =G27*S$8/1000 -> 0 | I27: =D27+G27 -> 0 | J27: =$S$8*I27/1000 -> 0 | L27: =K27*S$6/1000 -> 0 | M27: =K27*S$8/1000 -> 0 | N27: =K27*S$7/1000 -> 0 | O27: =I27-K27 -> 0 | P27: =$S$8*O27/1000 -> 0 | S27: =S25+S26 -> 334.18271
B28: 20 | D28: =+O27 -> 0 | E28: =$S$8*D28/1000 -> 0 | H28: =G28*S$8/1000 -> 0 | I28: =D28+G28 -> 0 | J28: =$S$8*I28/1000 -> 0 | L28: =K28*S$6/1000 -> 0 | M28: =K28*S$8/1000 -> 0 | N28: =K28*S$7/1000 -> 0 | O28: =I28-K28 -> 0 | P28: =$S$8*O28/1000 -> 0
B29: 21 | D29: =+O28 -> 0 | E29: =$S$8*D29/1000 -> 0 | H29: =G29*S$8/1000 -> 0 | I29: =D29+G29 -> 0 | J29: =$S$8*I29/1000 -> 0 | L29: =K29*S$6/1000 -> 0 | M29: =K29*S$8/1000 -> 0 | N29: =K29*S$7/1000 -> 0 | O29: =I29-K29 -> 0 | P29: =$S$8*O29/1000 -> 0
B30: 22 | D30: =+O29 -> 0 | E30: =$S$8*D30/1000 -> 0 | G30: 0 | H30: =G30*S$8/1000 -> 0 | I30: =D30+G30 -> 0 | J30: =$S$8*I30/1000 -> 0 | L30: =K30*S$6/1000 -> 0 | M30: =K30*S$8/1000 -> 0 | N30: =K30*S$7/1000 -> 0 | O30: =I30-K30 -> 0 | P30: =$S$8*O30/1000 -> 0
B31: 23 | D31: =+O30 -> 0 | E31: =$S$8*D31/1000 -> 0 | G31: 1 | H31: =G31*S$8/1000 -> 0.334183 | I31: =D31+G31 -> 1 | J31: =$S$8*I31/1000 -> 0.334183 | L31: =K31*S$6/1000 -> 0 | M31: =K31*S$8/1000 -> 0 | N31: =K31*S$7/1000 -> 0 | O31: =I31-K31 -> 1 | P31: =$S$8*O31/1000 -> 0.334183
B32: 24 | D32: =+O31 -> 1 | E32: =$S$8*D32/1000 -> 0.334183 | G32: 1 | H32: =G32*S$8/1000 -> 0.334183 | I32: =D32+G32 -> 2 | J32: =$S$8*I32/1000 -> 0.668366 | L32: =K32*S$6/1000 -> 0 | M32: =K32*S$8/1000 -> 0 | N32: =K32*S$7/1000 -> 0 | O32: =I32-K32 -> 2 | P32: =$S$8*O32/1000 -> 0.668366
B33: 25 | D33: =+O32 -> 2 | E33: =$S$8*D33/1000 -> 0.668366 | H33: =G33*S$8/1000 -> 0 | I33: =D33+G33 -> 2 | J33: =$S$8*I33/1000 -> 0.668366 | L33: =K33*S$6/1000 -> 0 | M33: =K33*S$8/1000 -> 0 | N33: =K33*S$7/1000 -> 0 | O33: =I33-K33 -> 2 | P33: =$S$8*O33/1000 -> 0.668366
B34: 26 | D34: =+O33 -> 2 | E34: =$S$8*D34/1000 -> 0.668366 | G34: 1 | H34: =G34*S$8/1000 -> 0.334183 | I34: =D34+G34 -> 3 | J34: =$S$8*I34/1000 -> 1.002549 | L34: =K34*S$6/1000 -> 0 | M34: =K34*S$8/1000 -> 0 | N34: =K34*S$7/1000 -> 0 | O34: =I34-K34 -> 3 | P34: =$S$8*O34/1000 -> 1.002549
B35: 27 | D35: =+O34 -> 3 | E35: =$S$8*D35/1000 -> 1.002549 | G35: 3 | H35: =G35*S$8/1000 -> 1.002549 | I35: =D35+G35 -> 6 | J35: =$S$8*I35/1000 -> 2.005098 | L35: =K35*S$6/1000 -> 0 | M35: =K35*S$8/1000 -> 0 | N35: =K35*S$7/1000 -> 0 | O35: =I35-K35 -> 6 | P35: =$S$8*O35/1000 -> 2.005098
B36: 28 | D36: =+O35 -> 6 | E36: =$S$8*D36/1000 -> 2.005098 | H36: =G36*S$8/1000 -> 0 | I36: =D36+G36 -> 6 | J36: =$S$8*I36/1000 -> 2.005098 | L36: =K36*S$6/1000 -> 0 | M36: =K36*S$8/1000 -> 0 | N36: =K36*S$7/1000 -> 0 | O36: =I36-K36 -> 6 | P36: =$S$8*O36/1000 -> 2.005098
B37: 29 | D37: =+O36 -> 6 | E37: =$S$8*D37/1000 -> 2.005098 | G37: 4 | H37: =G37*S$8/1000 -> 1.336732 | I37: =D37+G37 -> 10 | J37: =$S$8*I37/1000 -> 3.34183 | L37: =K37*S$6/1000 -> 0 | M37: =K37*S$8/1000 -> 0 | N37: =K37*S$7/1000 -> 0 | O37: =I37-K37 -> 10 | P37: =$S$8*O37/1000 -> 3.34183
B38: 30 | D38: =+O37 -> 10 | E38: =$S$8*D38/1000 -> 3.34183 | G38: 6 | H38: =G38*S$8/1000 -> 2.005098 | I38: =D38+G38 -> 16 | J38: =$S$8*I38/1000 -> 5.346928 | L38: =K38*S$6/1000 -> 0 | M38: =K38*S$8/1000 -> 0 | N38: =K38*S$7/1000 -> 0 | O38: =I38-K38 -> 16 | P38: =$S$8*O38/1000 -> 5.346928
B39: 31 | D39: =+O38 -> 16 | E39: =$S$8*D39/1000 -> 5.346928 | G39: 1 | H39: =G39*S$8/1000 -> 0.334183 | I39: =D39+G39 -> 17 | J39: =$S$8*I39/1000 -> 5.681111 | L39: =K39*S$6/1000 -> 0 | M39: =K39*S$8/1000 -> 0 | N39: =K39*S$7/1000 -> 0 | O39: =I39-K39 -> 17 | P39: =$S$8*O39/1000 -> 5.681111
B40: TOTAL | G40: =SUM(G9:G39) -> 89 | H40: =SUM(H9:H39) -> 29.742287 | K40: =SUM(K9:K39) -> 115 | L40: =SUM(L9:L39) -> 38.144925 | M40: =SUM(M9:M39) -> 38.431045 | N40: =SUM(N9:N39) -> 0.28612
B42: PROD PACK SHEET | G42: =G40*S7/1000 -> 0.221432 | H42: =+G40*S6/1000 -> 29.520855 | J42: DESPATCH PACK SHEET | L42: =+K40*S7/1000 -> 0.28612
H45: HESIAN TOTAL PCK SHEET | K45: =+G42+'20 X10 '!G42+'38-8.12-OZ '!G42+'44-8.12 OZ'!G42+'40-4.5-OZ'!G42+'36-4.05 OZ'!G42+'34-9.82'!G42+'54-6.5'!G42+'44-7.15 '!G42+'48-8.4-OZ '!G42+'40-6.5'!G42+'48-7.80 EXP'!E42+'40-5-OZ-EXP'!E42+'48-6 EXPORT'!G42+'44-5 OZ'!G42+'44-8.12 OZ (2)'!G42 -> 0.71550262
H47: EXPORT TOTAL PCK SHEET | K47: =+'40-5-OZ-EXP'!E42+'EXPORT '!E42 -> 0 | L47: HESS CLEARENCE PACKSHEED | O47: =+L42+'20 X10 '!L42+'38-8.12-OZ '!L42+'44-8.12 OZ'!L42+'40-4.5-OZ'!L42+'36-4.05 OZ'!L42+'34-9.82'!L42+'54-6.5'!L42+'44-7.15 '!L42+'48-8.4-OZ '!K42+'40-6.5'!L42+'51-11.36-OZ '!L42+'48-7.80 EXP'!L42+'40-5-OZ-EXP'!L42+'48-6 EXPORT'!L42+'44-5 OZ'!L42+'44-8.12 OZ (2)'!L42 -> 0.81918112
H48: TOTAL HESS + EXPORT | K48: =K45+K47 -> 0.71550262
L49: SKG CLEARENCE PACKSHEED | O49: =+'TYPE A GOV'!L42+'767 GMS 500 PCS'!L42 -> 2.081475
H50: SACKING TOTAL PCK SHEET | K50: =+'TYPE A GOV'!G42+'767 GMS 500 PCS'!G42 -> 1.42245
H52: GRAND TOTAL PACK SHEET | K52: =K45+K47+K50 -> 2.1379526

Sheet 20 X10 
B2: STOCK CARD- REF.NO
B3: THE EMPIRE JUTE MILL | R3: HESSIAN
B4: DESCRIPTION OF GOODS:- HESSIAN CLOTH 20X10 72 GM/BAG | R4: SACKING
A5: NATURE OF PACKING :- 1/B 2000 PCS | R5: YARN
B6: DATE | D6: OPENING BALANCE | G6: RECEIPT | I6: TOTAL | K6: ISSUES | M6: GROSS WT | O6: CLOSING BALLACE | Q6: REMARKS | R6: NET WGT. PER BALE | S6: 144
D7: NO.OF | E7: WEIGHT IN | G7: NO.OF | H7: WEIGHT IN | I7: NO.OF | J7: WEIGHT IN | K7: NO.OF | L7: NET WT | O7: NO.OF | P7: WEIGHT IN | R7: P.SHEET WGT | S7: =S6*0.75% -> 1.08
D8: BALE | E8: KGS | G8: BALE | H8: KGS | I8: BALE | J8: KGS | K8: BALE | L8: KGS | N8: PACK SHEET | O8: BALE | P8: KGS | R8: TOTAL WGT | S8: =S6+S7 -> 145.08
B9: 1 | E9: =$S$8*D9/1000 -> 0 | H9: =$S$8*G9/1000 -> 0 | I9: =D9+G9 -> 0 | J9: =$S$8*I9/1000 -> 0 | L9: =K9*S$6/1000 -> 0 | M9: =K9*S$8/1000 -> 0 | N9: =K9*S$7/1000 -> 0 | O9: =I9-K9 -> 0 | P9: =$S$8*O9/1000 -> 0 | Q9: =P9*T8/1000 -> 0
B10: 2 | D10: =+O9 -> 0 | E10: =$S$8*D10/1000 -> 0 | H10: =$S$8*G10/1000 -> 0 | I10: =D10+G10 -> 0 | J10: =$S$8*I10/1000 -> 0 | L10: =K10*S$6/1000 -> 0 | M10: =K10*S$8/1000 -> 0 | N10: =K10*S$7/1000 -> 0 | O10: =I10-K10 -> 0 | P10: =$S$8*O10/1000 -> 0
B11: 3 | D11: =+O10 -> 0 | E11: =$S$8*D11/1000 -> 0 | H11: =$S$8*G11/1000 -> 0 | I11: =D11+G11 -> 0 | J11: =$S$8*I11/1000 -> 0 | L11: =K11*S$6/1000 -> 0 | M11: =K11*S$8/1000 -> 0 | N11: =K11*S$7/1000 -> 0 | O11: =I11-K11 -> 0 | P11: =$S$8*O11/1000 -> 0
B12: 4 | D12: =+O11 -> 0 | E12: =$S$8*D12/1000 -> 0 | H12: =$S$8*G12/1000 -> 0 | I12: =D12+G12 -> 0 | J12: =$S$8*I12/1000 -> 0 | L12: =K12*S$6/1000 -> 0 | M12: =K12*S$8/1000 -> 0 | N12: =K12*S$7/1000 -> 0 | O12: =I12-K12 -> 0 | P12: =$S$8*O12/1000 -> 0
B13: 5 | D13: =+O12 -> 0 | E13: =$S$8*D13/1000 -> 0 | H13: =$S$8*G13/1000 -> 0 | I13: =D13+G13 -> 0 | J13: =$S$8*I13/1000 -> 0 | L13: =K13*S$6/1000 -> 0 | M13: =K13*S$8/1000 -> 0 | N13: =K13*S$7/1000 -> 0 | O13: =I13-K13 -> 0 | P13: =$S$8*O13/1000 -> 0
B14: 6 | D14: =+O13 -> 0 | E14: =$S$8*D14/1000 -> 0 | H14: =$S$8*G14/1000 -> 0 | I14: =D14+G14 -> 0 | J14: =$S$8*I14/1000 -> 0 | L14: =K14*S$6/1000 -> 0 | M14: =K14*S$8/1000 -> 0 | N14: =K14*S$7/1000 -> 0 | O14: =I14-K14 -> 0 | P14: =$S$8*O14/1000 -> 0
B15: 7 | D15: =+O14 -> 0 | E15: =$S$8*D15/1000 -> 0 | H15: =$S$8*G15/1000 -> 0 | I15: =D15+G15 -> 0 | J15: =$S$8*I15/1000 -> 0 | L15: =K15*S$6/1000 -> 0 | M15: =K15*S$8/1000 -> 0 | N15: =K15*S$7/1000 -> 0 | O15: =I15-K15 -> 0 | P15: =$S$8*O15/1000 -> 0
B16: 8 | D16: =+O15 -> 0 | E16: =$S$8*D16/1000 -> 0 | H16: =$S$8*G16/1000 -> 0 | I16: =D16+G16 -> 0 | J16: =$S$8*I16/1000 -> 0 | L16: =K16*S$6/1000 -> 0 | M16: =K16*S$8/1000 -> 0 | N16: =K16*S$7/1000 -> 0 | O16: =I16-K16 -> 0 | P16: =$S$8*O16/1000 -> 0
B17: 9 | D17: =+O16 -> 0 | E17: =$S$8*D17/1000 -> 0 | H17: =$S$8*G17/1000 -> 0 | I17: =D17+G17 -> 0 | J17: =$S$8*I17/1000 -> 0 | L17: =K17*S$6/1000 -> 0 | M17: =K17*S$8/1000 -> 0 | N17: =K17*S$7/1000 -> 0 | O17: =I17-K17 -> 0 | P17: =$S$8*O17/1000 -> 0
B18: 10 | D18: =+O17 -> 0 | E18: =$S$8*D18/1000 -> 0 | H18: =$S$8*G18/1000 -> 0 | I18: =D18+G18 -> 0 | J18: =$S$8*I18/1000 -> 0 | L18: =K18*S$6/1000 -> 0 | M18: =K18*S$8/1000 -> 0 | N18: =K18*S$7/1000 -> 0 | O18: =I18-K18 -> 0 | P18: =$S$8*O18/1000 -> 0
B19: 11 | D19: =+O18 -> 0 | E19: =$S$8*D19/1000 -> 0 | H19: =$S$8*G19/1000 -> 0 | I19: =D19+G19 -> 0 | J19: =$S$8*I19/1000 -> 0 | L19: =K19*S$6/1000 -> 0 | M19: =K19*S$8/1000 -> 0 | N19: =K19*S$7/1000 -> 0 | O19: =I19-K19 -> 0 | P19: =$S$8*O19/1000 -> 0
B20: 12 | D20: =+O19 -> 0 | E20: =$S$8*D20/1000 -> 0 | H20: =$S$8*G20/1000 -> 0 | I20: =D20+G20 -> 0 | J20: =$S$8*I20/1000 -> 0 | L20: =K20*S$6/1000 -> 0 | M20: =K20*S$8/1000 -> 0 | N20: =K20*S$7/1000 -> 0 | O20: =I20-K20 -> 0 | P20: =$S$8*O20/1000 -> 0
B21: 13 | D21: =+O20 -> 0 | E21: =$S$8*D21/1000 -> 0 | H21: =$S$8*G21/1000 -> 0 | I21: =D21+G21 -> 0 | J21: =$S$8*I21/1000 -> 0 | L21: =K21*S$6/1000 -> 0 | M21: =K21*S$8/1000 -> 0 | N21: =K21*S$7/1000 -> 0 | O21: =I21-K21 -> 0 | P21: =$S$8*O21/1000 -> 0
... B38: 30 | D38: =+O37 -> 0 | E38: =$S$8*D38/1000 -> 0 | H38: =$S$8*G38/1000 -> 0 | I38: =D38+G38 -> 0 | J38: =$S$8*I38/1000 -> 0 | L38: =K38*S$6/1000 -> 0 | M38: =K38*S$8/1000 -> 0 | N38: =K38*S$7/1000 -> 0 | O38: =I38-K38 -> 0 | P38: =$S$8*O38/1000 -> 0
B39: 31 | E39: =$S$8*D39/1000 -> 0 | H39: =$S$8*G39/1000 -> 0 | I39: =D39+G39 -> 0 | J39: =$S$8*I39/1000 -> 0 | L39: =K39*S$6/1000 -> 0 | M39: =K39*S$8/1000 -> 0 | N39: =K39*S$7/1000 -> 0 | O39: =I39-K39 -> 0 | P39: =$S$8*O39/1000 -> 0
B40: TOTAL | F40: =SUM(F9:F39) -> 0 | G40: =SUM(G9:G39) -> 0 | H40: =SUM(H9:H39) -> 0 | K40: =SUM(K9:K39) -> 0 | L40: =SUM(L9:L39) -> 0 | M40: =SUM(M9:M39) -> 0 | N40: =SUM(N9:N39) -> 0 | R40: 72 | S40: 2000 | U40: =R40*S40/1000 -> 144 | V40: 144
S41: 0.75 | U41: =U40*S41/1000 -> 0.108 | V41: 0.5
B42: PACK SHEET | G42: =G40*S7/1000 -> 0 | J42: DESPATCH PACKSHEET | L42: =+K40*S7/1000 -> 0 | U42: TOTAL | V42: =V40+V41 -> 144.5

Sheet 38-8.12-OZ 
B2: STOCK CARD- REF.NO
B3: THE EMPIRE JUTE MILL | R3: HESSIAN
B4: DESCRIPTION OF GOODS:- HESSIAN CLOTH 38-8.12 OZ/40 , 11X10 PLAIN | R4: SACKING
A5: NATURE OF PACKING :- 1/B 2000 YDS | R5: YARN
B6: DATE | D6: OPENING BALANCE | G6: RECEIPT | I6: TOTAL | K6: ISSUES | M6: GROSS WT | O6: CLOSING BALLACE | Q6: REMARKS | R6: NET WGT. PER BALE | S6: 437.384
D7: NO.OF | E7: WEIGHT IN | G7: NO.OF | H7: WEIGHT IN M.T | I7: NO.OF | J7: WEIGHT IN | K7: NO.OF | L7: NET WT | O7: NO.OF | P7: WEIGHT IN | R7: P.SHEET WGT | S7: 3.28
D8: BALE | E8: KGS | G8: BALE | I8: BALE | J8: KGS | K8: BALE | L8: KGS | N8: PACK SHEET | O8: BALE | P8: KGS | R8: TOTAL WGT | S8: =S6+S7 -> 440.664
B9: 1 | D9: 40 | E9: =$S$8*D9/1000 -> 17.62656 | H9: =$S$8*G9/1000 -> 0 | I9: =D9+G9 -> 40 | J9: =$S$8*I9/1000 -> 17.62656 | K9: 40 | L9: =K9*S$6/1000 -> 17.49536 | M9: =K9*S$8/1000 -> 17.62656 | N9: =K9*S$7/1000 -> 0.1312 | O9: =I9-K9 -> 0 | P9: =$S$8*O9/1000 -> 0 | Q9: =P9*T8/1000 -> 0
B10: 2 | D10: =+O9 -> 0 | E10: =$S$8*D10/1000 -> 0 | G10: 3 | H10: =$S$8*G10/1000 -> 1.321992 | I10: =D10+G10 -> 3 | J10: =$S$8*I10/1000 -> 1.321992 | L10: =K10*S$6/1000 -> 0 | M10: =K10*S$8/1000 -> 0 | N10: =K10*S$7/1000 -> 0 | O10: =I10-K10 -> 3 | P10: =$S$8*O10/1000 -> 1.321992
B11: 3 | D11: =+O10 -> 3 | E11: =$S$8*D11/1000 -> 1.321992 | G11: 3 | H11: =$S$8*G11/1000 -> 1.321992 | I11: =D11+G11 -> 6 | J11: =$S$8*I11/1000 -> 2.643984 | L11: =K11*S$6/1000 -> 0 | M11: =K11*S$8/1000 -> 0 | N11: =K11*S$7/1000 -> 0 | O11: =I11-K11 -> 6 | P11: =$S$8*O11/1000 -> 2.643984
B12: 4 | D12: =+O11 -> 6 | E12: =$S$8*D12/1000 -> 2.643984 | G12: 3 | H12: =$S$8*G12/1000 -> 1.321992 | I12: =D12+G12 -> 9 | J12: =$S$8*I12/1000 -> 3.965976 | L12: =K12*S$6/1000 -> 0 | M12: =K12*S$8/1000 -> 0 | N12: =K12*S$7/1000 -> 0 | O12: =I12-K12 -> 9 | P12: =$S$8*O12/1000 -> 3.965976
B13: 5 | D13: =+O12 -> 9 | E13: =$S$8*D13/1000 -> 3.965976 | G13: 8 | H13: =$S$8*G13/1000 -> 3.525312 | I13: =D13+G13 -> 17 | J13: =$S$8*I13/1000 -> 7.491288 | K13: 12 | L13: =K13*S$6/1000 -> 5.248608 | M13: =K13*S$8/1000 -> 5.287968 | N13: =K13*S$7/1000 -> 0.03936 | O13: =I13-K13 -> 5 | P13: =$S$8*O13/1000 -> 2.20332
B14: 6 | D14: =+O13 -> 5 | E14: =$S$8*D14/1000 -> 2.20332 | G14: 6 | H14: =$S$8*G14/1000 -> 2.643984 | I14: =D14+G14 -> 11 | J14: =$S$8*I14/1000 -> 4.847304 | L14: =K14*S$6/1000 -> 0 | M14: =K14*S$8/1000 -> 0 | N14: =K14*S$7/1000 -> 0 | O14: =I14-K14 -> 11 | P14: =$S$8*O14/1000 -> 4.847304
B15: 7 | D15: =+O14 -> 11 | E15: =$S$8*D15/1000 -> 4.847304 | G15: 4 | H15: =$S$8*G15/1000 -> 1.762656 | I15: =D15+G15 -> 15 | J15: =$S$8*I15/1000 -> 6.60996 | L15: =K15*S$6/1000 -> 0 | M15: =K15*S$8/1000 -> 0 | N15: =K15*S$7/1000 -> 0 | O15: =I15-K15 -> 15 | P15: =$S$8*O15/1000 -> 6.60996
B16: 8 | D16: =+O15 -> 15 | E16: =$S$8*D16/1000 -> 6.60996 | G16: 0 | H16: =$S$8*G16/1000 -> 0 | I16: =D16+G16 -> 15 | J16: =$S$8*I16/1000 -> 6.60996 | L16: =K16*S$6/1000 -> 0 | M16: =K16*S$8/1000 -> 0 | N16: =K16*S$7/1000 -> 0 | O16: =I16-K16 -> 15 | P16: =$S$8*O16/1000 -> 6.60996
B17: 9 | D17: =+O16 -> 15 | E17: =$S$8*D17/1000 -> 6.60996 | G17: 7 | H17: =$S$8*G17/1000 -> 3.084648 | I17: =D17+G17 -> 22 | J17: =$S$8*I17/1000 -> 9.694608 | K17: 22 | L17: =K17*S$6/1000 -> 9.622448 | M17: =K17*S$8/1000 -> 9.694608 | N17: =K17*S$7/1000 -> 0.07216 | O17: =I17-K17 -> 0 | P17: =$S$8*O17/1000 -> 0
B18: 10 | D18: =+O17 -> 0 | E18: =$S$8*D18/1000 -> 0 | H18: =$S$8*G18/1000 -> 0 | I18: =D18+G18 -> 0 | J18: =$S$8*I18/1000 -> 0 | L18: =K18*S$6/1000 -> 0 | M18: =K18*S$8/1000 -> 0 | N18: =K18*S$7/1000 -> 0 | O18: =I18-K18 -> 0 | P18: =$S$8*O18/1000 -> 0
B19: 11 | D19: =+O18 -> 0 | E19: =$S$8*D19/1000 -> 0 | H19: =$S$8*G19/1000 -> 0 | I19: =D19+G19 -> 0 | J19: =$S$8*I19/1000 -> 0 | L19: =K19*S$6/1000 -> 0 | M19: =K19*S$8/1000 -> 0 | N19: =K19*S$7/1000 -> 0 | O19: =I19-K19 -> 0 | P19: =$S$8*O19/1000 -> 0
B20: 12 | D20: =+O19 -> 0 | E20: =$S$8*D20/1000 -> 0 | G20: 2 | H20: =$S$8*G20/1000 -> 0.881328 | I20: =D20+G20 -> 2 | J20: =$S$8*I20/1000 -> 0.881328 | L20: =K20*S$6/1000 -> 0 | M20: =K20*S$8/1000 -> 0 | N20: =K20*S$7/1000 -> 0 | O20: =I20-K20 -> 2 | P20: =$S$8*O20/1000 -> 0.881328
B21: 13 | D21: =+O20 -> 2 | E21: =$S$8*D21/1000 -> 0.881328 | H21: =$S$8*G21/1000 -> 0 | I21: =D21+G21 -> 2 | J21: =$S$8*I21/1000 -> 0.881328 | L21: =K21*S$6/1000 -> 0 | M21: =K21*S$8/1000 -> 0 | N21: =K21*S$7/1000 -> 0 | O21: =I21-K21 -> 2 | P21: =$S$8*O21/1000 -> 0.881328
B22: 14 | D22: =+O21 -> 2 | E22: =$S$8*D22/1000 -> 0.881328 | H22: =$S$8*G22/1000 -> 0 | I22: =D22+G22 -> 2 | J22: =$S$8*I22/1000 -> 0.881328 | L22: =K22*S$6/1000 -> 0 | M22: =K22*S$8/1000 -> 0 | N22: =K22*S$7/1000 -> 0 | O22: =I22-K22 -> 2 | P22: =$S$8*O22/1000 -> 0.881328
B23: 15 | D23: =+O22 -> 2 | E23: =$S$8*D23/1000 -> 0.881328 | H23: =$S$8*G23/1000 -> 0 | I23: =D23+G23 -> 2 | J23: =$S$8*I23/1000 -> 0.881328 | L23: =K23*S$6/1000 -> 0 | M23: =K23*S$8/1000 -> 0 | N23: =K23*S$7/1000 -> 0 | O23: =I23-K23 -> 2 | P23: =$S$8*O23/1000 -> 0.881328
B24: 16 | D24: =+O23 -> 2 | E24: =$S$8*D24/1000 -> 0.881328 | G24: 7 | H24: =$S$8*G24/1000 -> 3.084648 | I24: =D24+G24 -> 9 | J24: =$S$8*I24/1000 -> 3.965976 | K24: 5 | L24: =K24*S$6/1000 -> 2.18692 | M24: =K24*S$8/1000 -> 2.20332 | N24: =K24*S$7/1000 -> 0.0164 | O24: =I24-K24 -> 4 | P24: =$S$8*O24/1000 -> 1.762656
B25: 17 | D25: =+O24 -> 4 | E25: =$S$8*D25/1000 -> 1.762656 | H25: =$S$8*G25/1000 -> 0 | I25: =D25+G25 -> 4 | J25: =$S$8*I25/1000 -> 1.762656 | L25: =K25*S$6/1000 -> 0 | M25: =K25*S$8/1000 -> 0 | N25: =K25*S$7/1000 -> 0 | O25: =I25-K25 -> 4 | P25: =$S$8*O25/1000 -> 1.762656
B26: 18 | D26: =+O25 -> 4 | E26: =$S$8*D26/1000 -> 1.762656 | H26: =$S$8*G26/1000 -> 0 | I26: =D26+G26 -> 4 | J26: =$S$8*I26/1000 -> 1.762656 | L26: =K26*S$6/1000 -> 0 | M26: =K26*S$8/1000 -> 0 | N26: =K26*S$7/1000 -> 0 | O26: =I26-K26 -> 4 | P26: =$S$8*O26/1000 -> 1.762656
B27: 19 | D27: =+O26 -> 4 | E27: =$S$8*D27/1000 -> 1.762656 | H27: =$S$8*G27/1000 -> 0 | I27: =D27+G27 -> 4 | J27: =$S$8*I27/1000 -> 1.762656 | L27: =K27*S$6/1000 -> 0 | M27: =K27*S$8/1000 -> 0 | N27: =K27*S$7/1000 -> 0 | O27: =I27-K27 -> 4 | P27: =$S$8*O27/1000 -> 1.762656
B28: 20 | D28: =+O27 -> 4 | E28: =$S$8*D28/1000 -> 1.762656 | H28: =$S$8*G28/1000 -> 0 | I28: =D28+G28 -> 4 | J28: =$S$8*I28/1000 -> 1.762656 | L28: =K28*S$6/1000 -> 0 | M28: =K28*S$8/1000 -> 0 | N28: =K28*S$7/1000 -> 0 | O28: =I28-K28 -> 4 | P28: =$S$8*O28/1000 -> 1.762656
B29: 21 | D29: =+O28 -> 4 | E29: =$S$8*D29/1000 -> 1.762656 | H29: =$S$8*G29/1000 -> 0 | I29: =D29+G29 -> 4 | J29: =$S$8*I29/1000 -> 1.762656 | L29: =K29*S$6/1000 -> 0 | M29: =K29*S$8/1000 -> 0 | N29: =K29*S$7/1000 -> 0 | O29: =I29-K29 -> 4 | P29: =$S$8*O29/1000 -> 1.762656
B30: 22 | D30: =+O29 -> 4 | E30: =$S$8*D30/1000 -> 1.762656 | G30: 0 | H30: =$S$8*G30/1000 -> 0 | I30: =D30+G30 -> 4 | J30: =$S$8*I30/1000 -> 1.762656 | L30: =K30*S$6/1000 -> 0 | M30: =K30*S$8/1000 -> 0 | N30: =K30*S$7/1000 -> 0 | O30: =I30-K30 -> 4 | P30: =$S$8*O30/1000 -> 1.762656
B31: 23 | D31: =+O30 -> 4 | E31: =$S$8*D31/1000 -> 1.762656 | G31: 8 | H31: =$S$8*G31/1000 -> 3.525312 | I31: =D31+G31 -> 12 | J31: =$S$8*I31/1000 -> 5.287968 | L31: =K31*S$6/1000 -> 0 | M31: =K31*S$8/1000 -> 0 | N31: =K31*S$7/1000 -> 0 | O31: =I31-K31 -> 12 | P31: =$S$8*O31/1000 -> 5.287968
B32: 24 | D32: =+O31 -> 12 | E32: =$S$8*D32/1000 -> 5.287968 | G32: 5 | H32: =$S$8*G32/1000 -> 2.20332 | I32: =D32+G32 -> 17 | J32: =$S$8*I32/1000 -> 7.491288 | L32: =K32*S$6/1000 -> 0 | M32: =K32*S$8/1000 -> 0 | N32: =K32*S$7/1000 -> 0 | O32: =I32-K32 -> 17 | P32: =$S$8*O32/1000 -> 7.491288
B33: 25 | D33: =+O32 -> 17 | E33: =$S$8*D33/1000 -> 7.491288 | H33: =$S$8*G33/1000 -> 0 | I33: =D33+G33 -> 17 | J33: =$S$8*I33/1000 -> 7.491288 | L33: =K33*S$6/1000 -> 0 | M33: =K33*S$8/1000 -> 0 | N33: =K33*S$7/1000 -> 0 | O33: =I33-K33 -> 17 | P33: =$S$8*O33/1000 -> 7.491288
B34: 26 | D34: =+O33 -> 17 | E34: =$S$8*D34/1000 -> 7.491288 | G34: 3 | H34: =$S$8*G34/1000 -> 1.321992 | I34: =D34+G34 -> 20 | J34: =$S$8*I34/1000 -> 8.81328 | L34: =K34*S$6/1000 -> 0 | M34: =K34*S$8/1000 -> 0 | N34: =K34*S$7/1000 -> 0 | O34: =I34-K34 -> 20 | P34: =$S$8*O34/1000 -> 8.81328
B35: 27 | D35: =+O34 -> 20 | E35: =$S$8*D35/1000 -> 8.81328 | G35: 6 | H35: =$S$8*G35/1000 -> 2.643984 | I35: =D35+G35 -> 26 | J35: =$S$8*I35/1000 -> 11.457264 | K35: 22 | L35: =K35*S$6/1000 -> 9.622448 | M35: =K35*S$8/1000 -> 9.694608 | N35: =K35*S$7/1000 -> 0.07216 | O35: =I35-K35 -> 4 | P35: =$S$8*O35/1000 -> 1.762656
B36: 28 | D36: =+O35 -> 4 | E36: =$S$8*D36/1000 -> 1.762656 | H36: =$S$8*G36/1000 -> 0 | I36: =D36+G36 -> 4 | J36: =$S$8*I36/1000 -> 1.762656 | L36: =K36*S$6/1000 -> 0 | M36: =K36*S$8/1000 -> 0 | N36: =K36*S$7/1000 -> 0 | O36: =I36-K36 -> 4 | P36: =$S$8*O36/1000 -> 1.762656
B37: 29 | D37: =+O36 -> 4 | E37: =$S$8*D37/1000 -> 1.762656 | G37: 2 | H37: =$S$8*G37/1000 -> 0.881328 | I37: =D37+G37 -> 6 | J37: =$S$8*I37/1000 -> 2.643984 | L37: =K37*S$6/1000 -> 0 | M37: =K37*S$8/1000 -> 0 | N37: =K37*S$7/1000 -> 0 | O37: =I37-K37 -> 6 | P37: =$S$8*O37/1000 -> 2.643984
B38: 30 | D38: =+O37 -> 6 | E38: =$S$8*D38/1000 -> 2.643984 | G38: 9 | H38: =$S$8*G38/1000 -> 3.965976 | I38: =D38+G38 -> 15 | J38: =$S$8*I38/1000 -> 6.60996 | L38: =K38*S$6/1000 -> 0 | M38: =K38*S$8/1000 -> 0 | N38: =K38*S$7/1000 -> 0 | O38: =I38-K38 -> 15 | P38: =$S$8*O38/1000 -> 6.60996
B39: 31 | D39: =+O38 -> 15 | E39: =$S$8*D39/1000 -> 6.60996 | G39: 3 | H39: =$S$8*G39/1000 -> 1.321992 | I39: =D39+G39 -> 18 | J39: =$S$8*I39/1000 -> 7.931952 | L39: =K39*S$6/1000 -> 0 | M39: =K39*S$8/1000 -> 0 | N39: =K39*S$7/1000 -> 0 | O39: =I39-K39 -> 18 | P39: =$S$8*O39/1000 -> 7.931952
B40: TOTAL | F40: =SUM(F9:F39) -> 0 | G40: =SUM(G9:G39) -> 79 | H40: =SUM(H9:H39) -> 34.812456 | K40: =SUM(K9:K39) -> 101 | L40: =SUM(L9:L39) -> 44.175784 | M40: =SUM(M9:M39) -> 44.507064 | N40: =SUM(N9:N39) -> 0.33128 | R40: 38 | S40: 8.12 | U40: 40 | V40: 28.35 | W40: 200 | X40: 2000
U41: =R40*S40/U40*V40*X40/1000 -> 437.3838
B42: PACK SHEET | G42: =G40*S7/1000 -> 0.25912 | H42: =+G40*S6/1000 -> 34.553336 | J42: DESPATCH PACKSHEET | L42: =K40*S7/1000 -> 0.33128 | S42: 0.75 | U42: =U41*S42% -> 3.2803785
U43: =U41+U42 -> 440.66418

Sheet 44-8.12 OZ (2)
B2: STOCK CARD- REF.NO
B3: THE EMPIRE JUTE MILL | R3: HESSIAN
B4: HESSIAN CLOTH 44-8.12 OZ/40 | R4: SACKING
A5: NATURE OF PACKING :- 1/B 1500 YDS | R5: YARN
B6: DATE | D6: OPENING BALANCE | G6: RECEIPT | I6: TOTAL | K6: ISSUES | M6: GROSS WT | O6: CLOSING BALLACE | Q6: REMARKS | R6: NET WGT. PER BALE | S6: =44*8.12/40*28.35*1500/1000 -> 379.8333
D7: NO.OF | E7: WEIGHT IN | G7: NO.OF | H7: WEIGHT IN | I7: NO.OF | J7: WEIGHT IN | K7: NO.OF | L7: NET WT | O7: NO.OF | P7: WEIGHT IN | R7: P.SHEET WGT | S7: =S6*0.75% -> 2.8487498
D8: BALE | E8: KGS | G8: BALE | H8: KGS | I8: BALE | J8: KGS | K8: BALE | L8: KGS | N8: PACK SHEET | O8: BALE | P8: KGS | R8: TOTAL WGT | S8: =S6+S7 -> 382.68205
B9: 1 | E9: =$S$8*D9/1000 -> 0 | H9: =$S$8*G9/1000 -> 0 | I9: =D9+G9 -> 0 | J9: =$S$8*I9/1000 -> 0 | L9: =K9*S$6/1000 -> 0 | M9: =K9*S$8/1000 -> 0 | N9: =K9*S$7/1000 -> 0 | O9: =I9-K9 -> 0 | P9: =$S$8*O9/1000 -> 0
B10: 2 | D10: =+O9 -> 0 | E10: =$S$8*D10/1000 -> 0 | H10: =$S$8*G10/1000 -> 0 | I10: =D10+G10 -> 0 | J10: =$S$8*I10/1000 -> 0 | L10: =K10*S$6/1000 -> 0 | M10: =K10*S$8/1000 -> 0 | N10: =K10*S$7/1000 -> 0 | O10: =I10-K10 -> 0 | P10: =$S$8*O10/1000 -> 0
B11: 3 | D11: =+O10 -> 0 | E11: =$S$8*D11/1000 -> 0 | H11: =$S$8*G11/1000 -> 0 | I11: =D11+G11 -> 0 | J11: =$S$8*I11/1000 -> 0 | L11: =K11*S$6/1000 -> 0 | M11: =K11*S$8/1000 -> 0 | N11: =K11*S$7/1000 -> 0 | O11: =I11-K11 -> 0 | P11: =$S$8*O11/1000 -> 0
B12: 4 | D12: =+O11 -> 0 | E12: =$S$8*D12/1000 -> 0 | H12: =$S$8*G12/1000 -> 0 | I12: =D12+G12 -> 0 | J12: =$S$8*I12/1000 -> 0 | L12: =K12*S$6/1000 -> 0 | M12: =K12*S$8/1000 -> 0 | N12: =K12*S$7/1000 -> 0 | O12: =I12-K12 -> 0 | P12: =$S$8*O12/1000 -> 0
B13: 5 | D13: =+O12 -> 0 | E13: =$S$8*D13/1000 -> 0 | H13: =$S$8*G13/1000 -> 0 | I13: =D13+G13 -> 0 | J13: =$S$8*I13/1000 -> 0 | L13: =K13*S$6/1000 -> 0 | M13: =K13*S$8/1000 -> 0 | N13: =K13*S$7/1000 -> 0 | O13: =I13-K13 -> 0 | P13: =$S$8*O13/1000 -> 0
B14: 6 | D14: =+O13 -> 0 | E14: =$S$8*D14/1000 -> 0 | H14: =$S$8*G14/1000 -> 0 | I14: =D14+G14 -> 0 | J14: =$S$8*I14/1000 -> 0 | L14: =K14*S$6/1000 -> 0 | M14: =K14*S$8/1000 -> 0 | N14: =K14*S$7/1000 -> 0 | O14: =I14-K14 -> 0 | P14: =$S$8*O14/1000 -> 0
B15: 7 | D15: =+O14 -> 0 | E15: =$S$8*D15/1000 -> 0 | H15: =$S$8*G15/1000 -> 0 | I15: =D15+G15 -> 0 | J15: =$S$8*I15/1000 -> 0 | L15: =K15*S$6/1000 -> 0 | M15: =K15*S$8/1000 -> 0 | N15: =K15*S$7/1000 -> 0 | O15: =I15-K15 -> 0 | P15: =$S$8*O15/1000 -> 0
B16: 8 | D16: =+O15 -> 0 | E16: =$S$8*D16/1000 -> 0 | H16: =$S$8*G16/1000 -> 0 | I16: =D16+G16 -> 0 | J16: =$S$8*I16/1000 -> 0 | L16: =K16*S$6/1000 -> 0 | M16: =K16*S$8/1000 -> 0 | N16: =K16*S$7/1000 -> 0 | O16: =I16-K16 -> 0 | P16: =$S$8*O16/1000 -> 0
B17: 9 | D17: =+O16 -> 0 | E17: =$S$8*D17/1000 -> 0 | H17: =$S$8*G17/1000 -> 0 | I17: =D17+G17 -> 0 | J17: =$S$8*I17/1000 -> 0 | L17: =K17*S$6/1000 -> 0 | M17: =K17*S$8/1000 -> 0 | N17: =K17*S$7/1000 -> 0 | O17: =I17-K17 -> 0 | P17: =$S$8*O17/1000 -> 0
B18: 10 | D18: =+O17 -> 0 | E18: =$S$8*D18/1000 -> 0 | H18: =$S$8*G18/1000 -> 0 | I18: =D18+G18 -> 0 | J18: =$S$8*I18/1000 -> 0 | L18: =K18*S$6/1000 -> 0 | M18: =K18*S$8/1000 -> 0 | N18: =K18*S$7/1000 -> 0 | O18: =I18-K18 -> 0 | P18: =$S$8*O18/1000 -> 0
B19: 11 | D19: =+O18 -> 0 | E19: =$S$8*D19/1000 -> 0 | H19: =$S$8*G19/1000 -> 0 | I19: =D19+G19 -> 0 | J19: =$S$8*I19/1000 -> 0 | L19: =K19*S$6/1000 -> 0 | M19: =K19*S$8/1000 -> 0 | N19: =K19*S$7/1000 -> 0 | O19: =I19-K19 -> 0 | P19: =$S$8*O19/1000 -> 0
B20: 12 | D20: =+O19 -> 0 | E20: =$S$8*D20/1000 -> 0 | H20: =$S$8*G20/1000 -> 0 | I20: =D20+G20 -> 0 | J20: =$S$8*I20/1000 -> 0 | L20: =K20*S$6/1000 -> 0 | M20: =K20*S$8/1000 -> 0 | N20: =K20*S$7/1000 -> 0 | O20: =I20-K20 -> 0 | P20: =$S$8*O20/1000 -> 0
B21: 13 | D21: =+O20 -> 0 | E21: =$S$8*D21/1000 -> 0 | H21: =$S$8*G21/1000 -> 0 | I21: =D21+G21 -> 0 | J21: =$S$8*I21/1000 -> 0 | L21: =K21*S$6/1000 -> 0 | M21: =K21*S$8/1000 -> 0 | N21: =K21*S$7/1000 -> 0 | O21: =I21-K21 -> 0 | P21: =$S$8*O21/1000 -> 0
... B28: 20 | D28: =+O27 -> 0 | E28: =$S$8*D28/1000 -> 0 | H28: =$S$8*G28/1000 -> 0 | I28: =D28+G28 -> 0 | J28: =$S$8*I28/1000 -> 0 | L28: =K28*S$6/1000 -> 0 | M28: =K28*S$8/1000 -> 0 | N28: =K28*S$7/1000 -> 0 | O28: =I28-K28 -> 0 | P28: =$S$8*O28/1000 -> 0
B29: 21 | D29: =+O28 -> 0 | E29: =$S$8*D29/1000 -> 0 | H29: =$S$8*G29/1000 -> 0 | I29: =D29+G29 -> 0 | J29: 0.222 | L29: =K29*S$6/1000 -> 0 | M29: =K29*S$8/1000 -> 0 | N29: =K29*S$7/1000 -> 0 | O29: =I29-K29 -> 0 | P29: =$S$8*O29/1000 -> 0
B30: 22 | D30: =+O29 -> 0 | E30: =$S$8*D30/1000 -> 0 | H30: =$S$8*G30/1000 -> 0 | I30: =D30+G30 -> 0 | J30: =$S$8*I30/1000 -> 0 | L30: =K30*S$6/1000 -> 0 | M30: =K30*S$8/1000 -> 0 | N30: =K30*S$7/1000 -> 0 | O30: =I30-K30 -> 0 | P30: =$S$8*O30/1000 -> 0
B31: 23 | D31: =+O30 -> 0 | E31: =$S$8*D31/1000 -> 0 | H31: =$S$8*G31/1000 -> 0 | I31: =D31+G31 -> 0 | J31: =$S$8*I31/1000 -> 0 | L31: =K31*S$6/1000 -> 0 | M31: =K31*S$8/1000 -> 0 | N31: =K31*S$7/1000 -> 0 | O31: =I31-K31 -> 0 | P31: =$S$8*O31/1000 -> 0
B32: 24 | D32: =+O31 -> 0 | E32: =$S$8*D32/1000 -> 0 | H32: =$S$8*G32/1000 -> 0 | I32: =D32+G32 -> 0 | J32: =$S$8*I32/1000 -> 0 | L32: =K32*S$6/1000 -> 0 | M32: =K32*S$8/1000 -> 0 | N32: =K32*S$7/1000 -> 0 | O32: =I32-K32 -> 0 | P32: =$S$8*O32/1000 -> 0
B33: 25 | D33: =+O32 -> 0 | E33: =$S$8*D33/1000 -> 0 | H33: =$S$8*G33/1000 -> 0 | I33: =D33+G33 -> 0 | J33: =$S$8*I33/1000 -> 0 | L33: =K33*S$6/1000 -> 0 | M33: =K33*S$8/1000 -> 0 | N33: =K33*S$7/1000 -> 0 | O33: =I33-K33 -> 0 | P33: =$S$8*O33/1000 -> 0
B34: 26 | D34: =+O33 -> 0 | E34: =$S$8*D34/1000 -> 0 | H34: =$S$8*G34/1000 -> 0 | I34: =D34+G34 -> 0 | J34: =$S$8*I34/1000 -> 0 | L34: =K34*S$6/1000 -> 0 | M34: =K34*S$8/1000 -> 0 | N34: =K34*S$7/1000 -> 0 | O34: =I34-K34 -> 0 | P34: =$S$8*O34/1000 -> 0
B35: 27 | D35: =+O34 -> 0 | E35: =$S$8*D35/1000 -> 0 | H35: =$S$8*G35/1000 -> 0 | I35: =D35+G35 -> 0 | J35: =$S$8*I35/1000 -> 0 | L35: =K35*S$6/1000 -> 0 | M35: =K35*S$8/1000 -> 0 | N35: =K35*S$7/1000 -> 0 | O35: =I35-K35 -> 0 | P35: =$S$8*O35/1000 -> 0
B36: 28 | D36: =+O35 -> 0 | E36: =$S$8*D36/1000 -> 0 | H36: =$S$8*G36/1000 -> 0 | I36: =D36+G36 -> 0 | J36: =$S$8*I36/1000 -> 0 | L36: =K36*S$6/1000 -> 0 | M36: =K36*S$8/1000 -> 0 | N36: =K36*S$7/1000 -> 0 | O36: =I36-K36 -> 0 | P36: =$S$8*O36/1000 -> 0
B37: 29 | D37: =+O36 -> 0 | E37: =$S$8*D37/1000 -> 0 | H37: =$S$8*G37/1000 -> 0 | I37: =D37+G37 -> 0 | J37: =$S$8*I37/1000 -> 0 | L37: =K37*S$6/1000 -> 0 | M37: =K37*S$8/1000 -> 0 | N37: =K37*S$7/1000 -> 0 | O37: =I37-K37 -> 0 | P37: =$S$8*O37/1000 -> 0
B38: 30 | D38: =+O37 -> 0 | E38: =$S$8*D38/1000 -> 0 | H38: =$S$8*G38/1000 -> 0 | I38: =D38+G38 -> 0 | J38: =$S$8*I38/1000 -> 0 | L38: =K38*S$6/1000 -> 0 | M38: =K38*S$8/1000 -> 0 | N38: =K38*S$7/1000 -> 0 | O38: =I38-K38 -> 0 | P38: =$S$8*O38/1000 -> 0
B39: 31 | D39: =+O38 -> 0 | E39: =$S$8*D39/1000 -> 0 | H39: =$S$8*G39/1000 -> 0 | I39: =D39+G39 -> 0 | J39: =$S$8*I39/1000 -> 0 | L39: =K39*S$6/1000 -> 0 | M39: =K39*S$8/1000 -> 0 | N39: =K39*S$7/1000 -> 0 | O39: =I39-K39 -> 0 | P39: =$S$8*O39/1000 -> 0
B40: TOTAL | F40: =SUM(F9:F39) -> 0 | G40: =SUM(G9:G39) -> 0 | H40: =SUM(H9:H39) -> 0 | K40: =SUM(K9:K39) -> 0 | L40: =SUM(L9:L39) -> 0 | N40: =SUM(N9:N39) -> 0
B42: PACK SHEET | G42: =G40*S7/1000 -> 0 | H42: =+G40*S6/1000 -> 0 | J42: DESPATCH PACKSHEET | L42: =K40*S7/1000 -> 0

Sheet 44-8.12 OZ
B2: STOCK CARD- REF.NO
B3: THE EMPIRE JUTE MILL | R3: HESSIAN
B4: HESSIAN CLOTH 44-8.12 OZ | R4: SACKING
A5: NATURE OF PACKING :- 1/B 1000 YDS | R5: YARN
B6: DATE | D6: OPENING BALANCE | G6: RECEIPT | I6: TOTAL | K6: ISSUES | M6: GROSS WT | O6: CLOSING BALLACE | Q6: REMARKS | R6: NET WGT. PER BALE | S6: =44*8.12/40*28.35*1000/1000 -> 253.2222
D7: NO.OF | E7: WEIGHT IN | G7: NO.OF | H7: WEIGHT IN | I7: NO.OF | J7: WEIGHT IN | K7: NO.OF | L7: NET WT | O7: NO.OF | P7: WEIGHT IN | R7: P.SHEET WGT | S7: =S6*0.75% -> 1.8991665
D8: BALE | E8: KGS | G8: BALE | H8: KGS | I8: BALE | J8: KGS | K8: BALE | L8: KGS | N8: PACK SHEET | O8: BALE | P8: KGS | R8: TOTAL WGT | S8: =S6+S7 -> 255.12137
B9: 1 | E9: =$S$8*D9/1000 -> 0 | H9: =$S$8*G9/1000 -> 0 | I9: =D9+G9 -> 0 | J9: =$S$8*I9/1000 -> 0 | L9: =K9*S$6/1000 -> 0 | M9: =K9*S$8/1000 -> 0 | N9: =K9*S$7/1000 -> 0 | O9: =I9-K9 -> 0 | P9: =$S$8*O9/1000 -> 0
B10: 2 | D10: =+O9 -> 0 | E10: =$S$8*D10/1000 -> 0 | H10: =$S$8*G10/1000 -> 0 | I10: =D10+G10 -> 0 | J10: =$S$8*I10/1000 -> 0 | L10: =K10*S$6/1000 -> 0 | M10: =K10*S$8/1000 -> 0 | N10: =K10*S$7/1000 -> 0 | O10: =I10-K10 -> 0 | P10: =$S$8*O10/1000 -> 0
B11: 3 | D11: =+O10 -> 0 | E11: =$S$8*D11/1000 -> 0 | H11: =$S$8*G11/1000 -> 0 | I11: =D11+G11 -> 0 | J11: =$S$8*I11/1000 -> 0 | L11: =K11*S$6/1000 -> 0 | M11: =K11*S$8/1000 -> 0 | N11: =K11*S$7/1000 -> 0 | O11: =I11-K11 -> 0 | P11: =$S$8*O11/1000 -> 0
B12: 4 | D12: =+O11 -> 0 | E12: =$S$8*D12/1000 -> 0 | H12: =$S$8*G12/1000 -> 0 | I12: =D12+G12 -> 0 | J12: =$S$8*I12/1000 -> 0 | L12: =K12*S$6/1000 -> 0 | M12: =K12*S$8/1000 -> 0 | N12: =K12*S$7/1000 -> 0 | O12: =I12-K12 -> 0 | P12: =$S$8*O12/1000 -> 0
B13: 5 | D13: =+O12 -> 0 | E13: =$S$8*D13/1000 -> 0 | H13: =$S$8*G13/1000 -> 0 | I13: =D13+G13 -> 0 | J13: =$S$8*I13/1000 -> 0 | L13: =K13*S$6/1000 -> 0 | M13: =K13*S$8/1000 -> 0 | N13: =K13*S$7/1000 -> 0 | O13: =I13-K13 -> 0 | P13: =$S$8*O13/1000 -> 0
B14: 6 | D14: =+O13 -> 0 | E14: =$S$8*D14/1000 -> 0 | H14: =$S$8*G14/1000 -> 0 | I14: =D14+G14 -> 0 | J14: =$S$8*I14/1000 -> 0 | L14: =K14*S$6/1000 -> 0 | M14: =K14*S$8/1000 -> 0 | N14: =K14*S$7/1000 -> 0 | O14: =I14-K14 -> 0 | P14: =$S$8*O14/1000 -> 0
B15: 7 | D15: =+O14 -> 0 | E15: =$S$8*D15/1000 -> 0 | H15: =$S$8*G15/1000 -> 0 | I15: =D15+G15 -> 0 | J15: =$S$8*I15/1000 -> 0 | L15: =K15*S$6/1000 -> 0 | M15: =K15*S$8/1000 -> 0 | N15: =K15*S$7/1000 -> 0 | O15: =I15-K15 -> 0 | P15: =$S$8*O15/1000 -> 0
B16: 8 | D16: =+O15 -> 0 | E16: =$S$8*D16/1000 -> 0 | H16: =$S$8*G16/1000 -> 0 | I16: =D16+G16 -> 0 | J16: =$S$8*I16/1000 -> 0 | L16: =K16*S$6/1000 -> 0 | M16: =K16*S$8/1000 -> 0 | N16: =K16*S$7/1000 -> 0 | O16: =I16-K16 -> 0 | P16: =$S$8*O16/1000 -> 0
B17: 9 | D17: =+O16 -> 0 | E17: =$S$8*D17/1000 -> 0 | H17: =$S$8*G17/1000 -> 0 | I17: =D17+G17 -> 0 | J17: =$S$8*I17/1000 -> 0 | L17: =K17*S$6/1000 -> 0 | M17: =K17*S$8/1000 -> 0 | N17: =K17*S$7/1000 -> 0 | O17: =I17-K17 -> 0 | P17: =$S$8*O17/1000 -> 0
B18: 10 | D18: =+O17 -> 0 | E18: =$S$8*D18/1000 -> 0 | H18: =$S$8*G18/1000 -> 0 | I18: =D18+G18 -> 0 | J18: =$S$8*I18/1000 -> 0 | L18: =K18*S$6/1000 -> 0 | M18: =K18*S$8/1000 -> 0 | N18: =K18*S$7/1000 -> 0 | O18: =I18-K18 -> 0 | P18: =$S$8*O18/1000 -> 0
B19: 11 | D19: =+O18 -> 0 | E19: =$S$8*D19/1000 -> 0 | H19: =$S$8*G19/1000 -> 0 | I19: =D19+G19 -> 0 | J19: =$S$8*I19/1000 -> 0 | L19: =K19*S$6/1000 -> 0 | M19: =K19*S$8/1000 -> 0 | N19: =K19*S$7/1000 -> 0 | O19: =I19-K19 -> 0 | P19: =$S$8*O19/1000 -> 0
B20: 12 | D20: =+O19 -> 0 | E20: =$S$8*D20/1000 -> 0 | H20: =$S$8*G20/1000 -> 0 | I20: =D20+G20 -> 0 | J20: =$S$8*I20/1000 -> 0 | L20: =K20*S$6/1000 -> 0 | M20: =K20*S$8/1000 -> 0 | N20: =K20*S$7/1000 -> 0 | O20: =I20-K20 -> 0 | P20: =$S$8*O20/1000 -> 0
B21: 13 | D21: =+O20 -> 0 | E21: =$S$8*D21/1000 -> 0 | H21: =$S$8*G21/1000 -> 0 | I21: =D21+G21 -> 0 | J21: =$S$8*I21/1000 -> 0 | L21: =K21*S$6/1000 -> 0 | M21: =K21*S$8/1000 -> 0 | N21: =K21*S$7/1000 -> 0 | O21: =I21-K21 -> 0 | P21: =$S$8*O21/1000 -> 0
... B28: 20 | D28: =+O27 -> 0 | E28: =$S$8*D28/1000 -> 0 | H28: =$S$8*G28/1000 -> 0 | I28: =D28+G28 -> 0 | J28: =$S$8*I28/1000 -> 0 | L28: =K28*S$6/1000 -> 0 | M28: =K28*S$8/1000 -> 0 | N28: =K28*S$7/1000 -> 0 | O28: =I28-K28 -> 0 | P28: =$S$8*O28/1000 -> 0
B29: 21 | D29: =+O28 -> 0 | E29: =$S$8*D29/1000 -> 0 | H29: =$S$8*G29/1000 -> 0 | I29: =D29+G29 -> 0 | J29: 0.222 | L29: =K29*S$6/1000 -> 0 | M29: =K29*S$8/1000 -> 0 | N29: =K29*S$7/1000 -> 0 | O29: =I29-K29 -> 0 | P29: =$S$8*O29/1000 -> 0
B30: 22 | D30: =+O29 -> 0 | E30: =$S$8*D30/1000 -> 0 | H30: =$S$8*G30/1000 -> 0 | I30: =D30+G30 -> 0 | J30: =$S$8*I30/1000 -> 0 | L30: =K30*S$6/1000 -> 0 | M30: =K30*S$8/1000 -> 0 | N30: =K30*S$7/1000 -> 0 | O30: =I30-K30 -> 0 | P30: =$S$8*O30/1000 -> 0
B31: 23 | D31: =+O30 -> 0 | E31: =$S$8*D31/1000 -> 0 | H31: =$S$8*G31/1000 -> 0 | I31: =D31+G31 -> 0 | J31: =$S$8*I31/1000 -> 0 | L31: =K31*S$6/1000 -> 0 | M31: =K31*S$8/1000 -> 0 | N31: =K31*S$7/1000 -> 0 | O31: =I31-K31 -> 0 | P31: =$S$8*O31/1000 -> 0
B32: 24 | D32: =+O31 -> 0 | E32: =$S$8*D32/1000 -> 0 | H32: =$S$8*G32/1000 -> 0 | I32: =D32+G32 -> 0 | J32: =$S$8*I32/1000 -> 0 | L32: =K32*S$6/1000 -> 0 | M32: =K32*S$8/1000 -> 0 | N32: =K32*S$7/1000 -> 0 | O32: =I32-K32 -> 0 | P32: =$S$8*O32/1000 -> 0
B33: 25 | D33: =+O32 -> 0 | E33: =$S$8*D33/1000 -> 0 | H33: =$S$8*G33/1000 -> 0 | I33: =D33+G33 -> 0 | J33: =$S$8*I33/1000 -> 0 | L33: =K33*S$6/1000 -> 0 | M33: =K33*S$8/1000 -> 0 | N33: =K33*S$7/1000 -> 0 | O33: =I33-K33 -> 0 | P33: =$S$8*O33/1000 -> 0
B34: 26 | D34: =+O33 -> 0 | E34: =$S$8*D34/1000 -> 0 | H34: =$S$8*G34/1000 -> 0 | I34: =D34+G34 -> 0 | J34: =$S$8*I34/1000 -> 0 | L34: =K34*S$6/1000 -> 0 | M34: =K34*S$8/1000 -> 0 | N34: =K34*S$7/1000 -> 0 | O34: =I34-K34 -> 0 | P34: =$S$8*O34/1000 -> 0
B35: 27 | D35: =+O34 -> 0 | E35: =$S$8*D35/1000 -> 0 | H35: =$S$8*G35/1000 -> 0 | I35: =D35+G35 -> 0 | J35: =$S$8*I35/1000 -> 0 | L35: =K35*S$6/1000 -> 0 | M35: =K35*S$8/1000 -> 0 | N35: =K35*S$7/1000 -> 0 | O35: =I35-K35 -> 0 | P35: =$S$8*O35/1000 -> 0
B36: 28 | D36: =+O35 -> 0 | E36: =$S$8*D36/1000 -> 0 | H36: =$S$8*G36/1000 -> 0 | I36: =D36+G36 -> 0 | J36: =$S$8*I36/1000 -> 0 | L36: =K36*S$6/1000 -> 0 | M36: =K36*S$8/1000 -> 0 | N36: =K36*S$7/1000 -> 0 | O36: =I36-K36 -> 0 | P36: =$S$8*O36/1000 -> 0
B37: 29 | D37: =+O36 -> 0 | E37: =$S$8*D37/1000 -> 0 | H37: =$S$8*G37/1000 -> 0 | I37: =D37+G37 -> 0 | J37: =$S$8*I37/1000 -> 0 | L37: =K37*S$6/1000 -> 0 | M37: =K37*S$8/1000 -> 0 | N37: =K37*S$7/1000 -> 0 | O37: =I37-K37 -> 0 | P37: =$S$8*O37/1000 -> 0
B38: 30 | D38: =+O37 -> 0 | E38: =$S$8*D38/1000 -> 0 | H38: =$S$8*G38/1000 -> 0 | I38: =D38+G38 -> 0 | J38: =$S$8*I38/1000 -> 0 | L38: =K38*S$6/1000 -> 0 | M38: =K38*S$8/1000 -> 0 | N38: =K38*S$7/1000 -> 0 | O38: =I38-K38 -> 0 | P38: =$S$8*O38/1000 -> 0
B39: 31 | D39: =+O38 -> 0 | E39: =$S$8*D39/1000 -> 0 | H39: =$S$8*G39/1000 -> 0 | I39: =D39+G39 -> 0 | J39: =$S$8*I39/1000 -> 0 | L39: =K39*S$6/1000 -> 0 | M39: =K39*S$8/1000 -> 0 | N39: =K39*S$7/1000 -> 0 | O39: =I39-K39 -> 0 | P39: =$S$8*O39/1000 -> 0
B40: TOTAL | F40: =SUM(F9:F39) -> 0 | G40: =SUM(G9:G39) -> 0 | H40: =SUM(H9:H39) -> 0 | K40: =SUM(K9:K39) -> 0 | L40: =SUM(L9:L39) -> 0 | N40: =SUM(N9:N39) -> 0
B42: PACK SHEET | G42: =G40*S7/1000 -> 0 | H42: =+G40*S6/1000 -> 0 | J42: DESPATCH PACKSHEET | L42: =K40*S7/1000 -> 0

Sheet 40-4.5-OZ
B2: STOCK CARD- REF.NO
B3: THE EMPIRE JUTE MILL | R3: HESSIAN
B4: HESSIAN CLOTH 40-4.5-OZ | R4: SACKING
A5: NATURE OF PACKING :- 1/B 2000 YDS | R5: YARN
B6: DATE | D6: OPENING BALANCE | G6: RECEIPT | I6: TOTAL | K6: ISSUES | M6: GROSS WT | O6: CLOSING BALLACE | Q6: REMARKS | R6: NET WGT. PER BALE | S6: 255.15
D7: NO.OF | E7: WEIGHT IN | G7: NO.OF | H7: WEIGHT IN | I7: NO.OF | J7: WEIGHT IN | K7: NO.OF | L7: NET WT | O7: NO.OF | P7: WEIGHT IN | R7: P.SHEET WGT | S7: =S6*0.75% -> 1.913625
D8: BALE | E8: KGS | G8: BALE | H8: KGS | I8: BALE | J8: KGS | K8: BALE | L8: KGS | N8: PACK SHEET | O8: BALE | P8: KGS | R8: TOTAL WGT | S8: =S6+S7 -> 257.06363
B9: 1 | E9: =$S$8*D9/1000 -> 0 | H9: =$S$8*G9/1000 -> 0 | I9: =D9+G9 -> 0 | J9: =$S$8*I9/1000 -> 0 | L9: =K9*S$6/1000 -> 0 | M9: =K9*S$8/1000 -> 0 | N9: =K9*S$7/1000 -> 0 | O9: =I9-K9 -> 0 | P9: =$S$8*O9/1000 -> 0
B10: 2 | D10: =+O9 -> 0 | E10: =$S$8*D10/1000 -> 0 | H10: =$S$8*G10/1000 -> 0 | I10: =D10+G10 -> 0 | J10: =$S$8*I10/1000 -> 0 | L10: =K10*S$6/1000 -> 0 | M10: =K10*S$8/1000 -> 0 | N10: =K10*S$7/1000 -> 0 | O10: =I10-K10 -> 0 | P10: =$S$8*O10/1000 -> 0
B11: 3 | D11: =+O10 -> 0 | E11: =$S$8*D11/1000 -> 0 | H11: =$S$8*G11/1000 -> 0 | I11: =D11+G11 -> 0 | J11: =$S$8*I11/1000 -> 0 | L11: =K11*S$6/1000 -> 0 | M11: =K11*S$8/1000 -> 0 | N11: =K11*S$7/1000 -> 0 | O11: =I11-K11 -> 0 | P11: =$S$8*O11/1000 -> 0
B12: 4 | D12: =+O11 -> 0 | E12: =$S$8*D12/1000 -> 0 | H12: =$S$8*G12/1000 -> 0 | I12: =D12+G12 -> 0 | J12: =$S$8*I12/1000 -> 0 | L12: =K12*S$6/1000 -> 0 | M12: =K12*S$8/1000 -> 0 | N12: =K12*S$7/1000 -> 0 | O12: =I12-K12 -> 0 | P12: =$S$8*O12/1000 -> 0
B13: 5 | D13: =+O12 -> 0 | E13: =$S$8*D13/1000 -> 0 | H13: =$S$8*G13/1000 -> 0 | I13: =D13+G13 -> 0 | J13: =$S$8*I13/1000 -> 0 | L13: =K13*S$6/1000 -> 0 | M13: =K13*S$8/1000 -> 0 | N13: =K13*S$7/1000 -> 0 | O13: =I13-K13 -> 0 | P13: =$S$8*O13/1000 -> 0
B14: 6 | D14: =+O13 -> 0 | E14: =$S$8*D14/1000 -> 0 | H14: =$S$8*G14/1000 -> 0 | I14: =D14+G14 -> 0 | J14: =$S$8*I14/1000 -> 0 | L14: =K14*S$6/1000 -> 0 | M14: =K14*S$8/1000 -> 0 | N14: =K14*S$7/1000 -> 0 | O14: =I14-K14 -> 0 | P14: =$S$8*O14/1000 -> 0
B15: 7 | D15: =+O14 -> 0 | E15: =$S$8*D15/1000 -> 0 | H15: =$S$8*G15/1000 -> 0 | I15: =D15+G15 -> 0 | J15: =$S$8*I15/1000 -> 0 | L15: =K15*S$6/1000 -> 0 | M15: =K15*S$8/1000 -> 0 | N15: =K15*S$7/1000 -> 0 | O15: =I15-K15 -> 0 | P15: =$S$8*O15/1000 -> 0
B16: 8 | D16: =+O15 -> 0 | E16: =$S$8*D16/1000 -> 0 | H16: =$S$8*G16/1000 -> 0 | I16: =D16+G16 -> 0 | J16: =$S$8*I16/1000 -> 0 | L16: =K16*S$6/1000 -> 0 | M16: =K16*S$8/1000 -> 0 | N16: =K16*S$7/1000 -> 0 | O16: =I16-K16 -> 0 | P16: =$S$8*O16/1000 -> 0
B17: 9 | D17: =+O16 -> 0 | E17: =$S$8*D17/1000 -> 0 | H17: =$S$8*G17/1000 -> 0 | I17: =D17+G17 -> 0 | J17: =$S$8*I17/1000 -> 0 | L17: =K17*S$6/1000 -> 0 | M17: =K17*S$8/1000 -> 0 | N17: =K17*S$7/1000 -> 0 | O17: =I17-K17 -> 0 | P17: =$S$8*O17/1000 -> 0
B18: 10 | D18: =+O17 -> 0 | E18: =$S$8*D18/1000 -> 0 | H18: =$S$8*G18/1000 -> 0 | I18: =D18+G18 -> 0 | J18: =$S$8*I18/1000 -> 0 | L18: =K18*S$6/1000 -> 0 | M18: =K18*S$8/1000 -> 0 | N18: =K18*S$7/1000 -> 0 | O18: =I18-K18 -> 0 | P18: =$S$8*O18/1000 -> 0
B19: 11 | D19: =+O18 -> 0 | E19: =$S$8*D19/1000 -> 0 | H19: =$S$8*G19/1000 -> 0 | I19: =D19+G19 -> 0 | J19: =$S$8*I19/1000 -> 0 | L19: =K19*S$6/1000 -> 0 | M19: =K19*S$8/1000 -> 0 | N19: =K19*S$7/1000 -> 0 | O19: =I19-K19 -> 0 | P19: =$S$8*O19/1000 -> 0
B20: 12 | D20: =+O19 -> 0 | E20: =$S$8*D20/1000 -> 0 | H20: =$S$8*G20/1000 -> 0 | I20: =D20+G20 -> 0 | J20: =$S$8*I20/1000 -> 0 | L20: =K20*S$6/1000 -> 0 | M20: =K20*S$8/1000 -> 0 | N20: =K20*S$7/1000 -> 0 | O20: =I20-K20 -> 0 | P20: =$S$8*O20/1000 -> 0
B21: 13 | D21: =+O20 -> 0 | E21: =$S$8*D21/1000 -> 0 | H21: =$S$8*G21/1000 -> 0 | I21: =D21+G21 -> 0 | J21: =$S$8*I21/1000 -> 0 | L21: =K21*S$6/1000 -> 0 | M21: =K21*S$8/1000 -> 0 | N21: =K21*S$7/1000 -> 0 | O21: =I21-K21 -> 0 | P21: =$S$8*O21/1000 -> 0
... B39: 31 | D39: =+O38 -> 0 | E39: =$S$8*D39/1000 -> 0 | H39: =$S$8*G39/1000 -> 0 | I39: =D39+G39 -> 0 | J39: =$S$8*I39/1000 -> 0 | L39: =K39*S$6/1000 -> 0 | M39: =K39*S$8/1000 -> 0 | N39: =K39*S$7/1000 -> 0 | O39: =I39-K39 -> 0 | P39: =$S$8*O39/1000 -> 0
B40: TOTAL | F40: =SUM(F9:F39) -> 0 | G40: =SUM(G9:G39) -> 0 | H40: =SUM(H9:H39) -> 0 | K40: =SUM(K9:K39) -> 0 | L40: =SUM(L9:L39) -> 0 | N40: =SUM(N9:N39) -> 0
B42: PACK SHEET | G42: =G40*S7/1000 -> 0 | H42: =+G40*S6/1000 -> 0 | J42: DESPATCH PACKSHEET | L42: =K40*S7/1000 -> 0

Sheet 36-4.05 OZ
B2: STOCK CARD- REF.NO
B3: THE EMPIRE JUTE MILL | R3: HESSIAN
B4: DESCRIPTION OF GOODS:- H.CLOTH 36-4.05 OZ | R4: SACKING
A5: NATURE OF PACKING :- 1/B 1828.80 MTR | R5: YARN
B6: DATE | D6: OPENING BALANCE | G6: RECEIPT | I6: TOTAL | K6: ISSUES | M6: GROSS WT | O6: CLOSING BALLACE | Q6: REMARKS | R6: NET WGT. PER BALE | S6: 229.63
D7: NO.OF | E7: WEIGHT IN | G7: NO.OF | H7: WEIGHT IN | I7: NO.OF | J7: WEIGHT IN | K7: NO.OF | L7: NET WT | O7: NO.OF | P7: WEIGHT IN | R7: P.SHEET WGT | S7: =S6*0.75% -> 1.722225
D8: BALE | E8: KGS | G8: BALE | H8: KGS | I8: BALE | J8: KGS | K8: BALE | L8: KGS | N8: PACK SHEET | O8: BALE | P8: KGS | R8: TOTAL WGT | S8: =S6+S7 -> 231.35223
B9: 1 | E9: =$S$8*D9/1000 -> 0 | H9: =$S$8*G9/1000 -> 0 | I9: =D9+G9 -> 0 | J9: =$S$8*I9/1000 -> 0 | L9: =K9*S$8/1000 -> 0 | M9: =+K9*S$8/1000 -> 0 | N9: =K9*S$7/1000 -> 0 | O9: =D9+G9-K9 -> 0 | P9: =$S$8*O9/1000 -> 0 | Q9: =P9*T8/1000 -> 0
B10: 2 | E10: =$S$8*D10/1000 -> 0 | H10: =$S$8*G10/1000 -> 0 | I10: =D10+G10 -> 0 | J10: =$S$8*I10/1000 -> 0 | L10: =K10*S$8/1000 -> 0 | M10: =+K10*S$8/1000 -> 0 | N10: =K10*S$7/1000 -> 0 | O10: =D10+G10-K10 -> 0 | P10: =$S$8*O10/1000 -> 0
B11: 3 | D11: =+O10 -> 0 | E11: =$S$8*D11/1000 -> 0 | H11: =$S$8*G11/1000 -> 0 | I11: =D11+G11 -> 0 | J11: =$S$8*I11/1000 -> 0 | L11: =K11*S$8/1000 -> 0 | M11: =+K11*S$8/1000 -> 0 | N11: =K11*S$7/1000 -> 0 | O11: =D11+G11-K11 -> 0 | P11: =$S$8*O11/1000 -> 0
B12: 4 | D12: =+O11 -> 0 | E12: =$S$8*D12/1000 -> 0 | H12: =$S$8*G12/1000 -> 0 | I12: =D12+G12 -> 0 | J12: =$S$8*I12/1000 -> 0 | L12: =K12*S$6/1000 -> 0 | M12: =+K12*S$8/1000 -> 0 | N12: =K12*S$7/1000 -> 0 | O12: =D12+G12-K12 -> 0 | P12: =$S$8*O12/1000 -> 0
B13: 5 | D13: =+O12 -> 0 | E13: =$S$8*D13/1000 -> 0 | H13: =$S$8*G13/1000 -> 0 | I13: =D13+G13 -> 0 | J13: =$S$8*I13/1000 -> 0 | L13: =K13*S$6/1000 -> 0 | M13: =+K13*S$8/1000 -> 0 | N13: =K13*S$7/1000 -> 0 | O13: =D13+G13-K13 -> 0 | P13: =$S$8*O13/1000 -> 0
B14: 6 | D14: =+O13 -> 0 | E14: =$S$8*D14/1000 -> 0 | H14: =$S$8*G14/1000 -> 0 | I14: =D14+G14 -> 0 | J14: =$S$8*I14/1000 -> 0 | L14: =K14*S$6/1000 -> 0 | M14: =+K14*S$8/1000 -> 0 | N14: =K14*S$7/1000 -> 0 | O14: =D14+G14-K14 -> 0 | P14: =$S$8*O14/1000 -> 0
B15: 7 | D15: =+O14 -> 0 | E15: =$S$8*D15/1000 -> 0 | H15: =$S$8*G15/1000 -> 0 | I15: =D15+G15 -> 0 | J15: =$S$8*I15/1000 -> 0 | L15: =K15*S$6/1000 -> 0 | M15: =+K15*S$8/1000 -> 0 | N15: =K15*S$7/1000 -> 0 | O15: =D15+G15-K15 -> 0 | P15: =$S$8*O15/1000 -> 0
B16: 8 | D16: =+O15 -> 0 | E16: =$S$8*D16/1000 -> 0 | H16: =$S$8*G16/1000 -> 0 | I16: =D16+G16 -> 0 | J16: =$S$8*I16/1000 -> 0 | L16: =K16*S$6/1000 -> 0 | M16: =+K16*S$8/1000 -> 0 | N16: =K16*S$7/1000 -> 0 | O16: =D16+G16-K16 -> 0 | P16: =$S$8*O16/1000 -> 0
B17: 9 | D17: =+D16 -> 0 | E17: =$S$8*D17/1000 -> 0 | H17: =$S$8*G17/1000 -> 0 | I17: =D17+G17 -> 0 | J17: =$S$8*I17/1000 -> 0 | L17: =K17*S$6/1000 -> 0 | M17: =+K17*S$8/1000 -> 0 | N17: =K17*S$7/1000 -> 0 | O17: =D17+G17-K17 -> 0 | P17: =$S$8*O17/1000 -> 0
B18: 10 | D18: =+D17 -> 0 | E18: =$S$8*D18/1000 -> 0 | H18: =$S$8*G18/1000 -> 0 | I18: =D18+G18 -> 0 | J18: =$S$8*I18/1000 -> 0 | L18: =K18*S$6/1000 -> 0 | M18: =+K18*S$8/1000 -> 0 | N18: =K18*S$7/1000 -> 0 | O18: =D18+G18-K18 -> 0 | P18: =$S$8*O18/1000 -> 0
B19: 11 | D19: =+D18 -> 0 | E19: =$S$8*D19/1000 -> 0 | H19: =$S$8*G19/1000 -> 0 | I19: =D19+G19 -> 0 | J19: =$S$8*I19/1000 -> 0 | L19: =K19*S$6/1000 -> 0 | M19: =+K19*S$8/1000 -> 0 | N19: =K19*S$7/1000 -> 0 | O19: =D19+G19-K19 -> 0 | P19: =$S$8*O19/1000 -> 0
B20: 12 | D20: =+D19 -> 0 | E20: =$S$8*D20/1000 -> 0 | H20: =$S$8*G20/1000 -> 0 | I20: =D20+G20 -> 0 | J20: =$S$8*I20/1000 -> 0 | L20: =K20*S$6/1000 -> 0 | M20: =+K20*S$8/1000 -> 0 | N20: =K20*S$7/1000 -> 0 | O20: =D20+G20-K20 -> 0 | P20: =$S$8*O20/1000 -> 0
B21: 13 | D21: =+D20 -> 0 | E21: =$S$8*D21/1000 -> 0 | H21: =$S$8*G21/1000 -> 0 | I21: =D21+G21 -> 0 | J21: =$S$8*I21/1000 -> 0 | L21: =K21*S$6/1000 -> 0 | M21: =+K21*S$8/1000 -> 0 | N21: =K21*S$7/1000 -> 0 | O21: =D21+G21-K21 -> 0 | P21: =$S$8*O21/1000 -> 0
B22: 14 | D22: =+D21 -> 0 | E22: =$S$8*D22/1000 -> 0 | H22: =$S$8*G22/1000 -> 0 | I22: =D22+G22 -> 0 | J22: =$S$8*I22/1000 -> 0 | L22: =K22*S$6/1000 -> 0 | M22: =+K22*S$8/1000 -> 0 | N22: =K22*S$7/1000 -> 0 | O22: =D22+G22-K22 -> 0 | P22: =$S$8*O22/1000 -> 0
B23: 15 | D23: =+D22 -> 0 | E23: =$S$8*D23/1000 -> 0 | H23: =$S$8*G23/1000 -> 0 | I23: =D23+G23 -> 0 | J23: =$S$8*I23/1000 -> 0 | L23: =K23*S$6/1000 -> 0 | M23: =+K23*S$8/1000 -> 0 | N23: =K23*S$7/1000 -> 0 | O23: =D23+G23-K23 -> 0 | P23: =$S$8*O23/1000 -> 0
B24: 16 | D24: =+D23 -> 0 | E24: =$S$8*D24/1000 -> 0 | H24: =$S$8*G24/1000 -> 0 | I24: =D24+G24 -> 0 | J24: =$S$8*I24/1000 -> 0 | L24: =K24*S$6/1000 -> 0 | M24: =+K24*S$8/1000 -> 0 | N24: =K24*S$7/1000 -> 0 | O24: =D24+G24-K24 -> 0 | P24: =$S$8*O24/1000 -> 0
B25: 17 | D25: =+D24 -> 0 | E25: =$S$8*D25/1000 -> 0 | H25: =$S$8*G25/1000 -> 0 | I25: =D25+G25 -> 0 | J25: =$S$8*I25/1000 -> 0 | L25: =K25*S$6/1000 -> 0 | M25: =+K25*S$8/1000 -> 0 | N25: =K25*S$7/1000 -> 0 | O25: =D25+G25-K25 -> 0 | P25: =$S$8*O25/1000 -> 0
B26: 18 | D26: =+D25 -> 0 | E26: =$S$8*D26/1000 -> 0 | H26: =$S$8*G26/1000 -> 0 | I26: =D26+G26 -> 0 | J26: =$S$8*I26/1000 -> 0 | L26: =K26*S$6/1000 -> 0 | M26: =+K26*S$8/1000 -> 0 | N26: =K26*S$7/1000 -> 0 | O26: =D26+G26-K26 -> 0 | P26: =$S$8*O26/1000 -> 0
B27: 19 | D27: =+D26 -> 0 | E27: =$S$8*D27/1000 -> 0 | H27: =$S$8*G27/1000 -> 0 | I27: =D27+G27 -> 0 | J27: =$S$8*I27/1000 -> 0 | L27: =K27*S$6/1000 -> 0 | M27: =+K27*S$8/1000 -> 0 | N27: =K27*S$7/1000 -> 0 | O27: =D27+G27-K27 -> 0 | P27: =$S$8*O27/1000 -> 0
B28: 20 | D28: =+D27 -> 0 | E28: =$S$8*D28/1000 -> 0 | H28: =$S$8*G28/1000 -> 0 | I28: =D28+G28 -> 0 | J28: =$S$8*I28/1000 -> 0 | L28: =K28*S$6/1000 -> 0 | M28: =+K28*S$8/1000 -> 0 | N28: =K28*S$7/1000 -> 0 | O28: =D28+G28-K28 -> 0 | P28: =$S$8*O28/1000 -> 0
... B39: 31 | D39: =+D38 -> 0 | E39: =$S$8*D39/1000 -> 0 | H39: =$S$8*G39/1000 -> 0 | I39: =D39+G39 -> 0 | J39: =$S$8*I39/1000 -> 0 | L39: =K39*S$6/1000 -> 0 | M39: =+K39*S$8/1000 -> 0 | N39: =K39*S$7/1000 -> 0 | O39: =D39+G39-K39 -> 0 | P39: =$S$8*O39/1000 -> 0
B40: TOTAL | F40: =SUM(F9:F39) -> 0 | G40: =SUM(G9:G39) -> 0 | H40: =SUM(H9:H39) -> 0 | K40: =SUM(K9:K39) -> 0 | L40: =SUM(L9:L39) -> 0 | M40: =SUM(M9:M39) -> 0 | N40: =SUM(N9:N39) -> 0 | R40: 40 | S40: 6.5 | U40: 40 | V40: 28.35 | X40: 2000
U41: =R40*S40/U40*V40*X40/1000 -> 368.55
B42: PACK SHEET | G42: =G40*S7/1000 -> 0 | H42: =+G40*S6/1000 -> 0 | J42: DESPATCH PACKSHEET | L42: =K40*S7/1000 -> 0 | S42: 0.75 | U42: =U41*S42% -> 2.764125
U43: =U41+U42 -> 371.31412

Sheet 34-9.82
B2: STOCK CARD- REF.NO
B3: THE EMPIRE JUTE MILL | R3: HESSIAN
B4: DESCRIPTION OF GOODS:- CANVASE 34-9.82 | R4: SACKING
A5: NATURE OF PACKING :- 1/B -1500 YDS | R5: YARN
B6: DATE | D6: OPENING BALANCE | G6: RECEIPT | I6: TOTAL | K6: ISSUES | M6: GROSS WT | O6: CLOSING BALLACE | Q6: REMARKS | R6: NET WGT. PER BALE | S6: 417.595
D7: NO.OF | E7: WEIGHT IN | G7: NO.OF | H7: WEIGHT IN | I7: NO.OF | J7: WEIGHT IN | K7: NO.OF | L7: NET WT | O7: NO.OF | P7: WEIGHT IN | R7: P.SHEET WGT | S7: 3.132
D8: BALE | E8: KGS | G8: BALE | H8: KGS | I8: BALE | J8: KGS | K8: BALE | L8: KGS | N8: PACK SHEET | O8: BALE | P8: KGS | R8: TOTAL WGT | S8: =S6+S7 -> 420.727
B9: 1 | E9: =$S$8*D9/1000 -> 0 | H9: =$S$8*G9/1000 -> 0 | I9: =D9+G9 -> 0 | J9: =$S$8*I9/1000 -> 0 | L9: =K9*S$6/1000 -> 0 | M9: =+K9*S$8/1000 -> 0 | N9: =K9*S$7/1000 -> 0 | O9: =D9+G9-K9 -> 0 | P9: =$S$8*O9/1000 -> 0 | Q9: =P9*T8/1000 -> 0
B10: 2 | D10: =+O9 -> 0 | E10: =$S$8*D10/1000 -> 0 | H10: =$S$8*G10/1000 -> 0 | I10: =D10+G10 -> 0 | J10: =$S$8*I10/1000 -> 0 | L10: =K10*S$8/1000 -> 0 | M10: =+K10*S$8/1000 -> 0 | N10: =K10*S$7/1000 -> 0 | O10: =D10+G10-K10 -> 0 | P10: =$S$8*O10/1000 -> 0
B11: 3 | D11: =+O10 -> 0 | E11: =$S$8*D11/1000 -> 0 | H11: =$S$8*G11/1000 -> 0 | I11: =D11+G11 -> 0 | J11: =$S$8*I11/1000 -> 0 | L11: =K11*S$6/1000 -> 0 | M11: =+K11*S$8/1000 -> 0 | N11: =K11*S$7/1000 -> 0 | O11: =D11+G11-K11 -> 0 | P11: =$S$8*O11/1000 -> 0
B12: 4 | D12: =+O11 -> 0 | E12: =$S$8*D12/1000 -> 0 | H12: =$S$8*G12/1000 -> 0 | I12: =D12+G12 -> 0 | J12: =$S$8*I12/1000 -> 0 | L12: =K12*S$6/1000 -> 0 | M12: =+K12*S$8/1000 -> 0 | N12: =K12*S$7/1000 -> 0 | O12: =D12+G12-K12 -> 0 | P12: =$S$8*O12/1000 -> 0
B13: 5 | D13: =+O12 -> 0 | E13: =$S$8*D13/1000 -> 0 | H13: =$S$8*G13/1000 -> 0 | I13: =D13+G13 -> 0 | J13: =$S$8*I13/1000 -> 0 | L13: =K13*S$6/1000 -> 0 | M13: =+K13*S$8/1000 -> 0 | N13: =K13*S$7/1000 -> 0 | O13: =D13+G13-K13 -> 0 | P13: =$S$8*O13/1000 -> 0
B14: 6 | D14: =+O13 -> 0 | E14: =$S$8*D14/1000 -> 0 | H14: =$S$8*G14/1000 -> 0 | I14: =D14+G14 -> 0 | J14: =$S$8*I14/1000 -> 0 | L14: =K14*S$6/1000 -> 0 | M14: =+K14*S$8/1000 -> 0 | N14: =K14*S$7/1000 -> 0 | O14: =D14+G14-K14 -> 0 | P14: =$S$8*O14/1000 -> 0
B15: 7 | D15: =+O14 -> 0 | E15: =$S$8*D15/1000 -> 0 | H15: =$S$8*G15/1000 -> 0 | I15: =D15+G15 -> 0 | J15: =$S$8*I15/1000 -> 0 | L15: =K15*S$6/1000 -> 0 | M15: =+K15*S$8/1000 -> 0 | N15: =K15*S$7/1000 -> 0 | O15: =D15+G15-K15 -> 0 | P15: =$S$8*O15/1000 -> 0
B16: 8 | D16: =+O15 -> 0 | E16: =$S$8*D16/1000 -> 0 | H16: =$S$8*G16/1000 -> 0 | I16: =D16+G16 -> 0 | J16: =$S$8*I16/1000 -> 0 | L16: =K16*S$6/1000 -> 0 | M16: =+K16*S$8/1000 -> 0 | N16: =K16*S$7/1000 -> 0 | O16: =D16+G16-K16 -> 0 | P16: =$S$8*O16/1000 -> 0 | S16: OCT
B17: 9 | D17: =+O16 -> 0 | E17: =$S$8*D17/1000 -> 0 | H17: =$S$8*G17/1000 -> 0 | I17: =D17+G17 -> 0 | J17: =$S$8*I17/1000 -> 0 | L17: =K17*S$6/1000 -> 0 | M17: =+K17*S$8/1000 -> 0 | N17: =K17*S$7/1000 -> 0 | O17: =D17+G17-K17 -> 0 | P17: =$S$8*O17/1000 -> 0
B18: 10 | D18: =+O17 -> 0 | E18: =$S$8*D18/1000 -> 0 | H18: =$S$8*G18/1000 -> 0 | I18: =D18+G18 -> 0 | J18: =$S$8*I18/1000 -> 0 | L18: =K18*S$6/1000 -> 0 | M18: =+K18*S$8/1000 -> 0 | N18: =K18*S$7/1000 -> 0 | O18: =D18+G18-K18 -> 0 | P18: =$S$8*O18/1000 -> 0
B19: 11 | D19: =+O18 -> 0 | E19: =$S$8*D19/1000 -> 0 | H19: =$S$8*G19/1000 -> 0 | I19: =D19+G19 -> 0 | J19: =$S$8*I19/1000 -> 0 | L19: =K19*S$6/1000 -> 0 | M19: =+K19*S$8/1000 -> 0 | N19: =K19*S$7/1000 -> 0 | O19: =D19+G19-K19 -> 0 | P19: =$S$8*O19/1000 -> 0
B20: 12 | D20: =+O19 -> 0 | E20: =$S$8*D20/1000 -> 0 | H20: =$S$8*G20/1000 -> 0 | I20: =D20+G20 -> 0 | J20: =$S$8*I20/1000 -> 0 | L20: =K20*S$6/1000 -> 0 | M20: =+K20*S$8/1000 -> 0 | N20: =K20*S$7/1000 -> 0 | O20: =D20+G20-K20 -> 0 | P20: =$S$8*O20/1000 -> 0
B21: 13 | D21: =+O20 -> 0 | E21: =$S$8*D21/1000 -> 0 | H21: =$S$8*G21/1000 -> 0 | I21: =D21+G21 -> 0 | J21: =$S$8*I21/1000 -> 0 | L21: =K21*S$6/1000 -> 0 | M21: =+K21*S$8/1000 -> 0 | N21: =K21*S$7/1000 -> 0 | O21: =D21+G21-K21 -> 0 | P21: =$S$8*O21/1000 -> 0
B22: 14 | D22: =+O21 -> 0 | E22: =$S$8*D22/1000 -> 0 | H22: =$S$8*G22/1000 -> 0 | I22: =D22+G22 -> 0 | J22: =$S$8*I22/1000 -> 0 | L22: =K22*S$6/1000 -> 0 | M22: =+K22*S$8/1000 -> 0 | N22: =K22*S$7/1000 -> 0 | O22: =D22+G22-K22 -> 0 | P22: =$S$8*O22/1000 -> 0
B23: 15 | D23: =+O22 -> 0 | E23: =$S$8*D23/1000 -> 0 | H23: =$S$8*G23/1000 -> 0 | I23: =D23+G23 -> 0 | J23: =$S$8*I23/1000 -> 0 | L23: =K23*S$6/1000 -> 0 | M23: =+K23*S$8/1000 -> 0 | N23: =K23*S$7/1000 -> 0 | O23: =D23+G23-K23 -> 0 | P23: =$S$8*O23/1000 -> 0
B24: 16 | D24: =+O23 -> 0 | E24: =$S$8*D24/1000 -> 0 | H24: =$S$8*G24/1000 -> 0 | I24: =D24+G24 -> 0 | J24: =$S$8*I24/1000 -> 0 | L24: =K24*S$6/1000 -> 0 | M24: =+K24*S$8/1000 -> 0 | N24: =K24*S$7/1000 -> 0 | O24: =D24+G24-K24 -> 0 | P24: =$S$8*O24/1000 -> 0
B25: 17 | D25: =+O24 -> 0 | E25: =$S$8*D25/1000 -> 0 | H25: =$S$8*G25/1000 -> 0 | I25: =D25+G25 -> 0 | J25: =$S$8*I25/1000 -> 0 | L25: =K25*S$6/1000 -> 0 | M25: =+K25*S$8/1000 -> 0 | N25: =K25*S$7/1000 -> 0 | O25: =D25+G25-K25 -> 0 | P25: =$S$8*O25/1000 -> 0
B26: 18 | D26: =+O25 -> 0 | E26: =$S$8*D26/1000 -> 0 | H26: =$S$8*G26/1000 -> 0 | I26: =D26+G26 -> 0 | J26: =$S$8*I26/1000 -> 0 | L26: =K26*S$6/1000 -> 0 | M26: =+K26*S$8/1000 -> 0 | N26: =K26*S$7/1000 -> 0 | O26: =D26+G26-K26 -> 0 | P26: =$S$8*O26/1000 -> 0
B27: 19 | D27: =+O26 -> 0 | E27: =$S$8*D27/1000 -> 0 | H27: =$S$8*G27/1000 -> 0 | I27: =D27+G27 -> 0 | J27: =$S$8*I27/1000 -> 0 | L27: =K27*S$6/1000 -> 0 | M27: =+K27*S$8/1000 -> 0 | N27: =K27*S$7/1000 -> 0 | O27: =D27+G27-K27 -> 0 | P27: =$S$8*O27/1000 -> 0
B28: 20 | D28: =+O27 -> 0 | E28: =$S$8*D28/1000 -> 0 | H28: =$S$8*G28/1000 -> 0 | I28: =D28+G28 -> 0 | J28: =$S$8*I28/1000 -> 0 | L28: =K28*S$6/1000 -> 0 | M28: =+K28*S$8/1000 -> 0 | N28: =K28*S$7/1000 -> 0 | O28: =D28+G28-K28 -> 0 | P28: =$S$8*O28/1000 -> 0
... B39: 31 | D39: =+O38 -> 0 | E39: =$S$8*D39/1000 -> 0 | H39: =$S$8*G39/1000 -> 0 | I39: =D39+G39 -> 0 | J39: =$S$8*I39/1000 -> 0 | L39: =K39*S$6/1000 -> 0 | M39: =+K39*S$8/1000 -> 0 | N39: =K39*S$7/1000 -> 0 | O39: =D39+G39-K39 -> 0 | P39: =$S$8*O39/1000 -> 0
B40: TOTAL | F40: =SUM(F9:F39) -> 0 | G40: =SUM(G9:G39) -> 0 | H40: =SUM(H9:H39) -> 0 | K40: =SUM(K9:K39) -> 0 | L40: =SUM(L9:L39) -> 0 | M40: =SUM(M9:M39) -> 0 | N40: =SUM(N9:N39) -> 0 | R40: 40 | S40: 6.5 | U40: 40 | V40: 28.35 | X40: 2000
U41: =R40*S40/U40*V40*X40/1000 -> 368.55
B42: PACK SHEET | G42: =G40*S7/1000 -> 0 | H42: =+G40*S6/1000 -> 0 | J42: DESPATCH PACKSHEET | L42: =K40*S7/1000 -> 0 | S42: 0.75 | U42: =U41*S42% -> 2.764125
U43: =U41+U42 -> 371.31412

Sheet 44-5 OZ (2)
B2: STOCK CARD- REF.NO | U2: YRAR | V2: 2023
B3: THE EMPIRE JUTE MILL | R3: HESSIAN
B4: DESCRIPTION OF GOODS:- HESSIAN CLOTH 44-5 OZ | R4: SACKING
A5: NATURE OF PACKING :- 1/B 1000 YDS | R5: YARN
D6: OPENING BALANCE | G6: RECEIPT | I6: TOTAL | K6: ISSUES | M6: GROSS WT | O6: CLOSING BALLACE | Q6: REMARKS | R6: NET WGT. PER BALE | S6: =5.5*28.35*1 -> 155.925 | Y6: 155.925
D7: NO.OF | E7: WEIGHT IN | G7: NO.OF | H7: WEIGHT IN MT | I7: NO.OF | J7: WEIGHT IN | K7: NO.OF | L7: NET WT | O7: NO.OF | P7: WEIGHT IN | R7: P.SHEET WGT | S7: =+S6*0.75% -> 1.1694375 | Y7: =+Y6*2 -> 311.85
B8: DATE | D8: BALE | E8: KGS | G8: BALE | I8: BALE | J8: KGS | K8: BALE | L8: KGS | N8: PACK SHEET | O8: BALE | P8: KGS | R8: TOTAL WGT | S8: =S6+S7 -> 157.09444
B9: 1 | E9: =$S$8*D9/1000 -> 0 | H9: =G9*S$8/1000 -> 0 | I9: =D9+G9 -> 0 | J9: =$S$8*I9/1000 -> 0 | L9: =K9*S$6/1000 -> 0 | M9: =K9*S$8/1000 -> 0 | N9: =K9*S$7/1000 -> 0 | O9: =I9-K9 -> 0 | P9: =$S$8*O9/1000 -> 0
B10: 2 | E10: =$S$8*D10/1000 -> 0 | H10: =G10*S$8/1000 -> 0 | I10: =D10+G10 -> 0 | J10: =$S$8*I10/1000 -> 0 | L10: =K10*S$6/1000 -> 0 | M10: =K10*S$8/1000 -> 0 | N10: =K10*S$7/1000 -> 0 | O10: =I10-K10 -> 0 | P10: =$S$8*O10/1000 -> 0
B11: 3 | E11: =$S$8*D11/1000 -> 0 | H11: =G11*S$8/1000 -> 0 | I11: =D11+G11 -> 0 | J11: =$S$8*I11/1000 -> 0 | L11: =K11*S$6/1000 -> 0 | M11: =K11*S$8/1000 -> 0 | N11: =K11*S$7/1000 -> 0 | O11: =I11-K11 -> 0 | P11: =$S$8*O11/1000 -> 0
B12: 4 | E12: =$S$8*D12/1000 -> 0 | H12: =G12*S$8/1000 -> 0 | I12: =D12+G12 -> 0 | J12: =$S$8*I12/1000 -> 0 | L12: =K12*S$6/1000 -> 0 | M12: =K12*S$8/1000 -> 0 | N12: =K12*S$7/1000 -> 0 | O12: =I12-K12 -> 0 | P12: =$S$8*O12/1000 -> 0
B13: 5 | E13: =$S$8*D13/1000 -> 0 | H13: =G13*S$8/1000 -> 0 | I13: =D13+G13 -> 0 | J13: =$S$8*I13/1000 -> 0 | L13: =K13*S$6/1000 -> 0 | M13: =K13*S$8/1000 -> 0 | N13: =K13*S$7/1000 -> 0 | O13: =I13-K13 -> 0 | P13: =$S$8*O13/1000 -> 0
B14: 6 | E14: =$S$8*D14/1000 -> 0 | H14: =G14*S$8/1000 -> 0 | I14: =D14+G14 -> 0 | J14: =$S$8*I14/1000 -> 0 | L14: =K14*S$6/1000 -> 0 | M14: =K14*S$8/1000 -> 0 | N14: =K14*S$7/1000 -> 0 | O14: =I14-K14 -> 0 | P14: =$S$8*O14/1000 -> 0
B15: 7 | E15: =$S$8*D15/1000 -> 0 | H15: =G15*S$8/1000 -> 0 | I15: =D15+G15 -> 0 | J15: =$S$8*I15/1000 -> 0 | L15: =K15*S$6/1000 -> 0 | M15: =K15*S$8/1000 -> 0 | N15: =K15*S$7/1000 -> 0 | O15: =I15-K15 -> 0 | P15: =$S$8*O15/1000 -> 0 | S15: =5.5*28.35*1 -> 155.925
B16: 8 | E16: =$S$8*D16/1000 -> 0 | H16: =G16*S$8/1000 -> 0 | I16: =D16+G16 -> 0 | J16: =$S$8*I16/1000 -> 0 | L16: =K16*S$6/1000 -> 0 | M16: =K16*S$8/1000 -> 0 | N16: =K16*S$7/1000 -> 0 | O16: =I16-K16 -> 0 | P16: =$S$8*O16/1000 -> 0 | S16: =+S15*0.75% -> 1.1694375
B17: 9 | E17: =$S$8*D17/1000 -> 0 | H17: =G17*S$8/1000 -> 0 | I17: =D17+G17 -> 0 | J17: =$S$8*I17/1000 -> 0 | L17: =K17*S$6/1000 -> 0 | M17: =K17*S$8/1000 -> 0 | N17: =K17*S$7/1000 -> 0 | O17: =I17-K17 -> 0 | P17: =$S$8*O17/1000 -> 0 | S17: =+S15+S16 -> 157.09444
B18: 10 | E18: =$S$8*D18/1000 -> 0 | H18: =G18*S$8/1000 -> 0 | I18: =D18+G18 -> 0 | J18: =$S$8*I18/1000 -> 0 | L18: =K18*S$6/1000 -> 0 | M18: =K18*S$8/1000 -> 0 | N18: =K18*S$7/1000 -> 0 | O18: =I18-K18 -> 0 | P18: =$S$8*O18/1000 -> 0
B19: 11 | E19: =$S$8*D19/1000 -> 0 | H19: =G19*S$8/1000 -> 0 | I19: =D19+G19 -> 0 | J19: =$S$8*I19/1000 -> 0 | L19: =K19*S$6/1000 -> 0 | M19: =K19*S$8/1000 -> 0 | N19: =K19*S$7/1000 -> 0 | O19: =I19-K19 -> 0 | P19: =$S$8*O19/1000 -> 0
B20: 12 | E20: =$S$8*D20/1000 -> 0 | H20: =G20*S$8/1000 -> 0 | I20: =D20+G20 -> 0 | J20: =$S$8*I20/1000 -> 0 | L20: =K20*S$6/1000 -> 0 | M20: =K20*S$8/1000 -> 0 | N20: =K20*S$7/1000 -> 0 | O20: =I20-K20 -> 0 | P20: =$S$8*O20/1000 -> 0
B21: 13 | E21: =$S$8*D21/1000 -> 0 | H21: =G21*S$8/1000 -> 0 | I21: =D21+G21 -> 0 | J21: =$S$8*I21/1000 -> 0 | L21: =K21*S$6/1000 -> 0 | M21: =K21*S$8/1000 -> 0 | N21: =K21*S$7/1000 -> 0 | O21: =I21-K21 -> 0 | P21: =$S$8*O21/1000 -> 0
B22: 14 | E22: =$S$8*D22/1000 -> 0 | H22: =G22*S$8/1000 -> 0 | I22: =D22+G22 -> 0 | J22: =$S$8*I22/1000 -> 0 | L22: =K22*S$6/1000 -> 0 | M22: =K22*S$8/1000 -> 0 | N22: =K22*S$7/1000 -> 0 | O22: =I22-K22 -> 0 | P22: =$S$8*O22/1000 -> 0
B23: 15 | E23: =$S$8*D23/1000 -> 0 | H23: =G23*S$8/1000 -> 0 | I23: =D23+G23 -> 0 | J23: =$S$8*I23/1000 -> 0 | L23: =K23*S$6/1000 -> 0 | M23: =K23*S$8/1000 -> 0 | N23: =K23*S$7/1000 -> 0 | O23: =I23-K23 -> 0 | P23: =$S$8*O23/1000 -> 0
B24: 16 | E24: =$S$8*D24/1000 -> 0 | H24: =G24*S$8/1000 -> 0 | I24: =D24+G24 -> 0 | J24: =$S$8*I24/1000 -> 0 | L24: =K24*S$6/1000 -> 0 | M24: =K24*S$8/1000 -> 0 | N24: =K24*S$7/1000 -> 0 | O24: =I24-K24 -> 0 | P24: =$S$8*O24/1000 -> 0
B25: 17 | D25: =+O24 -> 0 | E25: =$S$8*D25/1000 -> 0 | H25: =G25*S$8/1000 -> 0 | I25: =D25+G25 -> 0 | J25: =$S$8*I25/1000 -> 0 | L25: =K25*S$6/1000 -> 0 | M25: =K25*S$8/1000 -> 0 | N25: =K25*S$7/1000 -> 0 | O25: =I25-K25 -> 0 | P25: =$S$8*O25/1000 -> 0
B26: 18 | D26: =+O25 -> 0 | E26: =$S$8*D26/1000 -> 0 | H26: =G26*S$8/1000 -> 0 | I26: =D26+G26 -> 0 | J26: =$S$8*I26/1000 -> 0 | L26: =K26*S$6/1000 -> 0 | M26: =K26*S$8/1000 -> 0 | N26: =K26*S$7/1000 -> 0 | O26: =I26-K26 -> 0 | P26: =$S$8*O26/1000 -> 0
B27: 19 | D27: =+O26 -> 0 | E27: =$S$8*D27/1000 -> 0 | H27: =G27*S$8/1000 -> 0 | I27: =D27+G27 -> 0 | J27: =$S$8*I27/1000 -> 0 | L27: =K27*S$6/1000 -> 0 | M27: =K27*S$8/1000 -> 0 | N27: =K27*S$7/1000 -> 0 | O27: =I27-K27 -> 0 | P27: =$S$8*O27/1000 -> 0
B28: 20 | D28: =+O27 -> 0 | E28: =$S$8*D28/1000 -> 0 | H28: =G28*S$8/1000 -> 0 | I28: =D28+G28 -> 0 | J28: =$S$8*I28/1000 -> 0 | L28: =K28*S$6/1000 -> 0 | M28: =K28*S$8/1000 -> 0 | N28: =K28*S$7/1000 -> 0 | O28: =I28-K28 -> 0 | P28: =$S$8*O28/1000 -> 0
B29: 21 | D29: =+O28 -> 0 | E29: =$S$8*D29/1000 -> 0 | H29: =G29*S$8/1000 -> 0 | I29: =D29+G29 -> 0 | J29: =$S$8*I29/1000 -> 0 | L29: =K29*S$6/1000 -> 0 | M29: =K29*S$8/1000 -> 0 | N29: =K29*S$7/1000 -> 0 | O29: =I29-K29 -> 0 | P29: =$S$8*O29/1000 -> 0
B30: 22 | D30: =+O29 -> 0 | E30: =$S$8*D30/1000 -> 0 | H30: =G30*S$8/1000 -> 0 | I30: =D30+G30 -> 0 | J30: =$S$8*I30/1000 -> 0 | L30: =K30*S$6/1000 -> 0 | M30: =K30*S$8/1000 -> 0 | N30: =K30*S$7/1000 -> 0 | O30: =I30-K30 -> 0 | P30: =$S$8*O30/1000 -> 0
B31: 23 | D31: =+O30 -> 0 | E31: =$S$8*D31/1000 -> 0 | H31: =G31*S$8/1000 -> 0 | I31: =D31+G31 -> 0 | J31: =$S$8*I31/1000 -> 0 | L31: =K31*S$6/1000 -> 0 | M31: =K31*S$8/1000 -> 0 | N31: =K31*S$7/1000 -> 0 | O31: =I31-K31 -> 0 | P31: =$S$8*O31/1000 -> 0
B32: 24 | D32: =+O31 -> 0 | E32: =$S$8*D32/1000 -> 0 | H32: =G32*S$8/1000 -> 0 | I32: =D32+G32 -> 0 | J32: =$S$8*I32/1000 -> 0 | L32: =K32*S$6/1000 -> 0 | M32: =K32*S$8/1000 -> 0 | N32: =K32*S$7/1000 -> 0 | O32: =I32-K32 -> 0 | P32: =$S$8*O32/1000 -> 0
B33: 25 | D33: =+O32 -> 0 | E33: =$S$8*D33/1000 -> 0 | H33: =G33*S$8/1000 -> 0 | I33: =D33+G33 -> 0 | J33: =$S$8*I33/1000 -> 0 | L33: =K33*S$6/1000 -> 0 | M33: =K33*S$8/1000 -> 0 | N33: =K33*S$7/1000 -> 0 | O33: =I33-K33 -> 0 | P33: =$S$8*O33/1000 -> 0
B34: 26 | D34: =+O33 -> 0 | E34: =$S$8*D34/1000 -> 0 | H34: =G34*S$8/1000 -> 0 | I34: =D34+G34 -> 0 | J34: =$S$8*I34/1000 -> 0 | L34: =K34*S$6/1000 -> 0 | M34: =K34*S$8/1000 -> 0 | N34: =K34*S$7/1000 -> 0 | O34: =I34-K34 -> 0 | P34: =$S$8*O34/1000 -> 0
B35: 27 | D35: =+O34 -> 0 | E35: =$S$8*D35/1000 -> 0 | H35: =G35*S$8/1000 -> 0 | I35: =D35+G35 -> 0 | J35: =$S$8*I35/1000 -> 0 | L35: =K35*S$6/1000 -> 0 | M35: =K35*S$8/1000 -> 0 | N35: =K35*S$7/1000 -> 0 | O35: =I35-K35 -> 0 | P35: =$S$8*O35/1000 -> 0
B36: 28 | D36: =+O35 -> 0 | E36: =$S$8*D36/1000 -> 0 | H36: =G36*S$8/1000 -> 0 | I36: =D36+G36 -> 0 | J36: =$S$8*I36/1000 -> 0 | L36: =K36*S$6/1000 -> 0 | M36: =K36*S$8/1000 -> 0 | N36: =K36*S$7/1000 -> 0 | O36: =I36-K36 -> 0 | P36: =$S$8*O36/1000 -> 0
... B39: 31 | D39: =+O38 -> 0 | E39: =$S$8*D39/1000 -> 0 | H39: =G39*S$8/1000 -> 0 | I39: =D39+G39 -> 0 | J39: =$S$8*I39/1000 -> 0 | L39: =K39*S$6/1000 -> 0 | M39: =K39*S$8/1000 -> 0 | N39: =K39*S$7/1000 -> 0 | O39: =I39-K39 -> 0 | P39: =$S$8*O39/1000 -> 0
B40: TOTAL | G40: =SUM(G9:G39) -> 0 | H40: =SUM(H9:H39) -> 0 | K40: =SUM(K9:K39) -> 0 | L40: =SUM(L9:L39) -> 0 | M40: =SUM(M9:M39) -> 0 | N40: =SUM(N9:N39) -> 0
B42: PROD PACK SHEET | G42: =G40*S7/1000 -> 0 | H42: =+G40*S6/1000 -> 0 | J42: DESPATCH PACK SHEET | L42: =+K40*S7/1000 -> 0
H45: HESIAN TOTAL PCK SHEET | K45: =+G42+'20 X10 '!G42+'38-8.12-OZ '!G42+'44-8.12 OZ'!G42+'40-4.5-OZ'!G42+'36-4.05 OZ'!G42+'34-9.82'!G42+'54-6.5'!G42+'44-7.15 '!G42+'48-8.4-OZ '!G42+'40-6.5'!G42+'48-7.80 EXP'!E42+'40-5-OZ-EXP'!E42+'48-6 EXPORT'!G42 -> 0.49407062
H47: EXPORT TOTAL PCK SHEET | K47: =+'40-5-OZ-EXP'!E42+'EXPORT '!E42 -> 0 | L47: HESS CLEARENCE PACKSHEED | O47: =+L42+'20 X10 '!L42+'38-8.12-OZ '!L42+'44-8.12 OZ'!L42+'40-4.5-OZ'!L42+'36-4.05 OZ'!L42+'34-9.82'!L42+'54-6.5'!L42+'44-7.15 '!L42+'48-8.4-OZ '!K42+'40-6.5'!L42+'51-11.36-OZ '!L42+'48-7.80 EXP'!L42+'40-5-OZ-EXP'!L42+'48-6 EXPORT'!L42 -> 0.53306112
H48: TOTAL HESS + EXPORT | K48: =K45+K47 -> 0.49407062
L49: SKG CLEARENCE PACKSHEED | O49: =+'TYPE A GOV'!L42+'767 GMS 500 PCS'!L42 -> 2.081475
H50: SACKING TOTAL PCK SHEET | K50: =+'TYPE A GOV'!G42+'767 GMS 500 PCS'!G42 -> 1.42245
H52: GRAND TOTAL PACK SHEET | K52: =K45+K47+K50 -> 1.9165206

Sheet 44-5 OZ
B2: STOCK CARD- REF.NO | U2: YRAR | V2: 2023
B3: THE EMPIRE JUTE MILL | R3: HESSIAN
B4: DESCRIPTION OF GOODS:- HESSIAN CLOTH 44-5 OZ | R4: SACKING
A5: NATURE OF PACKING :- 1/B 2000 YDS | R5: YARN
D6: OPENING BALANCE | G6: RECEIPT | I6: TOTAL | K6: ISSUES | M6: GROSS WT | O6: CLOSING BALLACE | Q6: REMARKS | R6: NET WGT. PER BALE | S6: 311.85
D7: NO.OF | E7: WEIGHT IN | G7: NO.OF | H7: WEIGHT IN MT | I7: NO.OF | J7: WEIGHT IN | K7: NO.OF | L7: NET WT | O7: NO.OF | P7: WEIGHT IN | R7: P.SHEET WGT | S7: =+S6*0.75% -> 2.338875
B8: DATE | D8: BALE | E8: KGS | G8: BALE | I8: BALE | J8: KGS | K8: BALE | L8: KGS | N8: PACK SHEET | O8: BALE | P8: KGS | R8: TOTAL WGT | S8: =S6+S7 -> 314.18887
B9: 1 | E9: =$S$8*D9/1000 -> 0 | H9: =G9*S$8/1000 -> 0 | I9: =D9+G9 -> 0 | J9: =$S$8*I9/1000 -> 0 | L9: =K9*S$6/1000 -> 0 | M9: =K9*S$8/1000 -> 0 | N9: =K9*S$7/1000 -> 0 | O9: =I9-K9 -> 0 | P9: =$S$8*O9/1000 -> 0
B10: 2 | E10: =$S$8*D10/1000 -> 0 | H10: =G10*S$8/1000 -> 0 | I10: =D10+G10 -> 0 | J10: =$S$8*I10/1000 -> 0 | L10: =K10*S$6/1000 -> 0 | M10: =K10*S$8/1000 -> 0 | N10: =K10*S$7/1000 -> 0 | O10: =I10-K10 -> 0 | P10: =$S$8*O10/1000 -> 0
B11: 3 | E11: =$S$8*D11/1000 -> 0 | H11: =G11*S$8/1000 -> 0 | I11: =D11+G11 -> 0 | J11: =$S$8*I11/1000 -> 0 | L11: =K11*S$6/1000 -> 0 | M11: =K11*S$8/1000 -> 0 | N11: =K11*S$7/1000 -> 0 | O11: =I11-K11 -> 0 | P11: =$S$8*O11/1000 -> 0
B12: 4 | E12: =$S$8*D12/1000 -> 0 | H12: =G12*S$8/1000 -> 0 | I12: =D12+G12 -> 0 | J12: =$S$8*I12/1000 -> 0 | L12: =K12*S$6/1000 -> 0 | M12: =K12*S$8/1000 -> 0 | N12: =K12*S$7/1000 -> 0 | O12: =I12-K12 -> 0 | P12: =$S$8*O12/1000 -> 0
B13: 5 | E13: =$S$8*D13/1000 -> 0 | H13: =G13*S$8/1000 -> 0 | I13: =D13+G13 -> 0 | J13: =$S$8*I13/1000 -> 0 | L13: =K13*S$6/1000 -> 0 | M13: =K13*S$8/1000 -> 0 | N13: =K13*S$7/1000 -> 0 | O13: =I13-K13 -> 0 | P13: =$S$8*O13/1000 -> 0
B14: 6 | E14: =$S$8*D14/1000 -> 0 | H14: =G14*S$8/1000 -> 0 | I14: =D14+G14 -> 0 | J14: =$S$8*I14/1000 -> 0 | L14: =K14*S$6/1000 -> 0 | M14: =K14*S$8/1000 -> 0 | N14: =K14*S$7/1000 -> 0 | O14: =I14-K14 -> 0 | P14: =$S$8*O14/1000 -> 0
B15: 7 | E15: =$S$8*D15/1000 -> 0 | H15: =G15*S$8/1000 -> 0 | I15: =D15+G15 -> 0 | J15: =$S$8*I15/1000 -> 0 | L15: =K15*S$6/1000 -> 0 | M15: =K15*S$8/1000 -> 0 | N15: =K15*S$7/1000 -> 0 | O15: =I15-K15 -> 0 | P15: =$S$8*O15/1000 -> 0 | S15: =5.5*28.35*2 -> 311.85
B16: 8 | E16: =$S$8*D16/1000 -> 0 | H16: =G16*S$8/1000 -> 0 | I16: =D16+G16 -> 0 | J16: =$S$8*I16/1000 -> 0 | L16: =K16*S$6/1000 -> 0 | M16: =K16*S$8/1000 -> 0 | N16: =K16*S$7/1000 -> 0 | O16: =I16-K16 -> 0 | P16: =$S$8*O16/1000 -> 0 | S16: =+S15*0.75% -> 2.338875
B17: 9 | E17: =$S$8*D17/1000 -> 0 | H17: =G17*S$8/1000 -> 0 | I17: =D17+G17 -> 0 | J17: =$S$8*I17/1000 -> 0 | L17: =K17*S$6/1000 -> 0 | M17: =K17*S$8/1000 -> 0 | N17: =K17*S$7/1000 -> 0 | O17: =I17-K17 -> 0 | P17: =$S$8*O17/1000 -> 0 | S17: =+S15+S16 -> 314.18887
B18: 10 | E18: =$S$8*D18/1000 -> 0 | H18: =G18*S$8/1000 -> 0 | I18: =D18+G18 -> 0 | J18: =$S$8*I18/1000 -> 0 | L18: =K18*S$6/1000 -> 0 | M18: =K18*S$8/1000 -> 0 | N18: =K18*S$7/1000 -> 0 | O18: =I18-K18 -> 0 | P18: =$S$8*O18/1000 -> 0
B19: 11 | E19: =$S$8*D19/1000 -> 0 | H19: =G19*S$8/1000 -> 0 | I19: =D19+G19 -> 0 | J19: =$S$8*I19/1000 -> 0 | L19: =K19*S$6/1000 -> 0 | M19: =K19*S$8/1000 -> 0 | N19: =K19*S$7/1000 -> 0 | O19: =I19-K19 -> 0 | P19: =$S$8*O19/1000 -> 0
B20: 12 | E20: =$S$8*D20/1000 -> 0 | H20: =G20*S$8/1000 -> 0 | I20: =D20+G20 -> 0 | J20: =$S$8*I20/1000 -> 0 | L20: =K20*S$6/1000 -> 0 | M20: =K20*S$8/1000 -> 0 | N20: =K20*S$7/1000 -> 0 | O20: =I20-K20 -> 0 | P20: =$S$8*O20/1000 -> 0
B21: 13 | E21: =$S$8*D21/1000 -> 0 | H21: =G21*S$8/1000 -> 0 | I21: =D21+G21 -> 0 | J21: =$S$8*I21/1000 -> 0 | L21: =K21*S$6/1000 -> 0 | M21: =K21*S$8/1000 -> 0 | N21: =K21*S$7/1000 -> 0 | O21: =I21-K21 -> 0 | P21: =$S$8*O21/1000 -> 0
B22: 14 | E22: =$S$8*D22/1000 -> 0 | H22: =G22*S$8/1000 -> 0 | I22: =D22+G22 -> 0 | J22: =$S$8*I22/1000 -> 0 | L22: =K22*S$6/1000 -> 0 | M22: =K22*S$8/1000 -> 0 | N22: =K22*S$7/1000 -> 0 | O22: =I22-K22 -> 0 | P22: =$S$8*O22/1000 -> 0
B23: 15 | E23: =$S$8*D23/1000 -> 0 | H23: =G23*S$8/1000 -> 0 | I23: =D23+G23 -> 0 | J23: =$S$8*I23/1000 -> 0 | L23: =K23*S$6/1000 -> 0 | M23: =K23*S$8/1000 -> 0 | N23: =K23*S$7/1000 -> 0 | O23: =I23-K23 -> 0 | P23: =$S$8*O23/1000 -> 0
B24: 16 | D24: =+O23 -> 0 | E24: =$S$8*D24/1000 -> 0 | H24: =G24*S$8/1000 -> 0 | I24: =D24+G24 -> 0 | J24: =$S$8*I24/1000 -> 0 | L24: =K24*S$6/1000 -> 0 | M24: =K24*S$8/1000 -> 0 | N24: =K24*S$7/1000 -> 0 | O24: =I24-K24 -> 0 | P24: =$S$8*O24/1000 -> 0
B25: 17 | D25: =+O24 -> 0 | E25: =$S$8*D25/1000 -> 0 | H25: =G25*S$8/1000 -> 0 | I25: =D25+G25 -> 0 | J25: =$S$8*I25/1000 -> 0 | L25: =K25*S$6/1000 -> 0 | M25: =K25*S$8/1000 -> 0 | N25: =K25*S$7/1000 -> 0 | O25: =I25-K25 -> 0 | P25: =$S$8*O25/1000 -> 0
B26: 18 | D26: =+O25 -> 0 | E26: =$S$8*D26/1000 -> 0 | H26: =G26*S$8/1000 -> 0 | I26: =D26+G26 -> 0 | J26: =$S$8*I26/1000 -> 0 | L26: =K26*S$6/1000 -> 0 | M26: =K26*S$8/1000 -> 0 | N26: =K26*S$7/1000 -> 0 | O26: =I26-K26 -> 0 | P26: =$S$8*O26/1000 -> 0
B27: 19 | D27: =+O26 -> 0 | E27: =$S$8*D27/1000 -> 0 | H27: =G27*S$8/1000 -> 0 | I27: =D27+G27 -> 0 | J27: =$S$8*I27/1000 -> 0 | L27: =K27*S$6/1000 -> 0 | M27: =K27*S$8/1000 -> 0 | N27: =K27*S$7/1000 -> 0 | O27: =I27-K27 -> 0 | P27: =$S$8*O27/1000 -> 0
B28: 20 | D28: =+O27 -> 0 | E28: =$S$8*D28/1000 -> 0 | H28: =G28*S$8/1000 -> 0 | I28: =D28+G28 -> 0 | J28: =$S$8*I28/1000 -> 0 | L28: =K28*S$6/1000 -> 0 | M28: =K28*S$8/1000 -> 0 | N28: =K28*S$7/1000 -> 0 | O28: =I28-K28 -> 0 | P28: =$S$8*O28/1000 -> 0
B29: 21 | D29: =+O28 -> 0 | E29: =$S$8*D29/1000 -> 0 | H29: =G29*S$8/1000 -> 0 | I29: =D29+G29 -> 0 | J29: =$S$8*I29/1000 -> 0 | L29: =K29*S$6/1000 -> 0 | M29: =K29*S$8/1000 -> 0 | N29: =K29*S$7/1000 -> 0 | O29: =I29-K29 -> 0 | P29: =$S$8*O29/1000 -> 0
B30: 22 | D30: =+O29 -> 0 | E30: =$S$8*D30/1000 -> 0 | H30: =G30*S$8/1000 -> 0 | I30: =D30+G30 -> 0 | J30: =$S$8*I30/1000 -> 0 | L30: =K30*S$6/1000 -> 0 | M30: =K30*S$8/1000 -> 0 | N30: =K30*S$7/1000 -> 0 | O30: =I30-K30 -> 0 | P30: =$S$8*O30/1000 -> 0
B31: 23 | D31: =+O30 -> 0 | E31: =$S$8*D31/1000 -> 0 | H31: =G31*S$8/1000 -> 0 | I31: =D31+G31 -> 0 | J31: =$S$8*I31/1000 -> 0 | L31: =K31*S$6/1000 -> 0 | M31: =K31*S$8/1000 -> 0 | N31: =K31*S$7/1000 -> 0 | O31: =I31-K31 -> 0 | P31: =$S$8*O31/1000 -> 0
B32: 24 | D32: =+O31 -> 0 | E32: =$S$8*D32/1000 -> 0 | H32: =G32*S$8/1000 -> 0 | I32: =D32+G32 -> 0 | J32: =$S$8*I32/1000 -> 0 | L32: =K32*S$6/1000 -> 0 | M32: =K32*S$8/1000 -> 0 | N32: =K32*S$7/1000 -> 0 | O32: =I32-K32 -> 0 | P32: =$S$8*O32/1000 -> 0
B33: 25 | D33: =+O32 -> 0 | E33: =$S$8*D33/1000 -> 0 | H33: =G33*S$8/1000 -> 0 | I33: =D33+G33 -> 0 | J33: =$S$8*I33/1000 -> 0 | L33: =K33*S$6/1000 -> 0 | M33: =K33*S$8/1000 -> 0 | N33: =K33*S$7/1000 -> 0 | O33: =I33-K33 -> 0 | P33: =$S$8*O33/1000 -> 0
B34: 26 | D34: =+O33 -> 0 | E34: =$S$8*D34/1000 -> 0 | H34: =G34*S$8/1000 -> 0 | I34: =D34+G34 -> 0 | J34: =$S$8*I34/1000 -> 0 | L34: =K34*S$6/1000 -> 0 | M34: =K34*S$8/1000 -> 0 | N34: =K34*S$7/1000 -> 0 | O34: =I34-K34 -> 0 | P34: =$S$8*O34/1000 -> 0
B35: 27 | D35: =+O34 -> 0 | E35: =$S$8*D35/1000 -> 0 | H35: =G35*S$8/1000 -> 0 | I35: =D35+G35 -> 0 | J35: =$S$8*I35/1000 -> 0 | L35: =K35*S$6/1000 -> 0 | M35: =K35*S$8/1000 -> 0 | N35: =K35*S$7/1000 -> 0 | O35: =I35-K35 -> 0 | P35: =$S$8*O35/1000 -> 0
... B39: 31 | D39: =+O38 -> 0 | E39: =$S$8*D39/1000 -> 0 | H39: =G39*S$8/1000 -> 0 | I39: =D39+G39 -> 0 | J39: =$S$8*I39/1000 -> 0 | L39: =K39*S$6/1000 -> 0 | M39: =K39*S$8/1000 -> 0 | N39: =K39*S$7/1000 -> 0 | O39: =I39-K39 -> 0 | P39: =$S$8*O39/1000 -> 0
B40: TOTAL | G40: =SUM(G9:G39) -> 0 | H40: =SUM(H9:H39) -> 0 | K40: =SUM(K9:K39) -> 0 | L40: =SUM(L9:L39) -> 0 | M40: =SUM(M9:M39) -> 0 | N40: =SUM(N9:N39) -> 0
B42: PROD PACK SHEET | G42: =G40*S7/1000 -> 0 | H42: =+G40*S6/1000 -> 0 | J42: DESPATCH PACK SHEET | L42: =+K40*S7/1000 -> 0
H45: HESIAN TOTAL PCK SHEET | K45: =+G42+'20 X10 '!G42+'38-8.12-OZ '!G42+'44-8.12 OZ'!G42+'40-4.5-OZ'!G42+'36-4.05 OZ'!G42+'34-9.82'!G42+'54-6.5'!G42+'44-7.15 '!G42+'48-8.4-OZ '!G42+'40-6.5'!G42+'48-7.80 EXP'!E42+'40-5-OZ-EXP'!E42+'48-6 EXPORT'!G42 -> 0.49407062
H47: EXPORT TOTAL PCK SHEET | K47: =+'40-5-OZ-EXP'!E42+'EXPORT '!E42 -> 0 | L47: HESS CLEARENCE PACKSHEED | O47: =+L42+'20 X10 '!L42+'38-8.12-OZ '!L42+'44-8.12 OZ'!L42+'40-4.5-OZ'!L42+'36-4.05 OZ'!L42+'34-9.82'!L42+'54-6.5'!L42+'44-7.15 '!L42+'48-8.4-OZ '!K42+'40-6.5'!L42+'51-11.36-OZ '!L42+'48-7.80 EXP'!L42+'40-5-OZ-EXP'!L42+'48-6 EXPORT'!L42 -> 0.53306112
H48: TOTAL HESS + EXPORT | K48: =K45+K47 -> 0.49407062
L49: SKG CLEARENCE PACKSHEED | O49: =+'TYPE A GOV'!L42+'767 GMS 500 PCS'!L42 -> 2.081475
H50: SACKING TOTAL PCK SHEET | K50: =+'TYPE A GOV'!G42+'767 GMS 500 PCS'!G42 -> 1.42245
H52: GRAND TOTAL PACK SHEET | K52: =K45+K47+K50 -> 1.9165206

Sheet 54-6.5
B2: STOCK CARD- REF.NO
B3: THE EMPIRE JUTE MILL | R3: HESSIAN
B4: DESCRIPTION OF GOODS:- RAPIER 54"-6.5 OZ | R4: SACKING
A5: NATURE OF PACKING :- 1/B 1828.80 MTR | R5: YARN
B6: DATE | D6: OPENING BALANCE | G6: RECEIPT | I6: TOTAL | K6: ISSUES | M6: GROSS WT | O6: CLOSING BALLACE | Q6: REMARKS | R6: NET WGT. PER BALE | S6: 497.533
D7: NO.OF | E7: WEIGHT IN | G7: NO.OF | H7: WEIGHT IN | I7: NO.OF | J7: WEIGHT IN | K7: NO.OF | L7: NET WT | O7: NO.OF | P7: WEIGHT IN | R7: P.SHEET WGT | S7: =S6*0.75% -> 3.7314975
D8: BALE | E8: KGS | G8: BALE | H8: KGS | I8: BALE | J8: KGS | K8: BALE | L8: KGS | N8: PACK SHEET | O8: BALE | P8: KGS | R8: TOTAL WGT | S8: =S6+S7 -> 501.2645
B9: 1 | E9: =$S$8*D9/1000 -> 0 | H9: =$S$8*G9/1000 -> 0 | I9: =D9+G9 -> 0 | J9: =$S$8*I9/1000 -> 0 | L9: =K9*S$6/1000 -> 0 | M9: =+K9*S$8/1000 -> 0 | N9: =K9*S$7/1000 -> 0 | O9: =D9+G9-K9 -> 0 | P9: =$S$8*O9/1000 -> 0 | Q9: =P9*T8/1000 -> 0
B10: 2 | E10: =$S$8*D10/1000 -> 0 | H10: =$S$8*G10/1000 -> 0 | I10: =D10+G10 -> 0 | J10: =$S$8*I10/1000 -> 0 | L10: =K10*S$8/1000 -> 0 | M10: =+K10*S$8/1000 -> 0 | N10: =K10*S$7/1000 -> 0 | O10: =D10+G10-K10 -> 0 | P10: =$S$8*O10/1000 -> 0
B11: 3 | E11: =$S$8*D11/1000 -> 0 | H11: =$S$8*G11/1000 -> 0 | I11: =D11+G11 -> 0 | J11: =$S$8*I11/1000 -> 0 | L11: =K11*S$6/1000 -> 0 | M11: =+K11*S$8/1000 -> 0 | N11: =K11*S$7/1000 -> 0 | O11: =D11+G11-K11 -> 0 | P11: =$S$8*O11/1000 -> 0
B12: 4 | E12: =$S$8*D12/1000 -> 0 | H12: =$S$8*G12/1000 -> 0 | I12: =D12+G12 -> 0 | J12: =$S$8*I12/1000 -> 0 | L12: =K12*S$6/1000 -> 0 | M12: =+K12*S$8/1000 -> 0 | N12: =K12*S$7/1000 -> 0 | O12: =D12+G12-K12 -> 0 | P12: =$S$8*O12/1000 -> 0
B13: 5 | D13: =+D12 -> 0 | E13: =$S$8*D13/1000 -> 0 | H13: =$S$8*G13/1000 -> 0 | I13: =D13+G13 -> 0 | J13: =$S$8*I13/1000 -> 0 | L13: =K13*S$6/1000 -> 0 | M13: =+K13*S$8/1000 -> 0 | N13: =K13*S$7/1000 -> 0 | O13: =D13+G13-K13 -> 0 | P13: =$S$8*O13/1000 -> 0
B14: 6 | D14: =+D13 -> 0 | E14: =$S$8*D14/1000 -> 0 | H14: =$S$8*G14/1000 -> 0 | I14: =D14+G14 -> 0 | J14: =$S$8*I14/1000 -> 0 | L14: =K14*S$6/1000 -> 0 | M14: =+K14*S$8/1000 -> 0 | N14: =K14*S$7/1000 -> 0 | O14: =D14+G14-K14 -> 0 | P14: =$S$8*O14/1000 -> 0
B15: 7 | D15: =+D14 -> 0 | E15: =$S$8*D15/1000 -> 0 | H15: =$S$8*G15/1000 -> 0 | I15: =D15+G15 -> 0 | J15: =$S$8*I15/1000 -> 0 | L15: =K15*S$6/1000 -> 0 | M15: =+K15*S$8/1000 -> 0 | N15: =K15*S$7/1000 -> 0 | O15: =D15+G15-K15 -> 0 | P15: =$S$8*O15/1000 -> 0
B16: 8 | D16: =+D15 -> 0 | E16: =$S$8*D16/1000 -> 0 | H16: =$S$8*G16/1000 -> 0 | I16: =D16+G16 -> 0 | J16: =$S$8*I16/1000 -> 0 | L16: =K16*S$6/1000 -> 0 | M16: =+K16*S$8/1000 -> 0 | N16: =K16*S$7/1000 -> 0 | O16: =D16+G16-K16 -> 0 | P16: =$S$8*O16/1000 -> 0
B17: 9 | D17: =+D16 -> 0 | E17: =$S$8*D17/1000 -> 0 | H17: =$S$8*G17/1000 -> 0 | I17: =D17+G17 -> 0 | J17: =$S$8*I17/1000 -> 0 | L17: =K17*S$6/1000 -> 0 | M17: =+K17*S$8/1000 -> 0 | N17: =K17*S$7/1000 -> 0 | O17: =D17+G17-K17 -> 0 | P17: =$S$8*O17/1000 -> 0
B18: 10 | D18: =+D17 -> 0 | E18: =$S$8*D18/1000 -> 0 | H18: =$S$8*G18/1000 -> 0 | I18: =D18+G18 -> 0 | J18: =$S$8*I18/1000 -> 0 | L18: =K18*S$6/1000 -> 0 | M18: =+K18*S$8/1000 -> 0 | N18: =K18*S$7/1000 -> 0 | O18: =D18+G18-K18 -> 0 | P18: =$S$8*O18/1000 -> 0
B19: 11 | D19: =+D18 -> 0 | E19: =$S$8*D19/1000 -> 0 | H19: =$S$8*G19/1000 -> 0 | I19: =D19+G19 -> 0 | J19: =$S$8*I19/1000 -> 0 | L19: =K19*S$6/1000 -> 0 | M19: =+K19*S$8/1000 -> 0 | N19: =K19*S$7/1000 -> 0 | O19: =D19+G19-K19 -> 0 | P19: =$S$8*O19/1000 -> 0
B20: 12 | D20: =+D19 -> 0 | E20: =$S$8*D20/1000 -> 0 | H20: =$S$8*G20/1000 -> 0 | I20: =D20+G20 -> 0 | J20: =$S$8*I20/1000 -> 0 | L20: =K20*S$6/1000 -> 0 | M20: =+K20*S$8/1000 -> 0 | N20: =K20*S$7/1000 -> 0 | O20: =D20+G20-K20 -> 0 | P20: =$S$8*O20/1000 -> 0
B21: 13 | D21: =+D20 -> 0 | E21: =$S$8*D21/1000 -> 0 | H21: =$S$8*G21/1000 -> 0 | I21: =D21+G21 -> 0 | J21: =$S$8*I21/1000 -> 0 | L21: =K21*S$6/1000 -> 0 | M21: =+K21*S$8/1000 -> 0 | N21: =K21*S$7/1000 -> 0 | O21: =D21+G21-K21 -> 0 | P21: =$S$8*O21/1000 -> 0
B22: 14 | D22: =+D21 -> 0 | E22: =$S$8*D22/1000 -> 0 | H22: =$S$8*G22/1000 -> 0 | I22: =D22+G22 -> 0 | J22: =$S$8*I22/1000 -> 0 | L22: =K22*S$6/1000 -> 0 | M22: =+K22*S$8/1000 -> 0 | N22: =K22*S$7/1000 -> 0 | O22: =D22+G22-K22 -> 0 | P22: =$S$8*O22/1000 -> 0
B23: 15 | D23: =+D22 -> 0 | E23: =$S$8*D23/1000 -> 0 | H23: =$S$8*G23/1000 -> 0 | I23: =D23+G23 -> 0 | J23: =$S$8*I23/1000 -> 0 | L23: =K23*S$6/1000 -> 0 | M23: =+K23*S$8/1000 -> 0 | N23: =K23*S$7/1000 -> 0 | O23: =D23+G23-K23 -> 0 | P23: =$S$8*O23/1000 -> 0
B24: 16 | D24: =+D23 -> 0 | E24: =$S$8*D24/1000 -> 0 | H24: =$S$8*G24/1000 -> 0 | I24: =D24+G24 -> 0 | J24: =$S$8*I24/1000 -> 0 | L24: =K24*S$6/1000 -> 0 | M24: =+K24*S$8/1000 -> 0 | N24: =K24*S$7/1000 -> 0 | O24: =D24+G24-K24 -> 0 | P24: =$S$8*O24/1000 -> 0
... B39: 31 | D39: =+D38 -> 0 | E39: =$S$8*D39/1000 -> 0 | H39: =$S$8*G39/1000 -> 0 | I39: =D39+G39 -> 0 | J39: =$S$8*I39/1000 -> 0 | L39: =K39*S$6/1000 -> 0 | M39: =+K39*S$8/1000 -> 0 | N39: =K39*S$7/1000 -> 0 | O39: =D39+G39-K39 -> 0 | P39: =$S$8*O39/1000 -> 0
B40: TOTAL | F40: =SUM(F9:F39) -> 0 | G40: =SUM(G9:G39) -> 0 | H40: =SUM(H9:H39) -> 0 | K40: =SUM(K9:K39) -> 0 | L40: =SUM(L9:L39) -> 0 | M40: =SUM(M9:M39) -> 0 | N40: =SUM(N9:N39) -> 0 | R40: 40 | S40: 6.5 | U40: 40 | V40: 28.35 | X40: 2000
U41: =R40*S40/U40*V40*X40/1000 -> 368.55
B42: PACK SHEET | G42: =G40*S7/1000 -> 0 | H42: =+G40*S6/1000 -> 0 | J42: DESPATCH PACKSHEET | L42: =K40*S7/1000 -> 0 | S42: 0.75 | U42: =U41*S42% -> 2.764125
U43: =U41+U42 -> 371.31412

Sheet 44-7.15 
B2: STOCK CARD- REF.NO
B3: THE EMPIRE JUTE MILL | R3: HESSIAN
B4: HESSIAN CLOTH 44-7.15 OZ /40 8X8 PLAIN I/B-2000 YDS ( 44-6.5 OZ) | R4: SACKING
A5: NATURE OF PACKING :- 1/B 2000 YDS | R5: YARN
B6: DATE | D6: OPENING BALANCE | G6: RECEIPT | I6: TOTAL | K6: ISSUES | M6: GROSS WT | O6: CLOSING BALLACE | Q6: REMARKS | R6: NET WGT. PER BALE | S6: 405.405
D7: NO.OF | E7: WEIGHT IN | G7: NO.OF | H7: WEIGHT IN | I7: NO.OF | J7: WEIGHT IN | K7: NO.OF | L7: NET WT | O7: NO.OF | P7: WEIGHT IN | R7: P.SHEET WGT | S7: =+S6*0.75% -> 3.0405375
D8: BALE | E8: KGS | G8: BALE | H8: KGS | I8: BALE | J8: KGS | K8: BALE | L8: KGS | N8: PACK SHEET | O8: BALE | P8: KGS | R8: TOTAL WGT | S8: =S6+S7 -> 408.44554
B9: 1 | E9: =$S$8*D9/1000 -> 0 | H9: =$S$8*G9/1000 -> 0 | I9: =+D9+G9 -> 0 | J9: =$S$8*I9/1000 -> 0 | K9: 0 | L9: =K9*S$6/1000 -> 0 | M9: =K9*S$8/1000 -> 0 | N9: =K9*S$7/1000 -> 0 | O9: =D9+G9-K9 -> 0 | P9: =$S$8*O9/1000 -> 0 | Q9: =P9*T8/1000 -> 0
B10: 2 | D10: =+O9 -> 0 | E10: =$S$8*D10/1000 -> 0 | H10: =$S$8*G10/1000 -> 0 | I10: =+D10+G10 -> 0 | J10: =$S$8*I10/1000 -> 0 | K10: 0 | L10: =K10*S$6/1000 -> 0 | M10: =K10*S$8/1000 -> 0 | N10: =K10*S$7/1000 -> 0 | O10: =D10+G10-K10 -> 0 | P10: =$S$8*O10/1000 -> 0
B11: 3 | D11: =+O10 -> 0 | E11: =$S$8*D11/1000 -> 0 | H11: =$S$8*G11/1000 -> 0 | I11: =+D11+G11 -> 0 | J11: =$S$8*I11/1000 -> 0 | K11: 0 | L11: =K11*S$6/1000 -> 0 | M11: =K11*S$8/1000 -> 0 | N11: =K11*S$7/1000 -> 0 | O11: =D11+G11-K11 -> 0 | P11: =$S$8*O11/1000 -> 0
B12: 4 | D12: =+O11 -> 0 | E12: =$S$8*D12/1000 -> 0 | H12: =$S$8*G12/1000 -> 0 | I12: =+D12+G12 -> 0 | J12: =$S$8*I12/1000 -> 0 | K12: 0 | L12: =K12*S$6/1000 -> 0 | M12: =K12*S$8/1000 -> 0 | N12: =K12*S$7/1000 -> 0 | O12: =D12+G12-K12 -> 0 | P12: =$S$8*O12/1000 -> 0
B13: 5 | D13: =+O12 -> 0 | E13: =$S$8*D13/1000 -> 0 | H13: =$S$8*G13/1000 -> 0 | I13: =+D13+G13 -> 0 | J13: =$S$8*I13/1000 -> 0 | K13: 0 | L13: =K13*S$6/1000 -> 0 | M13: =K13*S$8/1000 -> 0 | N13: =K13*S$7/1000 -> 0 | O13: =D13+G13-K13 -> 0 | P13: =$S$8*O13/1000 -> 0
B14: 6 | D14: =+O13 -> 0 | E14: =$S$8*D14/1000 -> 0 | H14: =$S$8*G14/1000 -> 0 | I14: =+D14+G14 -> 0 | J14: =$S$8*I14/1000 -> 0 | K14: 0 | L14: =K14*S$6/1000 -> 0 | M14: =K14*S$8/1000 -> 0 | N14: =K14*S$7/1000 -> 0 | O14: =D14+G14-K14 -> 0 | P14: =$S$8*O14/1000 -> 0
B15: 7 | D15: =+O14 -> 0 | E15: =$S$8*D15/1000 -> 0 | H15: =$S$8*G15/1000 -> 0 | I15: =+D15+G15 -> 0 | J15: =$S$8*I15/1000 -> 0 | K15: 0 | L15: =K15*S$6/1000 -> 0 | M15: =K15*S$8/1000 -> 0 | N15: =K15*S$7/1000 -> 0 | O15: =D15+G15-K15 -> 0 | P15: =$S$8*O15/1000 -> 0
B16: 8 | D16: =+O15 -> 0 | E16: =$S$8*D16/1000 -> 0 | H16: =$S$8*G16/1000 -> 0 | I16: =+D16+G16 -> 0 | J16: =$S$8*I16/1000 -> 0 | K16: 0 | L16: =K16*S$6/1000 -> 0 | M16: =K16*S$8/1000 -> 0 | N16: =K16*S$7/1000 -> 0 | O16: =D16+G16-K16 -> 0 | P16: =$S$8*O16/1000 -> 0
B17: 9 | D17: =+O16 -> 0 | E17: =$S$8*D17/1000 -> 0 | H17: =$S$8*G17/1000 -> 0 | I17: =+D17+G17 -> 0 | J17: =$S$8*I17/1000 -> 0 | K17: 0 | L17: =K17*S$6/1000 -> 0 | M17: =K17*S$8/1000 -> 0 | N17: =K17*S$7/1000 -> 0 | O17: =D17+G17-K17 -> 0 | P17: =$S$8*O17/1000 -> 0
B18: 10 | D18: =+O17 -> 0 | E18: =$S$8*D18/1000 -> 0 | H18: =$S$8*G18/1000 -> 0 | I18: =+D18+G18 -> 0 | J18: =$S$8*I18/1000 -> 0 | K18: 0 | L18: =K18*S$6/1000 -> 0 | M18: =K18*S$8/1000 -> 0 | N18: =K18*S$7/1000 -> 0 | O18: =D18+G18-K18 -> 0 | P18: =$S$8*O18/1000 -> 0
B19: 11 | D19: =+O18 -> 0 | E19: =$S$8*D19/1000 -> 0 | H19: =$S$8*G19/1000 -> 0 | I19: =+D19+G19 -> 0 | J19: =$S$8*I19/1000 -> 0 | K19: 0 | L19: =K19*S$6/1000 -> 0 | M19: =K19*S$8/1000 -> 0 | N19: =K19*S$7/1000 -> 0 | O19: =D19+G19-K19 -> 0 | P19: =$S$8*O19/1000 -> 0
B20: 12 | D20: =+O19 -> 0 | E20: =$S$8*D20/1000 -> 0 | H20: =$S$8*G20/1000 -> 0 | I20: =+D20+G20 -> 0 | J20: =$S$8*I20/1000 -> 0 | K20: 0 | L20: =K20*S$6/1000 -> 0 | M20: =K20*S$8/1000 -> 0 | N20: =K20*S$7/1000 -> 0 | O20: =D20+G20-K20 -> 0 | P20: =$S$8*O20/1000 -> 0
B21: 13 | D21: =+O20 -> 0 | E21: =$S$8*D21/1000 -> 0 | H21: =$S$8*G21/1000 -> 0 | I21: =+D21+G21 -> 0 | J21: =$S$8*I21/1000 -> 0 | K21: 0 | L21: =K21*S$6/1000 -> 0 | M21: =K21*S$8/1000 -> 0 | N21: =K21*S$7/1000 -> 0 | O21: =D21+G21-K21 -> 0 | P21: =$S$8*O21/1000 -> 0
B22: 14 | D22: =+O21 -> 0 | E22: =$S$8*D22/1000 -> 0 | H22: =$S$8*G22/1000 -> 0 | I22: =+D22+G22 -> 0 | J22: =$S$8*I22/1000 -> 0 | K22: 0 | L22: =K22*S$6/1000 -> 0 | M22: =K22*S$8/1000 -> 0 | N22: =K22*S$7/1000 -> 0 | O22: =D22+G22-K22 -> 0 | P22: =$S$8*O22/1000 -> 0
B23: 15 | D23: =+O22 -> 0 | E23: =$S$8*D23/1000 -> 0 | H23: =$S$8*G23/1000 -> 0 | I23: =+D23+G23 -> 0 | J23: =$S$8*I23/1000 -> 0 | L23: =K23*S$6/1000 -> 0 | M23: =K23*S$8/1000 -> 0 | N23: =K23*S$7/1000 -> 0 | O23: =D23+G23-K23 -> 0 | P23: =$S$8*O23/1000 -> 0
B24: 16 | D24: =+O23 -> 0 | E24: =$S$8*D24/1000 -> 0 | H24: =$S$8*G24/1000 -> 0 | I24: =+D24+G24 -> 0 | J24: =$S$8*I24/1000 -> 0 | K24: 0 | L24: =K24*S$6/1000 -> 0 | M24: =K24*S$8/1000 -> 0 | N24: =K24*S$7/1000 -> 0 | O24: =D24+G24-K24 -> 0 | P24: =$S$8*O24/1000 -> 0
B25: 17 | D25: =+O24 -> 0 | E25: =$S$8*D25/1000 -> 0 | H25: =$S$8*G25/1000 -> 0 | I25: =+D25+G25 -> 0 | J25: =$S$8*I25/1000 -> 0 | K25: 0 | L25: =K25*S$6/1000 -> 0 | M25: =K25*S$8/1000 -> 0 | N25: =K25*S$7/1000 -> 0 | O25: =D25+G25-K25 -> 0 | P25: =$S$8*O25/1000 -> 0
B26: 18 | D26: =+O25 -> 0 | E26: =$S$8*D26/1000 -> 0 | H26: =$S$8*G26/1000 -> 0 | I26: =+D26+G26 -> 0 | J26: =$S$8*I26/1000 -> 0 | K26: 0 | L26: =K26*S$6/1000 -> 0 | M26: =K26*S$8/1000 -> 0 | N26: =K26*S$7/1000 -> 0 | O26: =D26+G26-K26 -> 0 | P26: =$S$8*O26/1000 -> 0
B27: 19 | D27: =+O26 -> 0 | E27: =$S$8*D27/1000 -> 0 | H27: =$S$8*G27/1000 -> 0 | I27: =+D27+G27 -> 0 | J27: =$S$8*I27/1000 -> 0 | K27: 0 | L27: =K27*S$6/1000 -> 0 | M27: =K27*S$8/1000 -> 0 | N27: =K27*S$7/1000 -> 0 | O27: =D27+G27-K27 -> 0 | P27: =$S$8*O27/1000 -> 0
B28: 20 | D28: =+O27 -> 0 | E28: =$S$8*D28/1000 -> 0 | H28: =$S$8*G28/1000 -> 0 | I28: =+D28+G28 -> 0 | J28: =$S$8*I28/1000 -> 0 | K28: 0 | L28: =K28*S$6/1000 -> 0 | M28: =K28*S$8/1000 -> 0 | N28: =K28*S$7/1000 -> 0 | O28: =D28+G28-K28 -> 0 | P28: =$S$8*O28/1000 -> 0
B29: 21 | D29: =+O28 -> 0 | E29: =$S$8*D29/1000 -> 0 | H29: =$S$8*G29/1000 -> 0 | I29: =+D29+G29 -> 0 | J29: =$S$8*I29/1000 -> 0 | K29: 0 | L29: =K29*S$6/1000 -> 0 | M29: =K29*S$8/1000 -> 0 | N29: =K29*S$7/1000 -> 0 | O29: =D29+G29-K29 -> 0 | P29: =$S$8*O29/1000 -> 0
B30: 22 | D30: =+O29 -> 0 | E30: =$S$8*D30/1000 -> 0 | H30: =$S$8*G30/1000 -> 0 | I30: =+D30+G30 -> 0 | J30: =$S$8*I30/1000 -> 0 | K30: 0 | L30: =K30*S$6/1000 -> 0 | M30: =K30*S$8/1000 -> 0 | N30: =K30*S$7/1000 -> 0 | O30: =D30+G30-K30 -> 0 | P30: =$S$8*O30/1000 -> 0
B31: 23 | D31: =+O30 -> 0 | E31: =$S$8*D31/1000 -> 0 | H31: =$S$8*G31/1000 -> 0 | I31: =+D31+G31 -> 0 | J31: =$S$8*I31/1000 -> 0 | K31: 0 | L31: =K31*S$6/1000 -> 0 | M31: =K31*S$8/1000 -> 0 | N31: =K31*S$7/1000 -> 0 | O31: =D31+G31-K31 -> 0 | P31: =$S$8*O31/1000 -> 0
B32: 24 | D32: =+O31 -> 0 | E32: =$S$8*D32/1000 -> 0 | H32: =$S$8*G32/1000 -> 0 | I32: =+D32+G32 -> 0 | J32: =$S$8*I32/1000 -> 0 | K32: 0 | L32: =K32*S$6/1000 -> 0 | M32: =K32*S$8/1000 -> 0 | N32: =K32*S$7/1000 -> 0 | O32: =D32+G32-K32 -> 0 | P32: =$S$8*O32/1000 -> 0
B33: 25 | D33: =+O32 -> 0 | E33: =$S$8*D33/1000 -> 0 | H33: =$S$8*G33/1000 -> 0 | I33: =+D33+G33 -> 0 | J33: =$S$8*I33/1000 -> 0 | K33: 0 | L33: =K33*S$6/1000 -> 0 | M33: =K33*S$8/1000 -> 0 | N33: =K33*S$7/1000 -> 0 | O33: =D33+G33-K33 -> 0 | P33: =$S$8*O33/1000 -> 0
B34: 26 | D34: =+O33 -> 0 | E34: =$S$8*D34/1000 -> 0 | H34: =$S$8*G34/1000 -> 0 | I34: =+D34+G34 -> 0 | J34: =$S$8*I34/1000 -> 0 | K34: 0 | L34: =K34*S$6/1000 -> 0 | M34: =K34*S$8/1000 -> 0 | N34: =K34*S$7/1000 -> 0 | O34: =D34+G34-K34 -> 0 | P34: =$S$8*O34/1000 -> 0
B35: 27 | D35: =+O34 -> 0 | E35: =$S$8*D35/1000 -> 0 | H35: =$S$8*G35/1000 -> 0 | I35: =+D35+G35 -> 0 | J35: =$S$8*I35/1000 -> 0 | K35: 0 | L35: =K35*S$6/1000 -> 0 | M35: =K35*S$8/1000 -> 0 | N35: =K35*S$7/1000 -> 0 | O35: =D35+G35-K35 -> 0 | P35: =$S$8*O35/1000 -> 0
... B37: 29 | D37: =+O36 -> 0 | E37: =$S$8*D37/1000 -> 0 | H37: =$S$8*G37/1000 -> 0 | I37: =+D37+G37 -> 0 | J37: =$S$8*I37/1000 -> 0 | K37: 0 | L37: =K37*S$6/1000 -> 0 | M37: =K37*S$8/1000 -> 0 | N37: =K37*S$7/1000 -> 0 | O37: =D37+G37-K37 -> 0 | P37: =$S$8*O37/1000 -> 0
B38: 30 | D38: =+O37 -> 0 | E38: =$S$8*D38/1000 -> 0 | H38: =$S$8*G38/1000 -> 0 | I38: =+D38+G38 -> 0 | J38: =$S$8*I38/1000 -> 0 | L38: =K38*S$6/1000 -> 0 | M38: =K38*S$8/1000 -> 0 | N38: =K38*S$7/1000 -> 0 | O38: =D38+G38-K38 -> 0 | P38: =$S$8*O38/1000 -> 0
B39: 31 | D39: =+O38 -> 0 | E39: =$S$8*D39/1000 -> 0 | H39: =$S$8*G39/1000 -> 0 | I39: =+D39+G39 -> 0 | J39: =$S$8*I39/1000 -> 0 | L39: =K39*S$6/1000 -> 0 | M39: =K39*S$8/1000 -> 0 | N39: =K39*S$7/1000 -> 0 | O39: =D39+G39-K39 -> 0 | P39: =$S$8*O39/1000 -> 0
B40: TOTAL | F40: =SUM(F9:F39) -> 0 | G40: =SUM(G9:G39) -> 0 | H40: =SUM(H9:H39) -> 0 | K40: =SUM(K9:K39) -> 0 | L40: =SUM(L9:L39) -> 0 | N40: =SUM(N9:N39) -> 0 | R40: 40 | S40: 7 | U40: 40 | V40: 28.35 | X40: 1500
U41: =R40*S40/U40*V40*X40/1000 -> 297.675
B42: PACK SHEET | G42: =G40*S7/1000 -> 0 | H42: =+G40*S6/1000 -> 0 | J42: DESPATCH PACKSHEET | L42: =K40*S7/1000 -> 0 | S42: 0.75 | U42: =U41*S42% -> 2.2325625
U43: =U41+U42 -> 299.90756

Sheet 48-8.4-OZ  
B2: STOCK CARD- REF.NO
B3: THE EMPIRE JUTE MILL | R3: HESSIAN
B4: HESSIAN CLOTH 48-8.4 OZ 9X8 | R4: SACKING
A5: RAPIER NATURAL :- 1/B 1000 MTR | R5: YARN
B6: DATE | D6: OPENING BALANCE | G6: RECEIPT | I6: TOTAL | K6: ISSUES | M6: GROSS WT | O6: CLOSING BALLACE | Q6: REMARKS | R6: NET WGT. PER BALE | S6: 260.433
D7: NO.OF | E7: WEIGHT IN | G7: NO.OF | H7: WEIGHT IN | I7: NO.OF | J7: WEIGHT IN | K7: NO.OF | L7: NET WT | O7: NO.OF | P7: WEIGHT IN | R7: P.SHEET WGT | S7: 1.953
D8: BALE | E8: KGS | G8: BALE | H8: KGS | I8: BALE | J8: KGS | K8: BALE | L8: KGS | N8: PACK SHEET | O8: BALE | P8: KGS | R8: TOTAL WGT | S8: =S6+S7 -> 262.386
B9: 1 | E9: =$S$8*D9/1000 -> 0 | G9: 0 | H9: =$S$8*G9/1000 -> 0 | I9: 0 | J9: =$S$8*I9/1000 -> 0 | K9: 0 | L9: =K9*S$6/1000 -> 0 | M9: =K9*S$8/1000 -> 0 | N9: =K9*S$7/1000 -> 0 | O9: =D9+G9-K9 -> 0 | P9: =$S$8*O9/1000 -> 0 | Q9: =P9*T8/1000 -> 0
B10: 2 | E10: =$S$8*D10/1000 -> 0 | G10: 0 | H10: =$S$8*G10/1000 -> 0 | I10: 0 | J10: =$S$8*I10/1000 -> 0 | K10: 0 | L10: =$S$8*K10/1000 -> 0 | M10: =K10*S$8/1000 -> 0 | N10: =K10*S$7/1000 -> 0 | O10: =D10+G10-K10 -> 0 | P10: =$S$8*O10/1000 -> 0
B11: 3 | E11: =$S$8*D11/1000 -> 0 | G11: 0 | H11: =$S$8*G11/1000 -> 0 | I11: 0 | J11: =$S$8*I11/1000 -> 0 | K11: 0 | L11: =$S$8*K11/1000 -> 0 | M11: =K11*S$8/1000 -> 0 | N11: =K11*S$7/1000 -> 0 | O11: =D11+G11-K11 -> 0 | P11: =$S$8*O11/1000 -> 0
B12: 4 | E12: =$S$8*D12/1000 -> 0 | G12: 0 | H12: =$S$8*G12/1000 -> 0 | I12: 0 | J12: =$S$8*I12/1000 -> 0 | K12: 0 | L12: =$S$8*K12/1000 -> 0 | M12: =K12*S$8/1000 -> 0 | N12: =K12*S$7/1000 -> 0 | O12: =D12+G12-K12 -> 0 | P12: =$S$8*O12/1000 -> 0
B13: 5 | E13: =$S$8*D13/1000 -> 0 | G13: 0 | H13: =$S$8*G13/1000 -> 0 | I13: 0 | J13: =$S$8*I13/1000 -> 0 | K13: 0 | L13: =$S$8*K13/1000 -> 0 | M13: =K13*S$8/1000 -> 0 | N13: =K13*S$7/1000 -> 0 | O13: =D13+G13-K13 -> 0 | P13: =$S$8*O13/1000 -> 0
B14: 6 | E14: =$S$8*D14/1000 -> 0 | G14: 0 | H14: =$S$8*G14/1000 -> 0 | I14: 0 | J14: =$S$8*I14/1000 -> 0 | K14: 0 | L14: =$S$8*K14/1000 -> 0 | M14: =K14*S$8/1000 -> 0 | N14: =K14*S$7/1000 -> 0 | O14: =D14+G14-K14 -> 0 | P14: =$S$8*O14/1000 -> 0
B15: 7 | E15: =$S$8*D15/1000 -> 0 | G15: 0 | H15: =$S$8*G15/1000 -> 0 | I15: 0 | J15: =$S$8*I15/1000 -> 0 | K15: 0 | L15: =$S$8*K15/1000 -> 0 | M15: =K15*S$8/1000 -> 0 | N15: =K15*S$7/1000 -> 0 | O15: =D15+G15-K15 -> 0 | P15: =$S$8*O15/1000 -> 0
B16: 8 | E16: =$S$8*D16/1000 -> 0 | G16: 0 | H16: =$S$8*G16/1000 -> 0 | I16: 0 | J16: =$S$8*I16/1000 -> 0 | K16: 0 | L16: =$S$8*K16/1000 -> 0 | M16: =K16*S$8/1000 -> 0 | N16: =K16*S$7/1000 -> 0 | O16: =D16+G16-K16 -> 0 | P16: =$S$8*O16/1000 -> 0
B17: 9 | E17: =$S$8*D17/1000 -> 0 | G17: 0 | H17: =$S$8*G17/1000 -> 0 | I17: 0 | J17: =$S$8*I17/1000 -> 0 | K17: 0 | L17: =$S$8*K17/1000 -> 0 | M17: =K17*S$8/1000 -> 0 | N17: =K17*S$7/1000 -> 0 | O17: =D17+G17-K17 -> 0 | P17: =$S$8*O17/1000 -> 0
B18: 10 | E18: =$S$8*D18/1000 -> 0 | G18: 0 | H18: =$S$8*G18/1000 -> 0 | I18: 0 | J18: =$S$8*I18/1000 -> 0 | K18: 0 | L18: =$S$8*K18/1000 -> 0 | M18: =K18*S$8/1000 -> 0 | N18: =K18*S$7/1000 -> 0 | O18: =D18+G18-K18 -> 0 | P18: =$S$8*O18/1000 -> 0
B19: 11 | E19: =$S$8*D19/1000 -> 0 | G19: 0 | H19: =$S$8*G19/1000 -> 0 | I19: 0 | J19: =$S$8*I19/1000 -> 0 | K19: 0 | L19: =$S$8*K19/1000 -> 0 | M19: =K19*S$8/1000 -> 0 | N19: =K19*S$7/1000 -> 0 | O19: =D19+G19-K19 -> 0 | P19: =$S$8*O19/1000 -> 0
B20: 12 | E20: =$S$8*D20/1000 -> 0 | G20: 0 | H20: =$S$8*G20/1000 -> 0 | I20: 0 | J20: =$S$8*I20/1000 -> 0 | K20: 0 | L20: =$S$8*K20/1000 -> 0 | M20: =K20*S$8/1000 -> 0 | N20: =K20*S$7/1000 -> 0 | O20: =D20+G20-K20 -> 0 | P20: =$S$8*O20/1000 -> 0
B21: 13 | E21: =$S$8*D21/1000 -> 0 | G21: 0 | H21: =$S$8*G21/1000 -> 0 | I21: 0 | J21: =$S$8*I21/1000 -> 0 | K21: 0 | L21: =$S$8*K21/1000 -> 0 | M21: =K21*S$8/1000 -> 0 | N21: =K21*S$7/1000 -> 0 | O21: =D21+G21-K21 -> 0 | P21: =$S$8*O21/1000 -> 0
B22: 14 | D22: =+O21 -> 0 | E22: =$S$8*D22/1000 -> 0 | G22: 0 | H22: =$S$8*G22/1000 -> 0 | I22: 0 | J22: =$S$8*I22/1000 -> 0 | K22: 0 | L22: =$S$8*K22/1000 -> 0 | M22: =K22*S$8/1000 -> 0 | N22: =K22*S$7/1000 -> 0 | O22: =D22+G22-K22 -> 0 | P22: =$S$8*O22/1000 -> 0
B23: 15 | D23: =+O22 -> 0 | E23: =$S$8*D23/1000 -> 0 | G23: 0 | H23: =$S$8*G23/1000 -> 0 | I23: 0 | J23: =$S$8*I23/1000 -> 0 | K23: 0 | L23: =$S$8*K23/1000 -> 0 | M23: =K23*S$8/1000 -> 0 | N23: =K23*S$7/1000 -> 0 | O23: =D23+G23-K23 -> 0 | P23: =$S$8*O23/1000 -> 0
B24: 16 | D24: =+O23 -> 0 | E24: =$S$8*D24/1000 -> 0 | G24: 0 | H24: =$S$8*G24/1000 -> 0 | I24: 0 | J24: =$S$8*I24/1000 -> 0 | K24: 0 | L24: =$S$8*K24/1000 -> 0 | M24: =K24*S$8/1000 -> 0 | N24: =K24*S$7/1000 -> 0 | O24: =D24+G24-K24 -> 0 | P24: =$S$8*O24/1000 -> 0
B25: 17 | D25: =+O24 -> 0 | E25: =$S$8*D25/1000 -> 0 | G25: 0 | H25: =$S$8*G25/1000 -> 0 | I25: 0 | J25: =$S$8*I25/1000 -> 0 | K25: 0 | L25: =$S$8*K25/1000 -> 0 | M25: =K25*S$8/1000 -> 0 | N25: =K25*S$7/1000 -> 0 | O25: =D25+G25-K25 -> 0 | P25: =$S$8*O25/1000 -> 0
B26: 18 | D26: =+O25 -> 0 | E26: =$S$8*D26/1000 -> 0 | G26: 0 | H26: =$S$8*G26/1000 -> 0 | I26: 0 | J26: =$S$8*I26/1000 -> 0 | K26: 0 | L26: =$S$8*K26/1000 -> 0 | M26: =K26*S$8/1000 -> 0 | N26: =K26*S$7/1000 -> 0 | O26: =D26+G26-K26 -> 0 | P26: =$S$8*O26/1000 -> 0
B27: 19 | D27: =+O26 -> 0 | E27: =$S$8*D27/1000 -> 0 | G27: 0 | H27: =$S$8*G27/1000 -> 0 | I27: 0 | J27: =$S$8*I27/1000 -> 0 | K27: 0 | L27: =$S$8*K27/1000 -> 0 | M27: =K27*S$8/1000 -> 0 | N27: =K27*S$7/1000 -> 0 | O27: =D27+G27-K27 -> 0 | P27: =$S$8*O27/1000 -> 0
B28: 20 | D28: =+O27 -> 0 | E28: =$S$8*D28/1000 -> 0 | G28: 0 | H28: =$S$8*G28/1000 -> 0 | I28: 0 | J28: =$S$8*I28/1000 -> 0 | K28: 0 | L28: =$S$8*K28/1000 -> 0 | M28: =K28*S$8/1000 -> 0 | N28: =K28*S$7/1000 -> 0 | O28: =D28+G28-K28 -> 0 | P28: =$S$8*O28/1000 -> 0
B29: 21 | D29: =+O28 -> 0 | E29: =$S$8*D29/1000 -> 0 | G29: 0 | H29: =$S$8*G29/1000 -> 0 | I29: 0 | J29: =$S$8*I29/1000 -> 0 | K29: 0 | L29: =$S$8*K29/1000 -> 0 | M29: =K29*S$8/1000 -> 0 | N29: =K29*S$7/1000 -> 0 | O29: =D29+G29-K29 -> 0 | P29: =$S$8*O29/1000 -> 0
B30: 22 | D30: =+O29 -> 0 | E30: =$S$8*D30/1000 -> 0 | G30: 0 | H30: =$S$8*G30/1000 -> 0 | I30: 0 | J30: =$S$8*I30/1000 -> 0 | K30: 0 | L30: =$S$8*K30/1000 -> 0 | M30: =K30*S$8/1000 -> 0 | N30: =K30*S$7/1000 -> 0 | O30: =D30+G30-K30 -> 0 | P30: =$S$8*O30/1000 -> 0
B31: 23 | D31: =+O30 -> 0 | E31: =$S$8*D31/1000 -> 0 | G31: 0 | H31: =$S$8*G31/1000 -> 0 | I31: 0 | J31: =$S$8*I31/1000 -> 0 | K31: 0 | L31: =$S$8*K31/1000 -> 0 | M31: =K31*S$8/1000 -> 0 | N31: =K31*S$7/1000 -> 0 | O31: =D31+G31-K31 -> 0 | P31: =$S$8*O31/1000 -> 0
B32: 24 | D32: =+O31 -> 0 | E32: =$S$8*D32/1000 -> 0 | G32: 0 | H32: =$S$8*G32/1000 -> 0 | I32: 0 | J32: =$S$8*I32/1000 -> 0 | K32: 0 | L32: =$S$8*K32/1000 -> 0 | M32: =K32*S$8/1000 -> 0 | N32: =K32*S$7/1000 -> 0 | O32: =D32+G32-K32 -> 0 | P32: =$S$8*O32/1000 -> 0
B33: 25 | D33: =+O32 -> 0 | E33: =$S$8*D33/1000 -> 0 | G33: 0 | H33: =$S$8*G33/1000 -> 0 | I33: 0 | J33: =$S$8*I33/1000 -> 0 | K33: 0 | L33: =$S$8*K33/1000 -> 0 | M33: =K33*S$8/1000 -> 0 | N33: =K33*S$7/1000 -> 0 | O33: =D33+G33-K33 -> 0 | P33: =$S$8*O33/1000 -> 0
... B37: 29 | D37: =+O36 -> 0 | E37: =$S$8*D37/1000 -> 0 | G37: 0 | H37: =$S$8*G37/1000 -> 0 | I37: 0 | J37: =$S$8*I37/1000 -> 0 | K37: 0 | L37: =$S$8*K37/1000 -> 0 | M37: =K37*S$8/1000 -> 0 | N37: =K37*S$7/1000 -> 0 | O37: =D37+G37-K37 -> 0 | P37: =$S$8*O37/1000 -> 0
B38: 30 | D38: =+O37 -> 0 | E38: =$S$8*D38/1000 -> 0 | G38: 0 | H38: =$S$8*G38/1000 -> 0 | J38: =$S$8*I38/1000 -> 0 | L38: =$S$8*K38/1000 -> 0 | M38: =K38*S$8/1000 -> 0 | N38: =K38*S$7/1000 -> 0 | O38: =D38+G38-K38 -> 0 | P38: =$S$8*O38/1000 -> 0
B39: 31 | E39: =$S$8*D39/1000 -> 0 | H39: =$S$8*G39/1000 -> 0 | J39: =$S$8*I39/1000 -> 0 | L39: =$S$8*K39/1000 -> 0 | M39: =K39*S$8/1000 -> 0 | N39: =K39*S$7/1000 -> 0 | O39: =D39+G39-K39 -> 0 | P39: =$S$8*O39/1000 -> 0
B40: TOTAL | F40: =SUM(F9:F39) -> 0 | G40: =SUM(G9:G39) -> 0 | H40: =SUM(H9:H39) -> 0 | K40: =SUM(K9:K39) -> 0 | L40: =SUM(L9:L39) -> 0 | N40: =SUM(N9:N39) -> 0
B42: PACK SHEET | G42: =G40*S7/1000 -> 0 | I42: DESPATCH PACKSHEET | K42: =K40*S7/1000 -> 0

Sheet 40-6.5
B2: STOCK CARD- REF.NO | R2: MONTH | U2: YRAR | V2: 2023
B3: THE EMPIRE JUTE MILL | R3: HESSIAN
B4: HESSIAN CLOTH:-40-6.5 OZ | R4: SACKING
A5: :- 1/B 2000 YDS | R5: YARN
B6: DATE | D6: OPENING BALANCE | G6: RECEIPT | I6: TOTAL | K6: ISSUES | M6: GROSS WT | O6: CLOSING BALLACE | Q6: REMARKS | R6: NET WGT. PER BALE | S6: 368.55
D7: NO.OF | E7: WEIGHT IN | G7: NO.OF | H7: WEIGHT IN MT | I7: NO.OF | J7: WEIGHT IN | K7: NO.OF | L7: NET WT | O7: NO.OF | P7: WEIGHT IN | R7: P.SHEET WGT | S7: =+S6*0.75% -> 2.764125
D8: BALE | E8: KGS | G8: BALE | I8: BALE | J8: KGS | K8: BALE | L8: KGS | N8: PACK SHEET | O8: BALE | P8: KGS | R8: TOTAL WGT | S8: =S6+S7 -> 371.31412
B9: 1 | D9: 7 | E9: =$S$8*D9/1000 -> 2.5991989 | H9: =$S$8*G9/1000 -> 0 | I9: =D9+G9 -> 7 | J9: =$S$8*I9/1000 -> 2.5991989 | L9: =K9*S$6/1000 -> 0 | M9: =K9*S$8/1000 -> 0 | N9: =K9*S$7/1000 -> 0 | O9: =D9+G9-K9 -> 7 | P9: =$S$8*O9/1000 -> 2.5991989
B10: 2 | D10: =+O9 -> 7 | E10: =$S$8*D10/1000 -> 2.5991989 | H10: =$S$8*G10/1000 -> 0 | I10: =D10+G10 -> 7 | J10: =$S$8*I10/1000 -> 2.5991989 | L10: =K10*S$6/1000 -> 0 | M10: =K10*S$8/1000 -> 0 | N10: =K10*S$7/1000 -> 0 | O10: =I10-K10 -> 7 | P10: =$S$8*O10/1000 -> 2.5991989
B11: 3 | D11: =+O10 -> 7 | E11: =$S$8*D11/1000 -> 2.5991989 | G11: 0 | H11: =$S$8*G11/1000 -> 0 | I11: =D11+G11 -> 7 | J11: =$S$8*I11/1000 -> 2.5991989 | L11: =K11*S$6/1000 -> 0 | M11: =K11*S$8/1000 -> 0 | N11: =K11*S$7/1000 -> 0 | O11: =I11-K11 -> 7 | P11: =$S$8*O11/1000 -> 2.5991989
B12: 4 | D12: =+O11 -> 7 | E12: =$S$8*D12/1000 -> 2.5991989 | G12: 0 | H12: =$S$8*G12/1000 -> 0 | I12: =D12+G12 -> 7 | J12: =$S$8*I12/1000 -> 2.5991989 | L12: =K12*S$6/1000 -> 0 | M12: =K12*S$8/1000 -> 0 | N12: =K12*S$7/1000 -> 0 | O12: =I12-K12 -> 7 | P12: =$S$8*O12/1000 -> 2.5991989
B13: 5 | D13: =+O12 -> 7 | E13: =$S$8*D13/1000 -> 2.5991989 | G13: 2 | H13: =$S$8*G13/1000 -> 0.74262825 | I13: =D13+G13 -> 9 | J13: =$S$8*I13/1000 -> 3.3418271 | K13: 7 | L13: =K13*S$6/1000 -> 2.57985 | M13: =K13*S$8/1000 -> 2.5991989 | N13: =K13*S$7/1000 -> 0.019348875 | O13: =I13-K13 -> 2 | P13: =$S$8*O13/1000 -> 0.74262825
B14: 6 | D14: =+O13 -> 2 | E14: =$S$8*D14/1000 -> 0.74262825 | G14: 6 | H14: =$S$8*G14/1000 -> 2.2278848 | I14: =D14+G14 -> 8 | J14: =$S$8*I14/1000 -> 2.970513 | L14: =K14*S$6/1000 -> 0 | M14: =K14*S$8/1000 -> 0 | N14: =K14*S$7/1000 -> 0 | O14: =I14-K14 -> 8 | P14: =$S$8*O14/1000 -> 2.970513
B15: 7 | D15: =+O14 -> 8 | E15: =$S$8*D15/1000 -> 2.970513 | G15: 0 | H15: =$S$8*G15/1000 -> 0 | I15: =D15+G15 -> 8 | J15: =$S$8*I15/1000 -> 2.970513 | L15: =K15*S$6/1000 -> 0 | M15: =K15*S$8/1000 -> 0 | N15: =K15*S$7/1000 -> 0 | O15: =I15-K15 -> 8 | P15: =$S$8*O15/1000 -> 2.970513
B16: 8 | D16: =+O15 -> 8 | E16: =$S$8*D16/1000 -> 2.970513 | G16: 0 | H16: =$S$8*G16/1000 -> 0 | I16: =D16+G16 -> 8 | J16: =$S$8*I16/1000 -> 2.970513 | L16: =K16*S$6/1000 -> 0 | M16: =K16*S$8/1000 -> 0 | N16: =K16*S$7/1000 -> 0 | O16: =I16-K16 -> 8 | P16: =$S$8*O16/1000 -> 2.970513
B17: 9 | D17: =+O16 -> 8 | E17: =$S$8*D17/1000 -> 2.970513 | G17: 12 | H17: =$S$8*G17/1000 -> 4.4557695 | I17: =D17+G17 -> 20 | J17: =$S$8*I17/1000 -> 7.4262825 | L17: =K17*S$6/1000 -> 0 | M17: =K17*S$8/1000 -> 0 | N17: =K17*S$7/1000 -> 0 | O17: =I17-K17 -> 20 | P17: =$S$8*O17/1000 -> 7.4262825
B18: 10 | D18: =+O17 -> 20 | E18: =$S$8*D18/1000 -> 7.4262825 | H18: =$S$8*G18/1000 -> 0 | I18: =D18+G18 -> 20 | J18: =$S$8*I18/1000 -> 7.4262825 | L18: =K18*S$6/1000 -> 0 | M18: =K18*S$8/1000 -> 0 | N18: =K18*S$7/1000 -> 0 | O18: =I18-K18 -> 20 | P18: =$S$8*O18/1000 -> 7.4262825
B19: 11 | D19: =+O18 -> 20 | E19: =$S$8*D19/1000 -> 7.4262825 | H19: =$S$8*G19/1000 -> 0 | I19: =D19+G19 -> 20 | J19: =$S$8*I19/1000 -> 7.4262825 | L19: =K19*S$6/1000 -> 0 | M19: =K19*S$8/1000 -> 0 | N19: =K19*S$7/1000 -> 0 | O19: =I19-K19 -> 20 | P19: =$S$8*O19/1000 -> 7.4262825
B20: 12 | D20: =+O19 -> 20 | E20: =$S$8*D20/1000 -> 7.4262825 | G20: 7 | H20: =$S$8*G20/1000 -> 2.5991989 | I20: =D20+G20 -> 27 | J20: =$S$8*I20/1000 -> 10.025481 | L20: =K20*S$6/1000 -> 0 | M20: =K20*S$8/1000 -> 0 | N20: =K20*S$7/1000 -> 0 | O20: =I20-K20 -> 27 | P20: =$S$8*O20/1000 -> 10.025481
B21: 13 | D21: =+O20 -> 27 | E21: =$S$8*D21/1000 -> 10.025481 | H21: =$S$8*G21/1000 -> 0 | I21: =D21+G21 -> 27 | J21: =$S$8*I21/1000 -> 10.025481 | L21: =K21*S$6/1000 -> 0 | M21: =K21*S$8/1000 -> 0 | N21: =K21*S$7/1000 -> 0 | O21: =I21-K21 -> 27 | P21: =$S$8*O21/1000 -> 10.025481
B22: 14 | D22: =+O21 -> 27 | E22: =$S$8*D22/1000 -> 10.025481 | H22: =$S$8*G22/1000 -> 0 | I22: =D22+G22 -> 27 | J22: =$S$8*I22/1000 -> 10.025481 | L22: =K22*S$6/1000 -> 0 | M22: =K22*S$8/1000 -> 0 | N22: =K22*S$7/1000 -> 0 | O22: =I22-K22 -> 27 | P22: =$S$8*O22/1000 -> 10.025481
B23: 15 | D23: =+O22 -> 27 | E23: =$S$8*D23/1000 -> 10.025481 | H23: =$S$8*G23/1000 -> 0 | I23: =D23+G23 -> 27 | J23: =$S$8*I23/1000 -> 10.025481 | L23: =K23*S$6/1000 -> 0 | M23: =K23*S$8/1000 -> 0 | N23: =K23*S$7/1000 -> 0 | O23: =I23-K23 -> 27 | P23: =$S$8*O23/1000 -> 10.025481
B24: 16 | D24: =+O23 -> 27 | E24: =$S$8*D24/1000 -> 10.025481 | G24: 9 | H24: =$S$8*G24/1000 -> 3.3418271 | I24: =D24+G24 -> 36 | J24: =$S$8*I24/1000 -> 13.367309 | K24: 36 | L24: =K24*S$6/1000 -> 13.2678 | M24: =K24*S$8/1000 -> 13.367309 | N24: =K24*S$7/1000 -> 0.0995085 | O24: =I24-K24 -> 0 | P24: =$S$8*O24/1000 -> 0
B25: 17 | D25: =+O24 -> 0 | E25: =$S$8*D25/1000 -> 0 | H25: =$S$8*G25/1000 -> 0 | I25: =D25+G25 -> 0 | J25: =$S$8*I25/1000 -> 0 | L25: =K25*S$6/1000 -> 0 | M25: =K25*S$8/1000 -> 0 | N25: =K25*S$7/1000 -> 0 | O25: =I25-K25 -> 0 | P25: =$S$8*O25/1000 -> 0
B26: 18 | D26: =+O25 -> 0 | E26: =$S$8*D26/1000 -> 0 | H26: =$S$8*G26/1000 -> 0 | I26: =D26+G26 -> 0 | J26: =$S$8*I26/1000 -> 0 | L26: =K26*S$6/1000 -> 0 | M26: =K26*S$8/1000 -> 0 | N26: =K26*S$7/1000 -> 0 | O26: =I26-K26 -> 0 | P26: =$S$8*O26/1000 -> 0
B27: 19 | D27: =+O26 -> 0 | E27: =$S$8*D27/1000 -> 0 | H27: =$S$8*G27/1000 -> 0 | I27: =D27+G27 -> 0 | J27: =$S$8*I27/1000 -> 0 | L27: =K27*S$6/1000 -> 0 | M27: =K27*S$8/1000 -> 0 | N27: =K27*S$7/1000 -> 0 | O27: =I27-K27 -> 0 | P27: =$S$8*O27/1000 -> 0
B28: 20 | D28: =+O27 -> 0 | E28: =$S$8*D28/1000 -> 0 | H28: =$S$8*G28/1000 -> 0 | I28: =D28+G28 -> 0 | J28: =$S$8*I28/1000 -> 0 | L28: =K28*S$6/1000 -> 0 | M28: =K28*S$8/1000 -> 0 | N28: =K28*S$7/1000 -> 0 | O28: =I28-K28 -> 0 | P28: =$S$8*O28/1000 -> 0
B29: 21 | D29: =+O28 -> 0 | E29: =$S$8*D29/1000 -> 0 | H29: =$S$8*G29/1000 -> 0 | I29: =D29+G29 -> 0 | J29: =$S$8*I29/1000 -> 0 | L29: =K29*S$6/1000 -> 0 | M29: =K29*S$8/1000 -> 0 | N29: =K29*S$7/1000 -> 0 | O29: =I29-K29 -> 0 | P29: =$S$8*O29/1000 -> 0
B30: 22 | D30: =+O29 -> 0 | E30: =$S$8*D30/1000 -> 0 | G30: 6 | H30: =$S$8*G30/1000 -> 2.2278848 | I30: =D30+G30 -> 6 | J30: =$S$8*I30/1000 -> 2.2278848 | L30: =K30*S$6/1000 -> 0 | M30: =K30*S$8/1000 -> 0 | N30: =K30*S$7/1000 -> 0 | O30: =I30-K30 -> 6 | P30: =$S$8*O30/1000 -> 2.2278848
B31: 23 | D31: =+O30 -> 6 | E31: =$S$8*D31/1000 -> 2.2278848 | G31: 5 | H31: =$S$8*G31/1000 -> 1.8565706 | I31: =D31+G31 -> 11 | J31: =$S$8*I31/1000 -> 4.0844554 | L31: =K31*S$6/1000 -> 0 | M31: =K31*S$8/1000 -> 0 | N31: =K31*S$7/1000 -> 0 | O31: =I31-K31 -> 11 | P31: =$S$8*O31/1000 -> 4.0844554
B32: 24 | D32: =+O31 -> 11 | E32: =$S$8*D32/1000 -> 4.0844554 | G32: 12 | H32: =$S$8*G32/1000 -> 4.4557695 | I32: =D32+G32 -> 23 | J32: =$S$8*I32/1000 -> 8.5402249 | L32: =K32*S$6/1000 -> 0 | M32: =K32*S$8/1000 -> 0 | N32: =K32*S$7/1000 -> 0 | O32: =I32-K32 -> 23 | P32: =$S$8*O32/1000 -> 8.5402249
B33: 25 | D33: =+O32 -> 23 | E33: =$S$8*D33/1000 -> 8.5402249 | H33: =$S$8*G33/1000 -> 0 | I33: =D33+G33 -> 23 | J33: =$S$8*I33/1000 -> 8.5402249 | L33: =K33*S$6/1000 -> 0 | M33: =K33*S$8/1000 -> 0 | N33: =K33*S$7/1000 -> 0 | O33: =I33-K33 -> 23 | P33: =$S$8*O33/1000 -> 8.5402249
B34: 26 | D34: =+O33 -> 23 | E34: =$S$8*D34/1000 -> 8.5402249 | G34: 4 | H34: =$S$8*G34/1000 -> 1.4852565 | I34: =D34+G34 -> 27 | J34: =$S$8*I34/1000 -> 10.025481 | L34: =K34*S$6/1000 -> 0 | M34: =K34*S$8/1000 -> 0 | N34: =K34*S$7/1000 -> 0 | O34: =I34-K34 -> 27 | P34: =$S$8*O34/1000 -> 10.025481
B35: 27 | D35: =+O34 -> 27 | E35: =$S$8*D35/1000 -> 10.025481 | G35: 9 | H35: =$S$8*G35/1000 -> 3.3418271 | I35: =D35+G35 -> 36 | J35: =$S$8*I35/1000 -> 13.367309 | K35: 30 | L35: =K35*S$6/1000 -> 11.0565 | M35: =K35*S$8/1000 -> 11.139424 | N35: =K35*S$7/1000 -> 0.08292375 | O35: =I35-K35 -> 6 | P35: =$S$8*O35/1000 -> 2.2278848
B36: 28 | D36: =+O35 -> 6 | E36: =$S$8*D36/1000 -> 2.2278848 | H36: =$S$8*G36/1000 -> 0 | I36: =D36+G36 -> 6 | J36: =$S$8*I36/1000 -> 2.2278848 | L36: =K36*S$6/1000 -> 0 | M36: =K36*S$8/1000 -> 0 | N36: =K36*S$7/1000 -> 0 | O36: =I36-K36 -> 6 | P36: =$S$8*O36/1000 -> 2.2278848
B37: 29 | D37: =+O36 -> 6 | E37: =$S$8*D37/1000 -> 2.2278848 | G37: 4 | H37: =$S$8*G37/1000 -> 1.4852565 | I37: =D37+G37 -> 10 | J37: =$S$8*I37/1000 -> 3.7131412 | L37: =K37*S$6/1000 -> 0 | M37: =K37*S$8/1000 -> 0 | N37: =K37*S$7/1000 -> 0 | O37: =I37-K37 -> 10 | P37: =$S$8*O37/1000 -> 3.7131412
B38: 30 | D38: =+O37 -> 10 | E38: =$S$8*D38/1000 -> 3.7131412 | G38: 7 | H38: =$S$8*G38/1000 -> 2.5991989 | I38: =D38+G38 -> 17 | J38: =$S$8*I38/1000 -> 6.3123401 | L38: =K38*S$6/1000 -> 0 | M38: =K38*S$8/1000 -> 0 | N38: =K38*S$7/1000 -> 0 | O38: =I38-K38 -> 17 | P38: =$S$8*O38/1000 -> 6.3123401
B39: 31 | D39: =+O38 -> 17 | E39: =$S$8*D39/1000 -> 6.3123401 | G39: 2 | H39: =$S$8*G39/1000 -> 0.74262825 | I39: =D39+G39 -> 19 | J39: =$S$8*I39/1000 -> 7.0549684 | L39: =K39*S$6/1000 -> 0 | M39: =K39*S$8/1000 -> 0 | N39: =K39*S$7/1000 -> 0 | O39: =I39-K39 -> 19 | P39: =$S$8*O39/1000 -> 7.0549684
B40: TOTAL | F40: =SUM(F9:F39) -> 0 | G40: =SUM(G9:G39) -> 85 | H40: =SUM(H9:H39) -> 31.561701 | K40: =SUM(K9:K39) -> 73 | L40: =SUM(L9:L39) -> 26.90415 | M40: =SUM(M9:M39) -> 27.105931 | N40: =SUM(N9:N39) -> 0.20178113
B42: PACK SHEET | G42: =G40*S7/1000 -> 0.23495062 | H42: =+G40*S6/1000 -> 31.32675 | J42: DESPATCH PACKSHEET | L42: =K40*S7/1000 -> 0.20178113

Sheet 51-11.36-OZ 
B2: STOCK CARD- REF.NO
B3: THE EMPIRE JUTE MILL | R3: HESSIAN
B4: HESSIAN CLOTH 51-11.36 OZ 8X8 BOX STRIPE | R4: SACKING
A5: RAPIER NATURAL :- 1/B 500 MTRS | R5: YARN
B6: DATE | D6: OPENING BALANCE | G6: RECEIPT | I6: TOTAL | K6: ISSUES | M6: GROSS WT | O6: CLOSING BALLACE | Q6: REMARKS | R6: NET WGT. PER BALE | S6: 175.792
D7: NO.OF | E7: WEIGHT IN | G7: NO.OF | H7: WEIGHT IN | I7: NO.OF | J7: WEIGHT IN | K7: NO.OF | L7: NET WT | O7: NO.OF | P7: WEIGHT IN | R7: P.SHEET WGT | S7: 1.318
D8: BALE | E8: KGS | G8: BALE | H8: KGS | I8: BALE | J8: KGS | K8: BALE | L8: KGS | N8: PACK SHEET | O8: BALE | P8: KGS | R8: TOTAL WGT | S8: =S6+S7 -> 177.11
B9: 1 | E9: =$S$8*D9/1000 -> 0 | G9: 0 | H9: =$S$8*G9/1000 -> 0 | I9: 0 | J9: =$S$8*I9/1000 -> 0 | L9: =K9*S$6/1000 -> 0 | M9: =K9*S$8/1000 -> 0 | N9: =K9*S$7/1000 -> 0 | O9: =D9+G9-K9 -> 0 | P9: =$S$8*O9/1000 -> 0
B10: 2 | D10: =+O9 -> 0 | E10: =$S$8*D10/1000 -> 0 | G10: 0 | H10: =$S$8*G10/1000 -> 0 | I10: 0 | J10: =$S$8*I10/1000 -> 0 | L10: =K10*S$6/1000 -> 0 | M10: =K10*S$8/1000 -> 0 | N10: =K10*S$7/1000 -> 0 | O10: =D10+G10-K10 -> 0 | P10: =$S$8*O10/1000 -> 0
B11: 3 | D11: =+O10 -> 0 | E11: =$S$8*D11/1000 -> 0 | G11: 0 | H11: =$S$8*G11/1000 -> 0 | I11: 0 | J11: =$S$8*I11/1000 -> 0 | L11: =K11*S$6/1000 -> 0 | M11: =K11*S$8/1000 -> 0 | N11: =K11*S$7/1000 -> 0 | O11: =D11+G11-K11 -> 0 | P11: =$S$8*O11/1000 -> 0
B12: 4 | D12: =+O11 -> 0 | E12: =$S$8*D12/1000 -> 0 | G12: 0 | H12: =$S$8*G12/1000 -> 0 | I12: 0 | J12: =$S$8*I12/1000 -> 0 | L12: =K12*S$6/1000 -> 0 | M12: =K12*S$8/1000 -> 0 | N12: =K12*S$7/1000 -> 0 | O12: =D12+G12-K12 -> 0 | P12: =$S$8*O12/1000 -> 0
B13: 5 | D13: =+O12 -> 0 | E13: =$S$8*D13/1000 -> 0 | G13: 0 | H13: =$S$8*G13/1000 -> 0 | I13: 0 | J13: =$S$8*I13/1000 -> 0 | L13: =K13*S$6/1000 -> 0 | M13: =K13*S$8/1000 -> 0 | N13: =K13*S$7/1000 -> 0 | O13: =D13+G13-K13 -> 0 | P13: =$S$8*O13/1000 -> 0
B14: 6 | D14: =+O13 -> 0 | E14: =$S$8*D14/1000 -> 0 | G14: 0 | H14: =$S$8*G14/1000 -> 0 | I14: 0 | J14: =$S$8*I14/1000 -> 0 | L14: =K14*S$6/1000 -> 0 | M14: =K14*S$8/1000 -> 0 | N14: =K14*S$7/1000 -> 0 | O14: =D14+G14-K14 -> 0 | P14: =$S$8*O14/1000 -> 0
B15: 7 | D15: =+O14 -> 0 | E15: =$S$8*D15/1000 -> 0 | G15: 0 | H15: =$S$8*G15/1000 -> 0 | I15: 0 | J15: =$S$8*I15/1000 -> 0 | L15: =K15*S$6/1000 -> 0 | M15: =K15*S$8/1000 -> 0 | N15: =K15*S$7/1000 -> 0 | O15: =D15+G15-K15 -> 0 | P15: =$S$8*O15/1000 -> 0
B16: 8 | D16: =+O15 -> 0 | E16: =$S$8*D16/1000 -> 0 | G16: 0 | H16: =$S$8*G16/1000 -> 0 | I16: 0 | J16: =$S$8*I16/1000 -> 0 | L16: =K16*S$6/1000 -> 0 | M16: =K16*S$8/1000 -> 0 | N16: =K16*S$7/1000 -> 0 | O16: =D16+G16-K16 -> 0 | P16: =$S$8*O16/1000 -> 0
B17: 9 | D17: =+O16 -> 0 | E17: =$S$8*D17/1000 -> 0 | G17: 0 | H17: =$S$8*G17/1000 -> 0 | I17: 0 | J17: =$S$8*I17/1000 -> 0 | L17: =K17*S$6/1000 -> 0 | M17: =K17*S$8/1000 -> 0 | N17: =K17*S$7/1000 -> 0 | O17: =D17+G17-K17 -> 0 | P17: =$S$8*O17/1000 -> 0
B18: 10 | D18: =+O17 -> 0 | E18: =$S$8*D18/1000 -> 0 | G18: 0 | H18: =$S$8*G18/1000 -> 0 | I18: 0 | J18: =$S$8*I18/1000 -> 0 | L18: =K18*S$6/1000 -> 0 | M18: =K18*S$8/1000 -> 0 | N18: =K18*S$7/1000 -> 0 | O18: =D18+G18-K18 -> 0 | P18: =$S$8*O18/1000 -> 0
B19: 11 | D19: =+O18 -> 0 | E19: =$S$8*D19/1000 -> 0 | G19: 0 | H19: =$S$8*G19/1000 -> 0 | I19: 0 | J19: =$S$8*I19/1000 -> 0 | L19: =K19*S$6/1000 -> 0 | M19: =K19*S$8/1000 -> 0 | N19: =K19*S$7/1000 -> 0 | O19: =D19+G19-K19 -> 0 | P19: =$S$8*O19/1000 -> 0
B20: 12 | D20: =+O19 -> 0 | E20: =$S$8*D20/1000 -> 0 | G20: 0 | H20: =$S$8*G20/1000 -> 0 | I20: 0 | J20: =$S$8*I20/1000 -> 0 | L20: =K20*S$6/1000 -> 0 | M20: =K20*S$8/1000 -> 0 | N20: =K20*S$7/1000 -> 0 | O20: =D20+G20-K20 -> 0 | P20: =$S$8*O20/1000 -> 0
B21: 13 | D21: =+O20 -> 0 | E21: =$S$8*D21/1000 -> 0 | G21: 0 | H21: =$S$8*G21/1000 -> 0 | I21: 0 | J21: =$S$8*I21/1000 -> 0 | L21: =K21*S$6/1000 -> 0 | M21: =K21*S$8/1000 -> 0 | N21: =K21*S$7/1000 -> 0 | O21: =D21+G21-K21 -> 0 | P21: =$S$8*O21/1000 -> 0
... B37: 29 | D37: =+O36 -> 0 | E37: =$S$8*D37/1000 -> 0 | G37: 0 | H37: =$S$8*G37/1000 -> 0 | I37: 0 | J37: =$S$8*I37/1000 -> 0 | L37: =K37*S$6/1000 -> 0 | M37: =K37*S$8/1000 -> 0 | N37: =K37*S$7/1000 -> 0 | O37: =D37+G37-K37 -> 0 | P37: =$S$8*O37/1000 -> 0
B38: 30 | D38: =+O37 -> 0 | E38: =$S$8*D38/1000 -> 0 | H38: =$S$8*G38/1000 -> 0 | J38: =$S$8*I38/1000 -> 0 | L38: =K38*S$6/1000 -> 0 | M38: =K38*S$8/1000 -> 0 | N38: =K38*S$7/1000 -> 0 | O38: =D38+G38-K38 -> 0 | P38: =$S$8*O38/1000 -> 0
B39: 31 | D39: =+O38 -> 0 | E39: =$S$8*D39/1000 -> 0 | H39: =$S$8*G39/1000 -> 0 | J39: =$S$8*I39/1000 -> 0 | L39: =K39*S$6/1000 -> 0 | M39: =K39*S$8/1000 -> 0 | N39: =K39*S$7/1000 -> 0 | O39: =D39+G39-K39 -> 0 | P39: =$S$8*O39/1000 -> 0
B40: TOTAL | F40: =SUM(F9:F39) -> 0 | G40: =SUM(G9:G39) -> 0 | H40: =SUM(H9:H39) -> 0 | K40: =SUM(K9:K39) -> 0 | L40: =SUM(L9:L39) -> 0 | N40: =SUM(N9:N39) -> 0
B42: PACK SHEET | G42: =G40*S7/1000 -> 0 | H42: =+G39*S6/1000 -> 0 | J42: DESPATCH PACKSHEET | L42: =K40*S7/1000 -> 0

Sheet 48-7.80 EXP
B2: STOCK CARD- REF.NO | R2: MONTH | S2: FEB | U2: YRAR | V2: 2023
B3: THE EMPIRE JUTE MILL | R3: HESSIAN
B4: EXPORT :- 48-7.80-OZ 198 GRM/MTR | R4: SACKING
A5: I/B:- 1828.80 MTR | R5: YARN
B6: DATE | D6: OPENING BALANCE | G6: RECEIPT | I6: TOTAL | K6: ISSUES | M6: GROSS WT | O6: CLOSING BALLACE | Q6: REMARKS | R6: NET WGT. PER BALE | S6: 442.395
D7: NO.OF | E7: WEIGHT IN | G7: NO.OF | H7: WEIGHT IN | I7: NO.OF | J7: WEIGHT IN | K7: NO.OF | L7: NET WT | O7: NO.OF | P7: WEIGHT IN | R7: P.SHEET WGT | S7: 3.318
D8: BALE | E8: KGS | G8: BALE | H8: KGS | I8: BALE | J8: KGS | K8: BALE | L8: KGS | N8: PACK SHEET | O8: BALE | P8: KGS | R8: TOTAL WGT | S8: =S6+S7 -> 445.713
B9: 1 | E9: =$S$8*D9/1000 -> 0 | H9: =$S$8*G9/1000 -> 0 | I9: =+D9+G9 -> 0 | J9: =$S$8*I9/1000 -> 0 | L9: =$S$8*K9/1000 -> 0 | M9: =K9*S$8/1000 -> 0 | N9: =$S$7*L9/1000 -> 0 | O9: =+I9-K9 -> 0 | P9: =O9*S$8/1000 -> 0
B10: 2 | E10: =$S$8*D10/1000 -> 0 | H10: =$S$8*G10/1000 -> 0 | I10: =+D10+G10 -> 0 | J10: =$S$8*I10/1000 -> 0 | L10: =$S$8*K10/1000 -> 0 | M10: =K10*S$8/1000 -> 0 | N10: =$S$7*L10/1000 -> 0 | O10: =I10-K10 -> 0 | P10: =O10*S$8/1000 -> 0
B11: 3 | E11: =$S$8*D11/1000 -> 0 | H11: =$S$8*G11/1000 -> 0 | I11: =+D11+G11 -> 0 | J11: =$S$8*I11/1000 -> 0 | L11: =$S$8*K11/1000 -> 0 | M11: =K11*S$8/1000 -> 0 | N11: =$S$7*L11/1000 -> 0 | O11: =I11-K11 -> 0 | P11: =O11*S$8/1000 -> 0
B12: 4 | E12: =$S$8*D12/1000 -> 0 | H12: =$S$8*G12/1000 -> 0 | I12: =+D12+G12 -> 0 | J12: =$S$8*I12/1000 -> 0 | L12: =$S$8*K12/1000 -> 0 | M12: =K12*S$8/1000 -> 0 | N12: =$S$7*L12/1000 -> 0 | O12: =I12-K12 -> 0 | P12: =O12*S$8/1000 -> 0
B13: 5 | E13: =$S$8*D13/1000 -> 0 | H13: =$S$8*G13/1000 -> 0 | I13: =+D13+G13 -> 0 | J13: =$S$8*I13/1000 -> 0 | L13: =$S$8*K13/1000 -> 0 | M13: =K13*S$8/1000 -> 0 | N13: =$S$7*L13/1000 -> 0 | O13: =I13-K13 -> 0 | P13: =O13*S$8/1000 -> 0
B14: 6 | E14: =$S$8*D14/1000 -> 0 | H14: =$S$8*G14/1000 -> 0 | I14: =+D14+G14 -> 0 | J14: =$S$8*I14/1000 -> 0 | L14: =$S$8*K14/1000 -> 0 | M14: =K14*S$8/1000 -> 0 | N14: =$S$7*L14/1000 -> 0 | O14: =I14-K14 -> 0 | P14: =O14*S$8/1000 -> 0
B15: 7 | E15: =$S$8*D15/1000 -> 0 | H15: =$S$8*G15/1000 -> 0 | I15: =+D15+G15 -> 0 | J15: =$S$8*I15/1000 -> 0 | L15: =$S$8*K15/1000 -> 0 | M15: =K15*S$8/1000 -> 0 | N15: =$S$7*L15/1000 -> 0 | O15: =I15-K15 -> 0 | P15: =O15*S$8/1000 -> 0
B16: 8 | E16: =$S$8*D16/1000 -> 0 | H16: =$S$8*G16/1000 -> 0 | I16: =+D16+G16 -> 0 | J16: =$S$8*I16/1000 -> 0 | L16: =$S$8*K16/1000 -> 0 | M16: =K16*S$8/1000 -> 0 | N16: =$S$7*L16/1000 -> 0 | O16: =I16-K16 -> 0 | P16: =O16*S$8/1000 -> 0
B17: 9 | E17: =$S$8*D17/1000 -> 0 | H17: =$S$8*G17/1000 -> 0 | I17: =+D17+G17 -> 0 | J17: =$S$8*I17/1000 -> 0 | L17: =$S$8*K17/1000 -> 0 | M17: =K17*S$8/1000 -> 0 | N17: =$S$7*L17/1000 -> 0 | O17: =+I17-K17 -> 0 | P17: =O17*S$8/1000 -> 0
B18: 10 | E18: =$S$8*D18/1000 -> 0 | H18: =$S$8*G18/1000 -> 0 | I18: =+D18+G18 -> 0 | J18: =$S$8*I18/1000 -> 0 | L18: =$S$8*K18/1000 -> 0 | M18: =K18*S$8/1000 -> 0 | N18: =$S$7*L18/1000 -> 0 | O18: =+I18-K18 -> 0 | P18: =O18*S$8/1000 -> 0
B19: 11 | E19: =$S$8*D19/1000 -> 0 | H19: =$S$8*G19/1000 -> 0 | I19: =+D19+G19 -> 0 | J19: =$S$8*I19/1000 -> 0 | L19: =$S$8*K19/1000 -> 0 | M19: =K19*S$8/1000 -> 0 | N19: =$S$7*L19/1000 -> 0 | O19: =+I19-K19 -> 0 | P19: =O19*S$8/1000 -> 0
B20: 12 | E20: =$S$8*D20/1000 -> 0 | H20: =$S$8*G20/1000 -> 0 | I20: =+D20+G20 -> 0 | J20: =$S$8*I20/1000 -> 0 | L20: =$S$8*K20/1000 -> 0 | M20: =K20*S$8/1000 -> 0 | N20: =$S$7*L20/1000 -> 0 | O20: =+I20-K20 -> 0 | P20: =O20*S$8/1000 -> 0
B21: 13 | E21: =$S$8*D21/1000 -> 0 | H21: =$S$8*G21/1000 -> 0 | I21: =+D21+G21 -> 0 | J21: =$S$8*I21/1000 -> 0 | L21: =$S$8*K21/1000 -> 0 | M21: =K21*S$8/1000 -> 0 | N21: =$S$7*L21/1000 -> 0 | O21: =+I21-K21 -> 0 | P21: =O21*S$8/1000 -> 0
B22: 14 | E22: =$S$8*D22/1000 -> 0 | H22: =$S$8*G22/1000 -> 0 | I22: =+D22+G22 -> 0 | J22: =$S$8*I22/1000 -> 0 | L22: =$S$8*K22/1000 -> 0 | M22: =K22*S$8/1000 -> 0 | N22: =$S$7*L22/1000 -> 0 | O22: =+I22-K22 -> 0 | P22: =O22*S$8/1000 -> 0
B23: 15 | E23: =$S$8*D23/1000 -> 0 | H23: =$S$8*G23/1000 -> 0 | I23: =+D23+G23 -> 0 | J23: =$S$8*I23/1000 -> 0 | L23: =$S$8*K23/1000 -> 0 | M23: =K23*S$8/1000 -> 0 | N23: =$S$7*L23/1000 -> 0 | O23: =+I23-K23 -> 0 | P23: =O23*S$8/1000 -> 0
B24: 16 | E24: =$S$8*D24/1000 -> 0 | H24: =$S$8*G24/1000 -> 0 | I24: =+D24+G24 -> 0 | J24: =$S$8*I24/1000 -> 0 | L24: =$S$8*K24/1000 -> 0 | M24: =K24*S$8/1000 -> 0 | N24: =$S$7*L24/1000 -> 0 | O24: =+I24-K24 -> 0 | P24: =O24*S$8/1000 -> 0
B25: 17 | E25: =$S$8*D25/1000 -> 0 | H25: =$S$8*G25/1000 -> 0 | I25: =+D25+G25 -> 0 | J25: =$S$8*I25/1000 -> 0 | L25: =$S$8*K25/1000 -> 0 | M25: =K25*S$8/1000 -> 0 | N25: =$S$7*L25/1000 -> 0 | O25: =+I25-K25 -> 0 | P25: =O25*S$8/1000 -> 0
B26: 18 | E26: =$S$8*D26/1000 -> 0 | H26: =$S$8*G26/1000 -> 0 | I26: =+D26+G26 -> 0 | J26: =$S$8*I26/1000 -> 0 | L26: =$S$8*K26/1000 -> 0 | M26: =K26*S$8/1000 -> 0 | N26: =$S$7*L26/1000 -> 0 | O26: =+I26-K26 -> 0 | P26: =O26*S$8/1000 -> 0
B27: 19 | E27: =$S$8*D27/1000 -> 0 | H27: =$S$8*G27/1000 -> 0 | I27: =+D27+G27 -> 0 | J27: =$S$8*I27/1000 -> 0 | L27: =$S$8*K27/1000 -> 0 | M27: =K27*S$8/1000 -> 0 | N27: =$S$7*L27/1000 -> 0 | O27: =+I27-K27 -> 0 | P27: =O27*S$8/1000 -> 0
B28: 20 | E28: =$S$8*D28/1000 -> 0 | H28: =$S$8*G28/1000 -> 0 | I28: =+D28+G28 -> 0 | J28: =$S$8*I28/1000 -> 0 | L28: =$S$8*K28/1000 -> 0 | M28: =K28*S$8/1000 -> 0 | N28: =$S$7*L28/1000 -> 0 | O28: =+I28-K28 -> 0 | P28: =O28*S$8/1000 -> 0
... B37: 29 | E37: =$S$8*D37/1000 -> 0 | H37: =$S$8*G37/1000 -> 0 | I37: =+D37+G37 -> 0 | J37: =$S$8*I37/1000 -> 0 | L37: =$S$8*K37/1000 -> 0 | M37: =K37*S$8/1000 -> 0 | N37: =$S$7*L37/1000 -> 0 | O37: =+I37-K37 -> 0 | P37: =O37*S$8/1000 -> 0
B38: 30 | E38: =$S$8*D38/1000 -> 0 | H38: =$S$8*G38/1000 -> 0 | I38: =+D38+G38 -> 0 | J38: =$S$8*I38/1000 -> 0 | L38: =K38*S6/1000 -> 0 | M38: =K38*S$8/1000 -> 0 | N38: =K38*S7/1000 -> 0 | O38: =+I38-K38 -> 0 | P38: =O38*S$8/1000 -> 0
B39: 31 | E39: =$S$8*D39/1000 -> 0 | H39: =$S$8*G39/1000 -> 0 | I39: =+D39+G39 -> 0 | J39: =$S$8*I39/1000 -> 0 | L39: =$S$8*K39/1000 -> 0 | M39: =K39*S$8/1000 -> 0 | N39: =$S$7*L39/1000 -> 0 | O39: =+I39-K39 -> 0 | P39: =O39*S$8/1000 -> 0
B40: TOTAL | F40: =SUM(F9:F39) -> 0 | G40: =SUM(G9:G39) -> 0 | H40: =SUM(H9:H39) -> 0 | K40: =SUM(K9:K39) -> 0 | L40: =SUM(L9:L39) -> 0 | M40: =SUM(M9:M39) -> 0 | N40: =SUM(N9:N39) -> 0
B42: PACK SHEET | E42: =G40*S7/1000 -> 0 | J42: DESPATCH PACKSHEET | L42: =K40*S7/1000 -> 0

Sheet 40-5-OZ-EXP
B2: STOCK CARD- REF.NO
B3: THE EMPIRE JUTE MILL | R3: HESSIAN
B4: 101.5 CM 153.GM/SQR MTR (40-5-OZ) | R4: SACKING
A5: I/B-1828.80 MTR | R5: YARN
B6: DATE | D6: OPENING BALANCE | G6: RECEIPT | I6: TOTAL | K6: ISSUES | M6: GROSS WT | O6: CLOSING BALLACE | Q6: REMARKS | R6: NET WGT. PER BALE | S6: 279.806
D7: NO.OF | E7: WEIGHT IN | G7: NO.OF | H7: WEIGHT IN | I7: NO.OF | J7: WEIGHT IN | K7: NO.OF | L7: NET WT | O7: NO.OF | P7: WEIGHT IN | R7: P.SHEET WGT | S7: 2.099
D8: BALE | E8: KGS | G8: BALE | H8: KGS | I8: BALE | J8: KGS | K8: BALE | L8: KGS | N8: PACK SHEET | O8: BALE | P8: KGS | R8: TOTAL WGT | S8: =S6+S7 -> 281.905
B9: 1 | E9: =D9*S$8/1000 -> 0 | H9: =G9*S6/1000 -> 0 | I9: =SUM(D9+G9) -> 0 | J9: =I9*S6/1000 -> 0 | K9: 0 | L9: =K9*S6/1000 -> 0 | M9: =K9*S$8/1000 -> 0 | N9: =$S$7*L9/1000 -> 0 | O9: =SUM(I9-K9) -> 0 | P9: =O9*S$8/1000 -> 0
B10: 2 | E10: =D10*S$8/1000 -> 0 | G10: 0 | H10: =G10*S7/1000 -> 0 | I10: =SUM(D10+G10) -> 0 | J10: =I10*S7/1000 -> 0 | K10: 0 | L10: =K10*S7/1000 -> 0 | M10: =K10*S$8/1000 -> 0 | N10: =$S$7*L10/1000 -> 0 | O10: =SUM(I10-K10) -> 0 | P10: =O10*S$8/1000 -> 0
B11: 3 | E11: =D11*S$8/1000 -> 0 | G11: 0 | H11: =G11*S8/1000 -> 0 | I11: =SUM(D11+G11) -> 0 | J11: =I11*S8/1000 -> 0 | K11: 0 | L11: =K11*S8/1000 -> 0 | M11: =K11*S$8/1000 -> 0 | N11: =$S$7*L11/1000 -> 0 | O11: =SUM(I11-K11) -> 0 | P11: =O11*S$8/1000 -> 0
B12: 4 | E12: =D12*S$8/1000 -> 0 | G12: 0 | H12: =G12*S9/1000 -> 0 | I12: =SUM(D12+G12) -> 0 | J12: =I12*S9/1000 -> 0 | K12: 0 | L12: =K12*S9/1000 -> 0 | M12: =K12*S$8/1000 -> 0 | N12: =$S$7*L12/1000 -> 0 | O12: =SUM(I12-K12) -> 0 | P12: =O12*S$8/1000 -> 0
B13: 5 | E13: =D13*S$8/1000 -> 0 | G13: 0 | H13: =G13*S10/1000 -> 0 | I13: =SUM(D13+G13) -> 0 | J13: =I13*S10/1000 -> 0 | K13: 0 | L13: =K13*S10/1000 -> 0 | M13: =K13*S$8/1000 -> 0 | N13: =$S$7*L13/1000 -> 0 | O13: =SUM(I13-K13) -> 0 | P13: =O13*S$8/1000 -> 0
B14: 6 | E14: =D14*S$8/1000 -> 0 | G14: 0 | H14: =G14*S11/1000 -> 0 | I14: =SUM(D14+G14) -> 0 | J14: =I14*S11/1000 -> 0 | K14: 0 | L14: =K14*S11/1000 -> 0 | M14: =K14*S$8/1000 -> 0 | N14: =$S$7*L14/1000 -> 0 | O14: =SUM(I14-K14) -> 0 | P14: =O14*S$8/1000 -> 0
B15: 7 | E15: =D15*S$8/1000 -> 0 | G15: 0 | H15: =G15*S12/1000 -> 0 | I15: =SUM(D15+G15) -> 0 | J15: =I15*S12/1000 -> 0 | K15: 0 | L15: =K15*S12/1000 -> 0 | M15: =K15*S$8/1000 -> 0 | N15: =$S$7*L15/1000 -> 0 | O15: =SUM(I15-K15) -> 0 | P15: =O15*S$8/1000 -> 0
B16: 8 | E16: =D16*S$8/1000 -> 0 | G16: 0 | H16: =G16*S13/1000 -> 0 | I16: =SUM(D16+G16) -> 0 | J16: =I16*S13/1000 -> 0 | K16: 0 | L16: =K16*S13/1000 -> 0 | M16: =K16*S$8/1000 -> 0 | N16: =$S$7*L16/1000 -> 0 | O16: =SUM(I16-K16) -> 0 | P16: =O16*S$8/1000 -> 0
B17: 9 | E17: =D17*S$8/1000 -> 0 | G17: 0 | H17: =G17*S14/1000 -> 0 | I17: =SUM(D17+G17) -> 0 | J17: =I17*S14/1000 -> 0 | K17: 0 | L17: =K17*S14/1000 -> 0 | M17: =K17*S$8/1000 -> 0 | N17: =$S$7*L17/1000 -> 0 | O17: =SUM(I17-K17) -> 0 | P17: =O17*S$8/1000 -> 0
B18: 10 | E18: =D18*S$8/1000 -> 0 | G18: 0 | H18: =G18*S15/1000 -> 0 | I18: =SUM(D18+G18) -> 0 | J18: =I18*S15/1000 -> 0 | K18: 0 | L18: =K18*S15/1000 -> 0 | M18: =K18*S$8/1000 -> 0 | N18: =$S$7*L18/1000 -> 0 | O18: =SUM(I18-K18) -> 0 | P18: =O18*S$8/1000 -> 0
B19: 11 | E19: =D19*S$8/1000 -> 0 | G19: 0 | H19: =G19*S16/1000 -> 0 | I19: =SUM(D19+G19) -> 0 | J19: =I19*S16/1000 -> 0 | K19: 0 | L19: =K19*S16/1000 -> 0 | M19: =K19*S$8/1000 -> 0 | N19: =$S$7*L19/1000 -> 0 | O19: =SUM(I19-K19) -> 0 | P19: =O19*S$8/1000 -> 0
B20: 12 | E20: =D20*S$8/1000 -> 0 | G20: 0 | H20: =G20*S17/1000 -> 0 | I20: =SUM(D20+G20) -> 0 | J20: =I20*S17/1000 -> 0 | K20: 0 | L20: =K20*S17/1000 -> 0 | M20: =K20*S$8/1000 -> 0 | N20: =$S$7*L20/1000 -> 0 | O20: =SUM(I20-K20) -> 0 | P20: =O20*S$8/1000 -> 0
B21: 13 | E21: =D21*S$8/1000 -> 0 | G21: 0 | H21: =G21*S18/1000 -> 0 | I21: =SUM(D21+G21) -> 0 | J21: =I21*S18/1000 -> 0 | K21: 0 | L21: =K21*S18/1000 -> 0 | M21: =K21*S$8/1000 -> 0 | N21: =$S$7*L21/1000 -> 0 | O21: =SUM(I21-K21) -> 0 | P21: =O21*S$8/1000 -> 0
B22: 14 | E22: =D22*S$8/1000 -> 0 | G22: 0 | H22: =G22*S19/1000 -> 0 | I22: =SUM(D22+G22) -> 0 | J22: =I22*S19/1000 -> 0 | K22: 0 | L22: =K22*S19/1000 -> 0 | M22: =K22*S$8/1000 -> 0 | N22: =$S$7*L22/1000 -> 0 | O22: =SUM(I22-K22) -> 0 | P22: =O22*S$8/1000 -> 0
B23: 15 | E23: =D23*S$8/1000 -> 0 | G23: 0 | H23: =G23*S20/1000 -> 0 | I23: =SUM(D23+G23) -> 0 | J23: =I23*S20/1000 -> 0 | L23: =K23*S6/1000 -> 0 | M23: =K23*S$8/1000 -> 0 | N23: =K23*S7/1000 -> 0 | O23: =SUM(I23-K23) -> 0 | P23: =O23*S$8/1000 -> 0
B24: 16 | E24: =D24*S$8/1000 -> 0 | G24: 0 | H24: =G24*S21/1000 -> 0 | I24: =SUM(D24+G24) -> 0 | J24: =I24*S21/1000 -> 0 | K24: 0 | L24: =K24*S21/1000 -> 0 | M24: =K24*S$8/1000 -> 0 | N24: =$S$7*L24/1000 -> 0 | O24: =SUM(I24-K24) -> 0 | P24: =O24*S$8/1000 -> 0
B25: 17 | E25: =D25*S$8/1000 -> 0 | G25: 0 | H25: =G25*S22/1000 -> 0 | I25: =SUM(D25+G25) -> 0 | J25: =I25*S22/1000 -> 0 | K25: 0 | L25: =K25*S22/1000 -> 0 | M25: =K25*S$8/1000 -> 0 | N25: =$S$7*L25/1000 -> 0 | O25: =SUM(I25-K25) -> 0 | P25: =O25*S$8/1000 -> 0
B26: 18 | E26: =D26*S$8/1000 -> 0 | G26: 0 | H26: =G26*S23/1000 -> 0 | I26: =SUM(D26+G26) -> 0 | J26: =I26*S23/1000 -> 0 | K26: 0 | L26: =K26*S23/1000 -> 0 | M26: =K26*S$8/1000 -> 0 | N26: =$S$7*L26/1000 -> 0 | O26: =SUM(I26-K26) -> 0 | P26: =O26*S$8/1000 -> 0
B27: 19 | E27: =D27*S$8/1000 -> 0 | G27: 0 | H27: =G27*S24/1000 -> 0 | I27: =SUM(D27+G27) -> 0 | J27: =I27*S24/1000 -> 0 | K27: 0 | L27: =K27*S24/1000 -> 0 | M27: =K27*S$8/1000 -> 0 | N27: =$S$7*L27/1000 -> 0 | O27: =SUM(I27-K27) -> 0 | P27: =O27*S$8/1000 -> 0
B28: 20 | E28: =D28*S$8/1000 -> 0 | G28: 0 | H28: =G28*S25/1000 -> 0 | I28: =SUM(D28+G28) -> 0 | J28: =I28*S25/1000 -> 0 | K28: 0 | L28: =K28*S25/1000 -> 0 | M28: =K28*S$8/1000 -> 0 | N28: =$S$7*L28/1000 -> 0 | O28: =SUM(I28-K28) -> 0 | P28: =O28*S$8/1000 -> 0
B29: 21 | E29: =D29*S$8/1000 -> 0 | G29: 0 | H29: =G29*S26/1000 -> 0 | I29: =SUM(D29+G29) -> 0 | J29: =I29*S26/1000 -> 0 | K29: 0 | L29: =K29*S26/1000 -> 0 | M29: =K29*S$8/1000 -> 0 | N29: =$S$7*L29/1000 -> 0 | O29: =SUM(I29-K29) -> 0 | P29: =O29*S$8/1000 -> 0
B30: 22 | E30: =D30*S$8/1000 -> 0 | G30: 0 | H30: =G30*S27/1000 -> 0 | I30: =SUM(D30+G30) -> 0 | J30: =I30*S27/1000 -> 0 | K30: 0 | L30: =K30*S27/1000 -> 0 | M30: =K30*S$8/1000 -> 0 | N30: =$S$7*L30/1000 -> 0 | O30: =SUM(I30-K30) -> 0 | P30: =O30*S$8/1000 -> 0
B31: 23 | E31: =D31*S$8/1000 -> 0 | G31: 0 | H31: =G31*S28/1000 -> 0 | I31: =SUM(D31+G31) -> 0 | J31: =I31*S28/1000 -> 0 | K31: 0 | L31: =K31*S28/1000 -> 0 | M31: =K31*S$8/1000 -> 0 | N31: =$S$7*L31/1000 -> 0 | O31: =SUM(I31-K31) -> 0 | P31: =O31*S$8/1000 -> 0
B32: 24 | E32: =D32*S$8/1000 -> 0 | G32: 0 | H32: =G32*S29/1000 -> 0 | I32: =SUM(D32+G32) -> 0 | J32: =I32*S29/1000 -> 0 | K32: 0 | L32: =K32*S29/1000 -> 0 | M32: =K32*S$8/1000 -> 0 | N32: =$S$7*L32/1000 -> 0 | O32: =SUM(I32-K32) -> 0 | P32: =O32*S$8/1000 -> 0
B33: 25 | E33: =D33*S$8/1000 -> 0 | G33: 0 | H33: =G33*S30/1000 -> 0 | I33: =SUM(D33+G33) -> 0 | J33: =I33*S30/1000 -> 0 | K33: 0 | L33: =K33*S30/1000 -> 0 | M33: =K33*S$8/1000 -> 0 | N33: =$S$7*L33/1000 -> 0 | O33: =SUM(I33-K33) -> 0 | P33: =O33*S$8/1000 -> 0
B34: 26 | E34: =D34*S$8/1000 -> 0 | G34: 0 | H34: =G34*S31/1000 -> 0 | I34: =SUM(D34+G34) -> 0 | J34: =I34*S31/1000 -> 0 | K34: 0 | L34: =K34*S31/1000 -> 0 | M34: =K34*S$8/1000 -> 0 | N34: =$S$7*L34/1000 -> 0 | O34: =SUM(I34-K34) -> 0 | P34: =O34*S$8/1000 -> 0
B35: 27 | E35: =D35*S$8/1000 -> 0 | G35: 0 | H35: =G35*S32/1000 -> 0 | I35: =SUM(D35+G35) -> 0 | J35: =I35*S32/1000 -> 0 | K35: 0 | L35: =K35*S32/1000 -> 0 | M35: =K35*S$8/1000 -> 0 | N35: =$S$7*L35/1000 -> 0 | O35: =SUM(I35-K35) -> 0 | P35: =O35*S$8/1000 -> 0
... B37: 29 | E37: =D37*S$8/1000 -> 0 | G37: 0 | H37: =G37*S34/1000 -> 0 | I37: =SUM(D37+G37) -> 0 | J37: =I37*S34/1000 -> 0 | K37: 0 | L37: =K37*S34/1000 -> 0 | M37: =K37*S$8/1000 -> 0 | N37: =$S$7*L37/1000 -> 0 | O37: =SUM(I37-K37) -> 0 | P37: =O37*S$8/1000 -> 0
B38: 30 | E38: =D38*S$8/1000 -> 0 | G38: 0 | H38: =G38*S35/1000 -> 0 | I38: =SUM(D38+G38) -> 0 | J38: =I38*S35/1000 -> 0 | L38: =K38*S35/1000 -> 0 | M38: =K38*S$8/1000 -> 0 | N38: =$S$7*L38/1000 -> 0 | O38: =SUM(I38-K38) -> 0 | P38: =O38*S$8/1000 -> 0
B39: 31 | E39: =D39*S$8/1000 -> 0 | H39: =G39*S36/1000 -> 0 | I39: =SUM(D39+G39) -> 0 | J39: =I39*S36/1000 -> 0 | L39: =K39*S36/1000 -> 0 | M39: =K39*S$8/1000 -> 0 | N39: =$S$7*L39/1000 -> 0 | O39: =SUM(I39-K39) -> 0 | P39: =O39*S$8/1000 -> 0
B40: TOTAL | F40: =SUM(F9:F39) -> 0 | G40: =SUM(G9:G39) -> 0 | H40: =SUM(H9:H39) -> 0 | K40: =SUM(K9:K39) -> 0 | L40: =SUM(L9:L39) -> 0 | N40: =SUM(N9:N39) -> 0
B42: PACK SHEET | E42: =G40*S7/1000 -> 0 | J42: DESPATCH PACKSHEET | L42: =K40*S7/1000 -> 0

Sheet EXPORT 
B2: STOCK CARD- REF.NO | Q2: MONTH
B3: THE EMPIRE JUTE MILL | Q3: HESSIAN
B4: HESSIAN CLOTH 91.5 CMS 137 GMS/SQR MTR | Q4: SACKING
Q5: YARN
B6: DATE | D6: OPENING BALANCE | G6: RECEIPT | I6: TOTAL | K6: ISSUES | N6: CLOSING BALLACE | P6: REMARKS | Q6: NET WGT. PER BALE | W6: BOX
D7: NO.OF | E7: WEIGHT IN | G7: NO.OF | H7: WEIGHT IN | I7: NO.OF | J7: WEIGHT IN | K7: NO.OF | L7: WEIGHT IN | N7: NO.OF | O7: WEIGHT IN | Q7: P.SHEET WGT
D8: BALE | E8: KGS | G8: BALE | H8: KGS | I8: BALE | J8: KGS | K8: BALE | L8: KGS | M8: PACK SHEET | N8: BALE | O8: KGS | Q8: TOTAL WGT | R8: =R6+R7 -> 0
B9: 1 | L9: =+H9 -> 0 | M9: =$R$7*L9/1000 -> 0
B10: 2 | L10: =+H10 -> 0 | M10: =$R$7*L10/1000 -> 0
B11: 3 | E11: 0 | I11: =D11+G11 -> 0 | J11: 0 | K11: 0 | L11: =+H11 -> 0 | M11: =$R$7*L11/1000 -> 0 | N11: 0 | O11: =N11*R$8/1000 -> 0
B12: 4 | E12: =D12*R$8/1000 -> 0 | I12: =D12+G12 -> 0 | J12: =I12*T$8/1000 -> 0 | K12: 0 | L12: =+H12 -> 0 | M12: =$R$7*L12/1000 -> 0 | N12: =D12+G12-K12 -> 0 | O12: =N12*R$8/1000 -> 0
B13: 5 | E13: =D13*R$8/1000 -> 0 | I13: 0 | J13: =I13*T$8/1000 -> 0 | L13: =+H13 -> 0 | M13: =$R$7*L13/1000 -> 0 | N13: =D13+G13-K13 -> 0 | O13: =N13*R$8/1000 -> 0
B14: 6 | E14: =D14*R$8/1000 -> 0 | L14: =+H14 -> 0 | M14: =$R$7*L14/1000 -> 0 | N14: =D14+G14-K14 -> 0 | O14: =N14*R$8/1000 -> 0
B15: 7 | E15: =D15*R$8/1000 -> 0 | J15: =I15*T$8/1000 -> 0 | K15: 0 | L15: =+H15 -> 0 | M15: =$R$7*L15/1000 -> 0 | N15: =D15+G15-K15 -> 0 | O15: =N15*R$8/1000 -> 0
B16: 8 | E16: =D16*R$8/1000 -> 0 | J16: =I16*T$8/1000 -> 0 | K16: 0 | L16: =+H16 -> 0 | M16: =$R$7*L16/1000 -> 0 | N16: =D16+G16-K16 -> 0 | O16: =N16*R$8/1000 -> 0
B17: 9 | E17: =D17*R$8/1000 -> 0 | J17: =I17*T$8/1000 -> 0 | K17: 0 | L17: =+H17 -> 0 | M17: =$R$7*L17/1000 -> 0 | N17: =D17+G17-K17 -> 0 | O17: =N17*R$8/1000 -> 0
B18: 10 | E18: =D18*R$8/1000 -> 0 | I18: 0 | J18: =I18*T$8/1000 -> 0 | L18: =+H18 -> 0 | M18: =$R$7*L18/1000 -> 0 | N18: =D18+G18-K18 -> 0 | O18: =N18*R$8/1000 -> 0
L19: =+H19 -> 0 | M19: =$R$7*L19/1000 -> 0 | N19: =D19+G19-K19 -> 0 | O19: =N19*R$8/1000 -> 0
B20: 12 | E20: =D20*R$8/1000 -> 0 | I20: 0 | J20: =I20*T$8/1000 -> 0 | K20: 0 | L20: =+H20 -> 0 | M20: =$R$7*L20/1000 -> 0 | N20: =D20+G20-K20 -> 0 | O20: =N20*R$8/1000 -> 0
B21: 13 | E21: =D21*R$8/1000 -> 0 | L21: =+H21 -> 0 | M21: =$R$7*L21/1000 -> 0 | N21: =D21+G21-K21 -> 0 | O21: =N21*R$8/1000 -> 0
L22: =+H22 -> 0 | M22: =$R$7*L22/1000 -> 0 | N22: =D22+G22-K22 -> 0 | O22: =N22*R$8/1000 -> 0
B23: 15 | E23: =D23*R$8/1000 -> 0 | I23: 0 | J23: =I23*T$8/1000 -> 0 | K23: 0 | L23: =+H23 -> 0 | M23: =$R$7*L23/1000 -> 0 | N23: =D23+G23-K23 -> 0 | O23: =N23*R$8/1000 -> 0
B24: 16 | E24: =D24*R$8/1000 -> 0 | I24: 0 | J24: =I24*T$8/1000 -> 0 | L24: =+H24 -> 0 | M24: =$R$7*L24/1000 -> 0 | N24: =D24+G24-K24 -> 0 | O24: =N24*R$8/1000 -> 0
B25: 17 | E25: =D25*R$8/1000 -> 0 | I25: 0 | J25: =I25*T$8/1000 -> 0 | L25: =+H25 -> 0 | M25: =K25*R$7/1000 -> 0 | N25: =D25+G25-K25 -> 0 | O25: =N25*R$8/1000 -> 0
B26: 18 | E26: =D26*R$8/1000 -> 0 | I26: 0 | J26: =I26*T$8/1000 -> 0 | K26: 0 | L26: =+H26 -> 0 | M26: =K26*R$7/1000 -> 0 | N26: =D26+G26-K26 -> 0 | O26: =N26*R$8/1000 -> 0
B27: 19 | L27: =+H27 -> 0 | M27: =K27*R$7/1000 -> 0 | N27: =D27+G27-K27 -> 0 | O27: =N27*R$8/1000 -> 0
B28: 20 | E28: =D28*R$8/1000 -> 0 | I28: 0 | J28: =I28*T$8/1000 -> 0 | K28: 0 | L28: =+H28 -> 0 | M28: =K28*R$7/1000 -> 0 | N28: =D28+G28-K28 -> 0 | O28: =N28*R$8/1000 -> 0
B29: 21 | E29: =D29*R$8/1000 -> 0 | I29: 0 | J29: =I29*T$8/1000 -> 0 | K29: 0 | L29: =+H29 -> 0 | M29: =K29*R$7/1000 -> 0 | N29: =D29+G29-K29 -> 0 | O29: =N29*R$8/1000 -> 0
B30: 22 | E30: =D30*R$8/1000 -> 0 | I30: 0 | J30: =I30*T$8/1000 -> 0 | L30: =+H30 -> 0 | M30: =K30*R$7/1000 -> 0 | N30: =D30+G30-K30 -> 0 | O30: =N30*R$8/1000 -> 0
B31: 23 | E31: =D31*R$8/1000 -> 0 | I31: 0 | J31: =I31*T$8/1000 -> 0 | K31: 0 | L31: =+H31 -> 0 | M31: =K31*R$7/1000 -> 0 | N31: =D31+G31-K31 -> 0 | O31: =N31*R$8/1000 -> 0
L32: =+H32 -> 0 | M32: =K32*R$7/1000 -> 0 | N32: =D32+G32-K32 -> 0 | O32: =N32*R$8/1000 -> 0
B33: 25 | E33: =D33*R$8/1000 -> 0 | I33: 0 | J33: =I33*T$8/1000 -> 0 | L33: =+H33 -> 0 | M33: =K33*R$7/1000 -> 0 | N33: =D33+G33-K33 -> 0 | O33: =N33*R$8/1000 -> 0
B34: 26 | E34: =D34*R$8/1000 -> 0 | I34: 0 | J34: =I34*T$8/1000 -> 0 | L34: =+H34 -> 0 | M34: =K34*R$7/1000 -> 0 | N34: =D34+G34-K34 -> 0 | O34: =N34*R$8/1000 -> 0
B35: 27 | E35: =D35*R$8/1000 -> 0 | I35: 0 | J35: =I35*T$8/1000 -> 0 | K35: 0 | L35: =+H35 -> 0 | M35: =K35*R$7/1000 -> 0 | N35: =D35+G35-K35 -> 0 | O35: =N35*R$8/1000 -> 0
B36: 28 | E36: =D36*R$8/1000 -> 0 | I36: 0 | J36: =I36*T$8/1000 -> 0 | K36: 0 | L36: =+H36 -> 0 | M36: =K36*R$7/1000 -> 0 | N36: =D36+G36-K36 -> 0 | O36: =N36*R$8/1000 -> 0
B37: 29 | E37: =D37*R$8/1000 -> 0 | I37: 0 | J37: =I37*T$8/1000 -> 0 | K37: 0 | L37: =+H37 -> 0 | M37: =K37*R$7/1000 -> 0 | N37: =D37+G37-K37 -> 0 | O37: =N37*R$8/1000 -> 0
B38: 30 | E38: =D38*R$8/1000 -> 0 | J38: =I38*T$8/1000 -> 0 | L38: =+H38 -> 0 | M38: =K38*R$7/1000 -> 0 | N38: =D38+G38-K38 -> 0 | O38: =N38*R$8/1000 -> 0
B39: 31 | E39: =D39*R$8/1000 -> 0 | J39: =I39*T$8/1000 -> 0 | L39: =+H39 -> 0 | M39: =K39*R$7/1000 -> 0 | N39: =D39+G39-K39 -> 0 | O39: =N39*R$8/1000 -> 0
B40: TOTAL | F40: =SUM(F9:F39) -> 0 | G40: =SUM(G9:G39) -> 0 | H40: =SUM(H9:H39) -> 0 | K40: =SUM(K9:K39) -> 0 | L40: =SUM(L9:L39) -> 0 | M40: =SUM(M9:M39) -> 0
B42: PACK SHEET | E42: =G40*R7/1000 -> 0 | Q42: 6

Sheet 48-6 EXPORT
B2: STOCK CARD- REF.NO
B3: THE EMPIRE JUTE MILL | R3: HESSIAN
B4: HESSIAN CLOTH :- 48 -6.5 OZ / 153 GM/MTR | R4: SACKING
A5: I/B-1828.80 MTR | R5: YARN
B6: DATE | D6: OPENING BALANCE | G6: RECEIPT | I6: TOTAL | K6: ISSUES | M6: GROSS WT | O6: CLOSING BALLACE | Q6: REMARKS | R6: NET WGT. PER BALE | S6: 340
D7: NO.OF | E7: WEIGHT IN | G7: BALE | H7: WEIGHT IN | I7: NO.OF | J7: WEIGHT IN | K7: NO.OF | L7: NET WT | O7: NO.OF | P7: WEIGHT IN | R7: P.SHEET WGT | S7: 2.55
D8: BALE | E8: KGS | H8: KGS | I8: BALE | J8: KGS | K8: BALE | L8: KGS | N8: PACK SHEET | O8: BALE | P8: KGS | R8: TOTAL WGT | S8: =S6+S7 -> 342.55
B9: 1 | E9: =$S$8*D9/1000 -> 0 | I9: =+D9+G9 -> 0 | J9: =$S$8*I9/1000 -> 0 | L9: =K9*S$6/1000 -> 0 | M9: =K9*S$8/1000 -> 0 | N9: =$S$7*L9/1000 -> 0 | O9: =+I9-K9 -> 0
B10: 2 | H10: =$S$8*G10/1000 -> 0 | I10: =+D10+G10 -> 0 | J10: =$S$8*I10/1000 -> 0 | L10: =K10*S$6/1000 -> 0 | M10: =K10*S$8/1000 -> 0 | N10: =$S$7*L10/1000 -> 0 | O10: =+I10-K10 -> 0 | P10: =O10*S$8/1000 -> 0
B11: 3 | H11: =$S$8*G11/1000 -> 0 | I11: =+D11+G11 -> 0 | J11: =$S$8*I11/1000 -> 0 | L11: =K11*S$6/1000 -> 0 | M11: =K11*S$8/1000 -> 0 | N11: =$S$7*L11/1000 -> 0 | O11: =+I11-K11 -> 0 | P11: =O11*S$8/1000 -> 0
B12: 4 | H12: =$S$8*G12/1000 -> 0 | I12: =+D12+G12 -> 0 | J12: =$S$8*I12/1000 -> 0 | L12: =K12*S$6/1000 -> 0 | M12: =K12*S$8/1000 -> 0 | N12: =$S$7*L12/1000 -> 0 | O12: =+I12-K12 -> 0 | P12: =O12*S$8/1000 -> 0
B13: 5 | I13: =+D13+G13 -> 0 | L13: =K13*S$6/1000 -> 0 | M13: =K13*S$8/1000 -> 0 | N13: =$S$7*L13/1000 -> 0 | O13: =+I13-K13 -> 0
B14: 6 | H14: =$S$8*G14/1000 -> 0 | I14: =+D14+G14 -> 0 | L14: =K14*S$6/1000 -> 0 | M14: =K14*S$8/1000 -> 0 | N14: =$S$7*L14/1000 -> 0 | O14: =+I14-K14 -> 0
B15: 7 | H15: =$S$8*G15/1000 -> 0 | I15: =+D15+G15 -> 0 | L15: =K15*S$6/1000 -> 0 | M15: =K15*S$8/1000 -> 0 | N15: =$S$7*L15/1000 -> 0 | O15: =+I15-K15 -> 0
B16: 8 | H16: =$S$8*G16/1000 -> 0 | I16: =+D16+G16 -> 0 | L16: =K16*S$6/1000 -> 0 | M16: =K16*S$8/1000 -> 0 | N16: =$S$7*L16/1000 -> 0 | O16: =+I16-K16 -> 0
B17: 9 | H17: =$S$8*G17/1000 -> 0 | I17: =+D17+G17 -> 0 | O17: =+I17-K17 -> 0 | P17: =O17*S$8/1000 -> 0
B18: 10 | E18: =$S$8*D18/1000 -> 0 | H18: =$S$8*G18/1000 -> 0 | I18: =+D18+G18 -> 0 | J18: =$S$8*I18/1000 -> 0 | L18: =K18*S$6/1000 -> 0 | M18: =K18*S$8/1000 -> 0 | N18: =$S$7*L18/1000 -> 0 | O18: =+I18-K18 -> 0 | P18: =O18*S$8/1000 -> 0
B19: 11 | E19: =$S$8*D19/1000 -> 0 | H19: =$S$8*G19/1000 -> 0 | I19: =+D19+G19 -> 0 | J19: =$S$8*I19/1000 -> 0 | L19: =K19*S$6/1000 -> 0 | M19: =K19*S$8/1000 -> 0 | N19: =$S$7*L19/1000 -> 0 | O19: =+I19-K19 -> 0 | P19: =O19*S$8/1000 -> 0
B20: 12 | E20: =$S$8*D20/1000 -> 0 | H20: =$S$8*G20/1000 -> 0 | I20: =+D20+G20 -> 0 | J20: =$S$8*I20/1000 -> 0 | L20: =K20*S$6/1000 -> 0 | M20: =K20*S$8/1000 -> 0 | N20: =$S$7*L20/1000 -> 0 | O20: =+I20-K20 -> 0 | P20: =O20*S$8/1000 -> 0
B21: 13 | E21: =$S$8*D21/1000 -> 0 | H21: =$S$8*G21/1000 -> 0 | I21: =+D21+G21 -> 0 | J21: =$S$8*I21/1000 -> 0 | L21: =K21*S$6/1000 -> 0 | M21: =K21*S$8/1000 -> 0 | N21: =$S$7*L21/1000 -> 0 | O21: =+I21-K21 -> 0 | P21: =O21*S$8/1000 -> 0
B22: 14 | E22: =$S$8*D22/1000 -> 0 | H22: =$S$8*G22/1000 -> 0 | I22: =+D22+G22 -> 0 | J22: =$S$8*I22/1000 -> 0 | L22: =K22*S$6/1000 -> 0 | M22: =K22*S$8/1000 -> 0 | N22: =$S$7*L22/1000 -> 0 | O22: =+I22-K22 -> 0 | P22: =O22*S$8/1000 -> 0
B23: 15 | E23: =$S$8*D23/1000 -> 0 | H23: =$S$8*G23/1000 -> 0 | I23: =+D23+G23 -> 0 | J23: =$S$8*I23/1000 -> 0 | L23: =K23*S$6/1000 -> 0 | M23: =K23*S$8/1000 -> 0 | N23: =$S$7*L23/1000 -> 0 | O23: =+I23-K23 -> 0 | P23: =O23*S$8/1000 -> 0
B24: 16 | E24: =$S$8*D24/1000 -> 0 | H24: =$S$8*G24/1000 -> 0 | I24: =+D24+G24 -> 0 | J24: =$S$8*I24/1000 -> 0 | L24: =K24*S$6/1000 -> 0 | M24: =K24*S$8/1000 -> 0 | N24: =$S$7*L24/1000 -> 0 | O24: =+I24-K24 -> 0 | P24: =O24*S$8/1000 -> 0
B25: 17 | E25: =$S$8*D25/1000 -> 0 | H25: =$S$8*G25/1000 -> 0 | I25: =+D25+G25 -> 0 | J25: =$S$8*I25/1000 -> 0 | L25: =K25*S$6/1000 -> 0 | M25: =K25*S$8/1000 -> 0 | N25: =$S$7*L25/1000 -> 0 | O25: =+I25-K25 -> 0 | P25: =O25*S$8/1000 -> 0
B26: 18 | E26: =$S$8*D26/1000 -> 0 | H26: =$S$8*G26/1000 -> 0 | I26: =+D26+G26 -> 0 | J26: =$S$8*I26/1000 -> 0 | L26: =K26*S$6/1000 -> 0 | M26: =K26*S$8/1000 -> 0 | N26: =$S$7*L26/1000 -> 0 | O26: =+I26-K26 -> 0 | P26: =O26*S$8/1000 -> 0
B27: 19 | E27: =$S$8*D27/1000 -> 0 | H27: =$S$8*G27/1000 -> 0 | I27: =+D27+G27 -> 0 | J27: =$S$8*I27/1000 -> 0 | L27: =K27*S$6/1000 -> 0 | M27: =K27*S$8/1000 -> 0 | N27: =$S$7*L27/1000 -> 0 | O27: =+I27-K27 -> 0 | P27: =O27*S$8/1000 -> 0
B28: 20 | E28: =$S$8*D28/1000 -> 0 | H28: =$S$8*G28/1000 -> 0 | I28: =+D28+G28 -> 0 | J28: =$S$8*I28/1000 -> 0 | L28: =K28*S$6/1000 -> 0 | M28: =K28*S$8/1000 -> 0 | N28: =$S$7*L28/1000 -> 0 | O28: =+I28-K28 -> 0 | P28: =O28*S$8/1000 -> 0
B29: 21 | E29: =$S$8*D29/1000 -> 0 | H29: =$S$8*G29/1000 -> 0 | I29: =+D29+G29 -> 0 | J29: =$S$8*I29/1000 -> 0 | L29: =K29*S$6/1000 -> 0 | M29: =K29*S$8/1000 -> 0 | N29: =$S$7*L29/1000 -> 0 | O29: =+I29-K29 -> 0 | P29: =O29*S$8/1000 -> 0
... B39: 31 | E39: =$S$8*D39/1000 -> 0 | H39: =$S$8*G39/1000 -> 0 | I39: =+D39+G39 -> 0 | J39: =$S$8*I39/1000 -> 0 | L39: =K39*S$6/1000 -> 0 | M39: =K39*S$8/1000 -> 0 | N39: =$S$7*L39/1000 -> 0 | O39: =+I39-K39 -> 0 | P39: =O39*S$8/1000 -> 0
B40: TOTAL | F40: =SUM(F7:F39) -> 0 | G40: =SUM(G9:G39) -> 0 | H40: =SUM(H9:H39) -> 0 | K40: =SUM(K9:K39) -> 0 | L40: =SUM(L9:L39) -> 0 | N40: =SUM(N7:N39) -> 0
D42: PACK SHEET | G42: =G40*S7/1000 -> 0 | J42: DESPATCH PACKSHEET | L42: =K40*S7/1000 -> 0
N43: =L40+N40 -> 0

Sheet TYPE A GOV
B2: STOCK CARD- REF.NO
B3: THE EMPIRE JUTE MILL | R3: HESSIAN
B4: B. TWILL BAGS 37X22.5LTD 580 GM/BAG | R4: SACKING
A5: 1/B 500 PCS | R5: YARN
B6: DATE | D6: OPENING BALANCE | G6: RECEIPT | I6: TOTAL | K6: ISSUES | M6: GROSS WT | O6: CLOSING BALLACE | Q6: REMARKS | R6: NET WGT. PER BALE | S6: 290
D7: NO.OF | E7: WEIGHT IN | G7: NO.OF | H7: WEIGHT IN MT | I7: NO.OF | J7: WEIGHT IN | K7: NO.OF | L7: NET WT | O7: NO.OF | P7: WEIGHT IN | R7: P.SHEET WGT | S7: 2.175
D8: BALE | E8: KGS | G8: BALE | I8: BALE | J8: KGS | K8: BALE | L8: KGS | N8: PACK SHEET | O8: BALE | P8: KGS | R8: TOTAL WGT | S8: =S6+S7 -> 292.175
B9: 1 | D9: 365 | E9: =$S$8*D9/1000 -> 106.64387 | G9: 28 | H9: =$S$8*G9/1000 -> 8.1809 | I9: =D9+G9 -> 393 | J9: =$S$8*I9/1000 -> 114.82478 | K9: 336 | L9: =K9*S$6/1000 -> 97.44 | M9: =K9*S$8/1000 -> 98.1708 | N9: =K9*S$7/1000 -> 0.7308 | O9: =I9-K9 -> 57 | P9: =O9*S$8/1000 -> 16.653975
B10: 2 | D10: =+O9 -> 57 | E10: =$S$8*D10/1000 -> 16.653975 | G10: 40 | H10: =$S$8*G10/1000 -> 11.687 | I10: =D10+G10 -> 97 | J10: =$S$8*I10/1000 -> 28.340975 | L10: =K10*S$6/1000 -> 0 | M10: =K10*S$8/1000 -> 0 | N10: =K10*S$7/1000 -> 0 | O10: =I10-K10 -> 97 | P10: =O10*S$8/1000 -> 28.340975
B11: 3 | D11: =+O10 -> 97 | E11: =$S$8*D11/1000 -> 28.340975 | G11: 44 | H11: =$S$8*G11/1000 -> 12.8557 | I11: =D11+G11 -> 141 | J11: =$S$8*I11/1000 -> 41.196675 | L11: =K11*S$6/1000 -> 0 | M11: =K11*S$8/1000 -> 0 | N11: =K11*S$7/1000 -> 0 | O11: =I11-K11 -> 141 | P11: =O11*S$8/1000 -> 41.196675
B12: 4 | D12: =+O11 -> 141 | E12: =$S$8*D12/1000 -> 41.196675 | G12: 44 | H12: =$S$8*G12/1000 -> 12.8557 | I12: =D12+G12 -> 185 | J12: =$S$8*I12/1000 -> 54.052375 | L12: =K12*S$6/1000 -> 0 | M12: =K12*S$8/1000 -> 0 | N12: =K12*S$7/1000 -> 0 | O12: =I12-K12 -> 185 | P12: =O12*S$8/1000 -> 54.052375
B13: 5 | D13: =+O12 -> 185 | E13: =$S$8*D13/1000 -> 54.052375 | G13: 46 | H13: =$S$8*G13/1000 -> 13.44005 | I13: =D13+G13 -> 231 | J13: =$S$8*I13/1000 -> 67.492425 | K13: 48 | L13: =K13*S$6/1000 -> 13.92 | M13: =K13*S$8/1000 -> 14.0244 | N13: =K13*S$7/1000 -> 0.1044 | O13: =I13-K13 -> 183 | P13: =O13*S$8/1000 -> 53.468025
B14: 6 | D14: =+O13 -> 183 | E14: =$S$8*D14/1000 -> 53.468025 | G14: 34 | H14: =$S$8*G14/1000 -> 9.93395 | I14: =D14+G14 -> 217 | J14: =$S$8*I14/1000 -> 63.401975 | L14: =K14*S$6/1000 -> 0 | M14: =K14*S$8/1000 -> 0 | N14: =K14*S$7/1000 -> 0 | O14: =I14-K14 -> 217 | P14: =O14*S$8/1000 -> 63.401975
B15: 7 | D15: =+O14 -> 217 | E15: =$S$8*D15/1000 -> 63.401975 | G15: 0 | H15: =$S$8*G15/1000 -> 0 | I15: =D15+G15 -> 217 | J15: =$S$8*I15/1000 -> 63.401975 | L15: =K15*S$6/1000 -> 0 | M15: =K15*S$8/1000 -> 0 | N15: =K15*S$7/1000 -> 0 | O15: =I15-K15 -> 217 | P15: =O15*S$8/1000 -> 63.401975
B16: 8 | D16: =+O15 -> 217 | E16: =$S$8*D16/1000 -> 63.401975 | G16: 56 | H16: =$S$8*G16/1000 -> 16.3618 | I16: =D16+G16 -> 273 | J16: =$S$8*I16/1000 -> 79.763775 | L16: =K16*S$6/1000 -> 0 | M16: =K16*S$8/1000 -> 0 | N16: =K16*S$7/1000 -> 0 | O16: =I16-K16 -> 273 | P16: =O16*S$8/1000 -> 79.763775
B17: 9 | D17: =+O16 -> 273 | E17: =$S$8*D17/1000 -> 79.763775 | G17: 51 | H17: =$S$8*G17/1000 -> 14.900925 | I17: =D17+G17 -> 324 | J17: =$S$8*I17/1000 -> 94.6647 | K17: 260 | L17: =K17*S$6/1000 -> 75.4 | M17: =K17*S$8/1000 -> 75.9655 | N17: =K17*S$7/1000 -> 0.5655 | O17: =I17-K17 -> 64 | P17: =O17*S$8/1000 -> 18.6992
B18: 10 | D18: =+O17 -> 64 | E18: =$S$8*D18/1000 -> 18.6992 | H18: =$S$8*G18/1000 -> 0 | I18: =D18+G18 -> 64 | J18: =$S$8*I18/1000 -> 18.6992 | L18: =K18*S$6/1000 -> 0 | M18: =K18*S$8/1000 -> 0 | N18: =K18*S$7/1000 -> 0 | O18: =I18-K18 -> 64 | P18: =O18*S$8/1000 -> 18.6992
B19: 11 | D19: =+O18 -> 64 | E19: =$S$8*D19/1000 -> 18.6992 | H19: =$S$8*G19/1000 -> 0 | I19: =D19+G19 -> 64 | J19: =$S$8*I19/1000 -> 18.6992 | L19: =K19*S$6/1000 -> 0 | M19: =K19*S$8/1000 -> 0 | N19: =K19*S$7/1000 -> 0 | O19: =I19-K19 -> 64 | P19: =O19*S$8/1000 -> 18.6992
B20: 12 | D20: =+O19 -> 64 | E20: =$S$8*D20/1000 -> 18.6992 | G20: 43 | H20: =$S$8*G20/1000 -> 12.563525 | I20: =D20+G20 -> 107 | J20: =$S$8*I20/1000 -> 31.262725 | L20: =K20*S$6/1000 -> 0 | M20: =K20*S$8/1000 -> 0 | N20: =K20*S$7/1000 -> 0 | O20: =I20-K20 -> 107 | P20: =O20*S$8/1000 -> 31.262725
B21: 13 | D21: =+O20 -> 107 | E21: =$S$8*D21/1000 -> 31.262725 | H21: =$S$8*G21/1000 -> 0 | I21: =D21+G21 -> 107 | J21: =$S$8*I21/1000 -> 31.262725 | L21: =K21*S$6/1000 -> 0 | M21: =K21*S$8/1000 -> 0 | N21: =K21*S$7/1000 -> 0 | O21: =I21-K21 -> 107 | P21: =O21*S$8/1000 -> 31.262725
B22: 14 | D22: =+O21 -> 107 | E22: =$S$8*D22/1000 -> 31.262725 | H22: =$S$8*G22/1000 -> 0 | I22: =D22+G22 -> 107 | J22: =$S$8*I22/1000 -> 31.262725 | L22: =K22*S$6/1000 -> 0 | M22: =K22*S$8/1000 -> 0 | N22: =K22*S$7/1000 -> 0 | O22: =I22-K22 -> 107 | P22: =O22*S$8/1000 -> 31.262725
B23: 15 | D23: =+O22 -> 107 | E23: =$S$8*D23/1000 -> 31.262725 | H23: =$S$8*G23/1000 -> 0 | I23: =D23+G23 -> 107 | J23: =$S$8*I23/1000 -> 31.262725 | L23: =K23*S$6/1000 -> 0 | M23: =K23*S$8/1000 -> 0 | N23: =K23*S$7/1000 -> 0 | O23: =I23-K23 -> 107 | P23: =O23*S$8/1000 -> 31.262725
B24: 16 | D24: =+O23 -> 107 | E24: =$S$8*D24/1000 -> 31.262725 | G24: 35 | H24: =$S$8*G24/1000 -> 10.226125 | I24: =D24+G24 -> 142 | J24: =$S$8*I24/1000 -> 41.48885 | K24: 25 | L24: =K24*S$6/1000 -> 7.25 | M24: =K24*S$8/1000 -> 7.304375 | N24: =K24*S$7/1000 -> 0.054375 | O24: =I24-K24 -> 117 | P24: =O24*S$8/1000 -> 34.184475
B25: 17 | D25: =+O24 -> 117 | E25: =$S$8*D25/1000 -> 34.184475 | H25: =$S$8*G25/1000 -> 0 | I25: =D25+G25 -> 117 | J25: =$S$8*I25/1000 -> 34.184475 | L25: =K25*S$6/1000 -> 0 | M25: =K25*S$8/1000 -> 0 | N25: =K25*S$7/1000 -> 0 | O25: =I25-K25 -> 117 | P25: =O25*S$8/1000 -> 34.184475
B26: 18 | D26: =+O25 -> 117 | E26: =$S$8*D26/1000 -> 34.184475 | H26: =$S$8*G26/1000 -> 0 | I26: =D26+G26 -> 117 | J26: =$S$8*I26/1000 -> 34.184475 | L26: =K26*S$6/1000 -> 0 | M26: =K26*S$8/1000 -> 0 | N26: =K26*S$7/1000 -> 0 | O26: =I26-K26 -> 117 | P26: =O26*S$8/1000 -> 34.184475
B27: 19 | D27: =+O26 -> 117 | E27: =$S$8*D27/1000 -> 34.184475 | H27: =$S$8*G27/1000 -> 0 | I27: =D27+G27 -> 117 | J27: =$S$8*I27/1000 -> 34.184475 | L27: =K27*S$6/1000 -> 0 | M27: =K27*S$8/1000 -> 0 | N27: =K27*S$7/1000 -> 0 | O27: =I27-K27 -> 117 | P27: =O27*S$8/1000 -> 34.184475
B28: 20 | D28: =+O27 -> 117 | E28: =$S$8*D28/1000 -> 34.184475 | H28: =$S$8*G28/1000 -> 0 | I28: =D28+G28 -> 117 | J28: =$S$8*I28/1000 -> 34.184475 | L28: =K28*S$6/1000 -> 0 | M28: =K28*S$8/1000 -> 0 | N28: =K28*S$7/1000 -> 0 | O28: =I28-K28 -> 117 | P28: =O28*S$8/1000 -> 34.184475
B29: 21 | D29: =+O28 -> 117 | E29: =$S$8*D29/1000 -> 34.184475 | H29: =$S$8*G29/1000 -> 0 | I29: =D29+G29 -> 117 | J29: =$S$8*I29/1000 -> 34.184475 | L29: =K29*S$6/1000 -> 0 | M29: =K29*S$8/1000 -> 0 | N29: =K29*S$7/1000 -> 0 | O29: =I29-K29 -> 117 | P29: =O29*S$8/1000 -> 34.184475
B30: 22 | D30: =+O29 -> 117 | E30: =$S$8*D30/1000 -> 34.184475 | G30: 52 | H30: =$S$8*G30/1000 -> 15.1931 | I30: =D30+G30 -> 169 | J30: =$S$8*I30/1000 -> 49.377575 | L30: =K30*S$6/1000 -> 0 | M30: =K30*S$8/1000 -> 0 | N30: =K30*S$7/1000 -> 0 | O30: =I30-K30 -> 169 | P30: =O30*S$8/1000 -> 49.377575
B31: 23 | D31: =+O30 -> 169 | E31: =$S$8*D31/1000 -> 49.377575 | G31: 28 | H31: =$S$8*G31/1000 -> 8.1809 | I31: =D31+G31 -> 197 | J31: =$S$8*I31/1000 -> 57.558475 | L31: =K31*S$6/1000 -> 0 | M31: =K31*S$8/1000 -> 0 | N31: =K31*S$7/1000 -> 0 | O31: =I31-K31 -> 197 | P31: =O31*S$8/1000 -> 57.558475
B32: 24 | D32: =+O31 -> 197 | E32: =$S$8*D32/1000 -> 57.558475 | G32: 31 | H32: =$S$8*G32/1000 -> 9.057425 | I32: =D32+G32 -> 228 | J32: =$S$8*I32/1000 -> 66.6159 | L32: =K32*S$6/1000 -> 0 | M32: =K32*S$8/1000 -> 0 | N32: =K32*S$7/1000 -> 0 | O32: =I32-K32 -> 228 | P32: =O32*S$8/1000 -> 66.6159
B33: 25 | D33: =+O32 -> 228 | E33: =$S$8*D33/1000 -> 66.6159 | H33: =$S$8*G33/1000 -> 0 | I33: =D33+G33 -> 228 | J33: =$S$8*I33/1000 -> 66.6159 | L33: =K33*S$6/1000 -> 0 | M33: =K33*S$8/1000 -> 0 | N33: =K33*S$7/1000 -> 0 | O33: =I33-K33 -> 228 | P33: =O33*S$8/1000 -> 66.6159
B34: 26 | D34: =+O33 -> 228 | E34: =$S$8*D34/1000 -> 66.6159 | G34: 23 | H34: =$S$8*G34/1000 -> 6.720025 | I34: =D34+G34 -> 251 | J34: =$S$8*I34/1000 -> 73.335925 | K34: 192 | L34: =K34*S$6/1000 -> 55.68 | M34: =K34*S$8/1000 -> 56.0976 | N34: =K34*S$7/1000 -> 0.4176 | O34: =I34-K34 -> 59 | P34: =O34*S$8/1000 -> 17.238325
B35: 27 | D35: =+O34 -> 59 | E35: =$S$8*D35/1000 -> 17.238325 | G35: 27 | H35: =$S$8*G35/1000 -> 7.888725 | I35: =D35+G35 -> 86 | J35: =$S$8*I35/1000 -> 25.12705 | L35: =K35*S$6/1000 -> 0 | M35: =K35*S$8/1000 -> 0 | N35: =K35*S$7/1000 -> 0 | O35: =I35-K35 -> 86 | P35: =O35*S$8/1000 -> 25.12705
B36: 28 | D36: =+O35 -> 86 | E36: =$S$8*D36/1000 -> 25.12705 | H36: =$S$8*G36/1000 -> 0 | I36: =D36+G36 -> 86 | J36: =$S$8*I36/1000 -> 25.12705 | L36: =K36*S$6/1000 -> 0 | M36: =K36*S$8/1000 -> 0 | N36: =K36*S$7/1000 -> 0 | O36: =I36-K36 -> 86 | P36: =O36*S$8/1000 -> 25.12705 | R36: 580 | S36: 500 | U36: =R36*S36/1000 -> 290
B37: 29 | D37: =+O36 -> 86 | E37: =$S$8*D37/1000 -> 25.12705 | G37: 26 | H37: =$S$8*G37/1000 -> 7.59655 | I37: =D37+G37 -> 112 | J37: =$S$8*I37/1000 -> 32.7236 | L37: =K37*S$6/1000 -> 0 | M37: =K37*S$8/1000 -> 0 | N37: =K37*S$7/1000 -> 0 | O37: =I37-K37 -> 112 | P37: =O37*S$8/1000 -> 32.7236 | U37: =U36*0.75% -> 2.175
B38: 30 | D38: =+O37 -> 112 | E38: =$S$8*D38/1000 -> 32.7236 | G38: 23 | H38: =$S$8*G38/1000 -> 6.720025 | I38: =D38+G38 -> 135 | J38: =$S$8*I38/1000 -> 39.443625 | K38: 96 | L38: =K38*S$6/1000 -> 27.84 | M38: =K38*S$8/1000 -> 28.0488 | N38: =K38*S$7/1000 -> 0.2088 | O38: =I38-K38 -> 39 | P38: =O38*S$8/1000 -> 11.394825 | U38: =U36+U37 -> 292.175
B39: 31 | D39: =+O38 -> 39 | E39: =$S$8*D39/1000 -> 11.394825 | G39: 23 | H39: =$S$8*G39/1000 -> 6.720025 | I39: =D39+G39 -> 62 | J39: =$S$8*I39/1000 -> 18.11485 | L39: =K39*S$6/1000 -> 0 | M39: =K39*S$8/1000 -> 0 | N39: =K39*S$7/1000 -> 0 | O39: =I39-K39 -> 62 | P39: =O39*S$8/1000 -> 18.11485
B40: TOTAL | F40: =SUM(F9:F39) -> 0 | G40: =SUM(G9:G39) -> 654 | H40: =SUM(H9:H39) -> 191.08245 | K40: =SUM(K9:K39) -> 957 | L40: =SUM(L9:L39) -> 277.53 | M40: =SUM(M9:M39) -> 279.61148 | N40: =SUM(N9:N39) -> 2.081475
B42: PACK SHEET | G42: =G40*S7/1000 -> 1.42245 | H42: =+G40*S6/1000 -> 189.66 | J42: DESPATCH PACKSHEET | L42: =K40*S7/1000 -> 2.081475

Sheet 767 GMS 500 PCS
B2: STOCK CARD- REF.NO
B3: THE EMPIRE JUTE MILL | R3: HESSIAN
B4: TYPE A-----B. TWILL BAGS 48X26.5 HD 767 GMS/BAG | R4: SACKING
A5: 1/B 500 PCS | R5: YARN
B6: DATE | D6: OPENING BALANCE | G6: RECEIPT | I6: TOTAL | K6: ISSUES | M6: GROSS WT | O6: CLOSING BALLACE | Q6: REMARKS | R6: NET WGT. PER BALE | S6: =767*500/1000 -> 383.5
D7: NO.OF | E7: WEIGHT IN | G7: NO.OF | H7: WEIGHT IN | I7: NO.OF | J7: WEIGHT IN | K7: NO.OF | L7: NET WT | O7: NO.OF | P7: WEIGHT IN | R7: P.SHEET WGT | S7: =+S6*0.75% -> 2.87625
D8: BALE | E8: KGS | G8: BALE | H8: KGS | I8: BALE | J8: KGS | K8: BALE | L8: KGS | N8: PACK SHEET | O8: BALE | P8: KGS | R8: TOTAL WGT | S8: =+S6+S7 -> 386.37625
B9: 1 | D9: 0 | E9: =$S$8*D9/1000 -> 0 | H9: =$S$8*G9/1000 -> 0 | I9: =D9+G9 -> 0 | J9: =$S$8*I9/1000 -> 0 | K9: 0 | L9: =K9*S$6/1000 -> 0 | M9: =K9*S$8/1000 -> 0 | N9: =K9*S$7/1000 -> 0 | O9: =I9-K9 -> 0 | P9: =O9*S$8/1000 -> 0
B10: 2 | D10: =+O9 -> 0 | E10: =$S$8*D10/1000 -> 0 | H10: =$S$8*G10/1000 -> 0 | I10: =D10+G10 -> 0 | J10: =$S$8*I10/1000 -> 0 | L10: =K10*S$6/1000 -> 0 | M10: =K10*S$8/1000 -> 0 | N10: =K10*S$7/1000 -> 0 | O10: =I10-K10 -> 0 | P10: =O10*S$8/1000 -> 0
B11: 3 | D11: =+O10 -> 0 | E11: =$S$8*D11/1000 -> 0 | H11: =$S$8*G11/1000 -> 0 | I11: =D11+G11 -> 0 | J11: =$S$8*I11/1000 -> 0 | L11: =K11*S$6/1000 -> 0 | M11: =K11*S$8/1000 -> 0 | N11: =K11*S$7/1000 -> 0 | O11: =I11-K11 -> 0 | P11: =O11*S$8/1000 -> 0
B12: 4 | D12: =+O11 -> 0 | E12: =$S$8*D12/1000 -> 0 | H12: =$S$8*G12/1000 -> 0 | I12: =D12+G12 -> 0 | J12: =$S$8*I12/1000 -> 0 | L12: =K12*S$6/1000 -> 0 | M12: =K12*S$8/1000 -> 0 | N12: =K12*S$7/1000 -> 0 | O12: =I12-K12 -> 0 | P12: =O12*S$8/1000 -> 0
B13: 5 | D13: =+O12 -> 0 | E13: =$S$8*D13/1000 -> 0 | H13: =$S$8*G13/1000 -> 0 | I13: =D13+G13 -> 0 | J13: =$S$8*I13/1000 -> 0 | L13: =K13*S$6/1000 -> 0 | M13: =K13*S$8/1000 -> 0 | N13: =K13*S$7/1000 -> 0 | O13: =I13-K13 -> 0 | P13: =O13*S$8/1000 -> 0
B14: 6 | D14: =+O13 -> 0 | E14: =$S$8*D14/1000 -> 0 | H14: =$S$8*G14/1000 -> 0 | I14: =D14+G14 -> 0 | J14: =$S$8*I14/1000 -> 0 | L14: =K14*S$6/1000 -> 0 | M14: =K14*S$8/1000 -> 0 | N14: =K14*S$7/1000 -> 0 | O14: =I14-K14 -> 0 | P14: =O14*S$8/1000 -> 0
B15: 7 | D15: =+O14 -> 0 | E15: =$S$8*D15/1000 -> 0 | H15: =$S$8*G15/1000 -> 0 | I15: =D15+G15 -> 0 | J15: =$S$8*I15/1000 -> 0 | L15: =K15*S$6/1000 -> 0 | M15: =K15*S$8/1000 -> 0 | N15: =K15*S$7/1000 -> 0 | O15: =I15-K15 -> 0 | P15: =O15*S$8/1000 -> 0
B16: 8 | D16: =+O15 -> 0 | E16: =$S$8*D16/1000 -> 0 | H16: =$S$8*G16/1000 -> 0 | I16: =D16+G16 -> 0 | J16: =$S$8*I16/1000 -> 0 | L16: =K16*S$6/1000 -> 0 | M16: =K16*S$8/1000 -> 0 | N16: =K16*S$7/1000 -> 0 | O16: =I16-K16 -> 0 | P16: =O16*S$8/1000 -> 0
B17: 9 | D17: =+O16 -> 0 | E17: =$S$8*D17/1000 -> 0 | H17: =$S$8*G17/1000 -> 0 | I17: =D17+G17 -> 0 | J17: =$S$8*I17/1000 -> 0 | L17: =K17*S$6/1000 -> 0 | M17: =K17*S$8/1000 -> 0 | N17: =K17*S$7/1000 -> 0 | O17: =I17-K17 -> 0 | P17: =O17*S$8/1000 -> 0
B18: 10 | D18: =+O17 -> 0 | E18: =$S$8*D18/1000 -> 0 | H18: =$S$8*G18/1000 -> 0 | I18: =D18+G18 -> 0 | J18: =$S$8*I18/1000 -> 0 | L18: =K18*S$6/1000 -> 0 | M18: =K18*S$8/1000 -> 0 | N18: =K18*S$7/1000 -> 0 | O18: =I18-K18 -> 0 | P18: =O18*S$8/1000 -> 0
B19: 11 | D19: =+O18 -> 0 | E19: =$S$8*D19/1000 -> 0 | H19: =$S$8*G19/1000 -> 0 | I19: =D19+G19 -> 0 | J19: =$S$8*I19/1000 -> 0 | L19: =K19*S$6/1000 -> 0 | M19: =K19*S$8/1000 -> 0 | N19: =K19*S$7/1000 -> 0 | O19: =I19-K19 -> 0 | P19: =O19*S$8/1000 -> 0
B20: 12 | D20: =+O19 -> 0 | E20: =$S$8*D20/1000 -> 0 | H20: =$S$8*G20/1000 -> 0 | I20: =D20+G20 -> 0 | J20: =$S$8*I20/1000 -> 0 | L20: =K20*S$6/1000 -> 0 | M20: =K20*S$8/1000 -> 0 | N20: =K20*S$7/1000 -> 0 | O20: =I20-K20 -> 0 | P20: =O20*S$8/1000 -> 0
B21: 13 | D21: =+O20 -> 0 | E21: =$S$8*D21/1000 -> 0 | H21: =$S$8*G21/1000 -> 0 | I21: =D21+G21 -> 0 | J21: =$S$8*I21/1000 -> 0 | L21: =K21*S$6/1000 -> 0 | M21: =K21*S$8/1000 -> 0 | N21: =K21*S$7/1000 -> 0 | O21: =I21-K21 -> 0 | P21: =O21*S$8/1000 -> 0
... B39: 31 | D39: =+O38 -> 0 | E39: =$S$8*D39/1000 -> 0 | H39: =$S$8*G39/1000 -> 0 | I39: =D39+G39 -> 0 | J39: =$S$8*I39/1000 -> 0 | L39: =K39*S$6/1000 -> 0 | M39: =K39*S$8/1000 -> 0 | N39: =K39*S$7/1000 -> 0 | O39: =I39-K39 -> 0 | P39: =O39*S$8/1000 -> 0
B40: TOTAL | F40: =SUM(F9:F39) -> 0 | G40: =SUM(G9:G39) -> 0 | H40: =SUM(H9:H39) -> 0 | K40: =SUM(K9:K39) -> 0 | L40: =SUM(L9:L39) -> 0 | M40: =SUM(M9:M39) -> 0 | N40: =SUM(N9:N39) -> 0
B42: PACK SHEET | G42: =G40*S7/1000 -> 0 | H42: =+G40*S6/1000 -> 0 | J42: DESPATCH PACKSHEET | L42: =K40*S7/1000 -> 0

Sheet EXCISE SALES DETAILS
A2: HESSIAN CLOTH | U2: SACKING BAG | AN2: SALE YARN | BD2: JUCO | BS2: DUST | CH2: CADDIES | CW2: BLEACHED | DM2: OTHERS
CR3: =++CL33 -> 0
A6: SRL.NO | B6: DATE | C6: PARTY NAME | D6: LORRY NUM | E6: INVOICE | F6: QUALITY | G6: BALE | H6: NET WT | I6: WT | J6: ST WGHT | K6: KANTA WT | L6: DIFF | M6: VALUE | N6: CGST | O6: SGST | P6: IGST | Q6: TCS | R6: INSURANCE | S6: TOTAL | U6: DATE | V6: PARTY NAME | W6: LORRY NUM | X6: INVOICE | Y6: QUALITY | Z6: BALE | AA6: PLACE | AB6: NET WT | AC6: VALUE | AD6: PRINTING CHARGE | AE6: 2ND HANDLING CHARGE | AF6: TOTAL VALUE | AG6: CGST@2.5% | AH6: SGST@2.5% | AI6: IGST@5% | AJ6: TCS | AK6: GRAND TOTAL | AM6: SL.NO | AN6: DATE | AO6: PARTY NAME | AP6: INVOICE | AQ6: LORRY NUM | AR6: QUALITY | AS6: TRUSS | AT6: NET WGHT | AU6: GROSS WT | AV6: VALUE | AW6: CGST | AX6: SGST | AY6: IGST | AZ6: INSURANCE | BA6: IGST@18% | BB6: TOTAL | BD6: DATE | BE6: INVOICE | BF6: PARTY NAME | BG6: LORRY NUM | BH6: QUALITY | BI6: MTR | BJ6: GMS/INCH | BK6: WGHT IN KG | BL6: VALUE | BM6: CGST | BN6: SGST | BO6: IGST | BP6: TCS | BQ6: TOTAL | BS6: DATE | BT6: BILL NO | BU6: QUALITY | BV6: BALE | BW6: WGT MT | BX6: RS | BY6: THREAD(RS) | BZ6: LORRY NUM | CA6: CUSTOMER NAME | CB6: DUE PAYMENT | CC6: AMOUNT | CD6: CGST | CE6: SGST | CF6: IGST | CH6: DATE | CI6: BILL NO | CJ6: QUALITY | CK6: BALE | CL6: WGT MT | CM6: RS | CN6: DUST | CO6: LORRY NUMBER | CP6: THREADS | CQ6: DUE | CR6: TOTAL | CW6: DATE | CX6: INVOICE | CY6: PARTY NAME | CZ6: LORRY NUM | DA6: QUALITY | DB6: BAG | DC6: NET WGT MT | DD6: VALUE | DE6: CGST | DF6: SGST | DG6: IGST | DH6: TCS | DJ6: TOTAL | DM6: DATE | DN6: INVOICE | DO6: PARTY NAME | DP6: LORRY NUM | DQ6: QUALITY | DR6: BAG | DS6: NET WGT MT | DT6: VALUE | DU6: CGST | DV6: SGST | DW6: IGST | DX6: TCS | DZ6: TOTAL
A7: 1 | F7: 100 FT EXPORT | S7: =ROUND(SUM(M7:Q7),0) -> 0 | U7: 02.12.25 | V7: PUNJAB | X7: 376 | Y7: 37X22.5 | Z7: 48 | AB7: =+Z7*290/1000 -> 13.92 | AC7: 1790114.4 | AD7: 12000 | AE7: 5169.6 | AF7: =SUM(AC7:AE7) -> 1807284 | AI7: =+AF7*5% -> 90364.2 | AK7: =ROUND(SUM(AF7:AJ7),0) -> 1897648 | AM7: 1 | AN7: 27.12.25 | AP7: 409 | AR7: 10 LBS 3PLY HANKS | AS7: 160 | AT7: 8 | AV7: 1027120 | AW7: 25678 | AX7: =+AW7 -> 25678 | BA7: =+AZ7*18% -> 0 | BB7: =ROUND(SUM(AV7:BA7),0) -> 1078476 | BD7: 01.12.25 | BE7: 375 | BH7: PPJ01 | BI7: 67 | BK7: 0.027 | BL7: 9045 | BM7: 226.13 | BN7: =+BM7 -> 226.13 | BQ7: =SUM(BL7:BO7) -> 9497.26 | BS7: 08.12.25 | BT7: 62 | BW7: 7.02 | BX7: 200 | BY7: 300 | CC7: =BW7*BX7+BY7 -> 1704 | CH7: 02.12.25 | CI7: 61 | CL7: 6.05 | CM7: 600 | CP7: 500 | CR7: =SUM(CL7*CM7)+CP7 -> 4130 | DJ7: =SUM(DD7:DH7) -> 0 | DZ7: =SUM(DT7:DX7) -> 0
A8: 2 | F8: 100 FT EXPORT | S8: =ROUND(SUM(M8:Q8),0) -> 0 | U8: 02.12.25 | V8: PUNJAB | X8: 377 | Y8: 37X22.5 | Z8: 48 | AB8: =+Z8*290/1000 -> 13.92 | AC8: 1790114.4 | AD8: 12000 | AE8: 5169.6 | AF8: =SUM(AC8:AE8) -> 1807284 | AI8: =+AF8*5% -> 90364.2 | AK8: =ROUND(SUM(AF8:AJ8),0) -> 1897648 | AM8: 2 | AR8: 8 LBS 3PLY HANKS | BB8: =ROUND(SUM(AV8:BA8),0) -> 0 | BQ8: =SUM(BL8:BO8) -> 0 | BS8: 22.12.25 | BT8: 65 | BW8: 5.88 | BX8: 200 | BY8: 100 | CC8: =BW8*BX8+BY8 -> 1276 | CH8: 09.12.25 | CI8: 63 | CL8: 5.12 | CM8: 600 | CP8: 400 | CR8: =SUM(CL8*CM8)+CP8 -> 3472 | DJ8: =SUM(DD8:DH8) -> 0 | DZ8: =SUM(DT8:DX8) -> 0
A9: 3 | F9: 100 FT EXPORT | S9: =ROUND(SUM(M9:Q9),0) -> 0 | U9: 02.12.25 | V9: PUNJAB | X9: 378 | Y9: 37X22.5 | Z9: 48 | AB9: =+Z9*290/1000 -> 13.92 | AC9: 1790114.4 | AD9: 12000 | AE9: 5169.6 | AF9: =SUM(AC9:AE9) -> 1807284 | AI9: =+AF9*5% -> 90364.2 | AK9: =ROUND(SUM(AF9:AJ9),0) -> 1897648 | AM9: 3 | AR9: 10 LBS 3PLY HANKS | AX9: =+AW9 -> 0 | BB9: =ROUND(SUM(AV9:BA9),0) -> 0 | BS9: 31.12.25 | BT9: 66 | BW9: 6.96 | BX9: 300 | CA9: RAKESH | CB9: DUE | CC9: =BW9*BX9+BY9 -> 2088 | CH9: 20.12.25 | CI9: 64 | CL9: 1.31 | CM9: 600 | CP9: 100 | CR9: =SUM(CL9*CM9)+CP9 -> 886
F10: 100 FT EXPORT | S10: =ROUND(SUM(M10:Q10),0) -> 0 | U10: 02.12.25 | V10: PUNJAB | X10: 379 | Y10: 37X22.5 | Z10: 48 | AB10: =+Z10*290/1000 -> 13.92 | AC10: 1790114.4 | AD10: 12000 | AE10: 5169.6 | AF10: =SUM(AC10:AE10) -> 1807284 | AI10: =+AF10*5% -> 90364.2 | AK10: =ROUND(SUM(AF10:AJ10),0) -> 1897648 | AX10: =+AW10 -> 0 | BB10: =ROUND(SUM(AV10:BA10),0) -> 0 | CC10: =BW10*BX10+BY10 -> 0 | CR10: =SUM(CL10*CM10)+CP10 -> 0
A11: 4 | F11: 100 FT EXPORT | O11: =+N11 -> 0 | S11: =ROUND(SUM(M11:Q11),0) -> 0 | U11: 02.12.25 | V11: PUNJAB | X11: 380 | Y11: 37X22.5 | Z11: 48 | AB11: =+Z11*290/1000 -> 13.92 | AC11: 1790114.4 | AD11: 12000 | AE11: 5169.6 | AF11: =SUM(AC11:AE11) -> 1807284 | AI11: =+AF11*5% -> 90364.2 | AK11: =ROUND(SUM(AF11:AJ11),0) -> 1897648 | AM11: 4 | AR11: 10 LBS 3PLY HANKS | BB11: =ROUND(SUM(AV11:BA11),0) -> 0 | CC11: =BW11*BX11+BY11 -> 0
B12: TOTAL | G12: =SUM(G7:G11) -> 0 | H12: =SUM(H7:H11) -> 0 | M12: =SUM(M7:M11) -> 0 | U12: 02.12.25 | V12: PUNJAB | X12: 381 | Y12: 37X22.5 | Z12: 48 | AB12: =+Z12*290/1000 -> 13.92 | AC12: 1790114.4 | AD12: 12000 | AE12: 5169.6 | AF12: =SUM(AC12:AE12) -> 1807284 | AI12: =+AF12*5% -> 90364.2 | AK12: =ROUND(SUM(AF12:AJ12),0) -> 1897648 | AM12: 5 | AR12: 10 LBS 3PLY HANKS | BB12: =ROUND(SUM(AV12:BA12),0) -> 0 | CC12: =BW12*BX12+BY12 -> 0
A13: 5 | F13: 30 FT EXPORT | S13: =ROUND(SUM(M13:Q13),0) -> 0 | U13: 02.12.25 | V13: PUNJAB | X13: 382 | Y13: 37X22.5 | Z13: 48 | AB13: =+Z13*290/1000 -> 13.92 | AC13: 1790114.4 | AD13: 12000 | AE13: 5169.6 | AF13: =SUM(AC13:AE13) -> 1807284 | AI13: =+AF13*5% -> 90364.2 | AK13: =ROUND(SUM(AF13:AJ13),0) -> 1897648 | AM13: 6 | AR13: 10 LBS 3PLY HANKS | BB13: =ROUND(SUM(AV13:BA13),0) -> 0
A14: 6 | F14: 30 FT EXPORT | S14: =ROUND(SUM(M14:Q14),0) -> 0 | U14: 05.12.25 | V14: PUNJAB | X14: 386 | Y14: 37X22.5 | Z14: 48 | AB14: =+Z14*290/1000 -> 13.92 | AC14: 1790114.4 | AD14: 12000 | AE14: 5169.6 | AF14: =SUM(AC14:AE14) -> 1807284 | AI14: =+AF14*5% -> 90364.2 | AK14: =ROUND(SUM(AF14:AJ14),0) -> 1897648 | AM14: 7 | AR14: 10 LBS 3PLY HANKS | BB14: =ROUND(SUM(AV14:BA14),0) -> 0
A15: 7 | F15: 30 FT EXPORT | O15: =+N15 -> 0 | S15: =ROUND(SUM(M15:Q15),0) -> 0 | U15: 09.12.25 | V15: PUNJAB | X15: 390 | Y15: 37X22.5 | Z15: 65 | AB15: =+Z15*290/1000 -> 18.85 | AC15: 2424113.2 | AD15: 16250 | AE15: 6552 | AF15: =SUM(AC15:AE15) -> 2446915.2 | AI15: =+AF15*5% -> 122345.76 | AK15: =ROUND(SUM(AF15:AJ15),0) -> 2569261 | AM15: 8 | AR15: 10 LBS 3PLY HANKS | BB15: =ROUND(SUM(AV15:BA15),0) -> 0
A16: 8 | F16: 30 FT EXPORT | O16: =+N16 -> 0 | S16: =ROUND(SUM(M16:Q16),0) -> 0 | U16: 09.12.25 | V16: PUNJAB | X16: 391 | Y16: 37X22.5 | Z16: 65 | AB16: =+Z16*290/1000 -> 18.85 | AC16: 2424113.2 | AD16: 16250 | AE16: 6552 | AF16: =SUM(AC16:AE16) -> 2446915.2 | AI16: =+AF16*5% -> 122345.76 | AK16: =ROUND(SUM(AF16:AJ16),0) -> 2569261 | AM16: 9 | AR16: 10 LBS 3PLY HANKS | BB16: =ROUND(SUM(AV16:BA16),0) -> 0
A17: 9 | F17: 30 FT EXPORT | O17: =+N17 -> 0 | S17: =ROUND(SUM(M17:Q17),0) -> 0 | U17: 10.12.25 | V17: PUNJAB | X17: 395 | Y17: 37X22.5 | Z17: 65 | AB17: =+Z17*290/1000 -> 18.85 | AC17: 2424113.2 | AD17: 16250 | AE17: 6552 | AF17: =SUM(AC17:AE17) -> 2446915.2 | AI17: =+AF17*5% -> 122345.76 | AK17: =ROUND(SUM(AF17:AJ17),0) -> 2569261 | AM17: 10 | AR17: 10 LBS 3PLY HANKS | BB17: =ROUND(SUM(AV17:BA17),0) -> 0
B18: TOTAL | G18: =SUM(G13:G17) -> 0 | H18: =SUM(H13:H17) -> 0 | M18: =SUM(M13:M17) -> 0 | U18: 10.12.25 | V18: PUNJAB | X18: 396 | Y18: 37X22.5 | Z18: 65 | AB18: =+Z18*290/1000 -> 18.85 | AC18: 2424113.2 | AD18: 16250 | AE18: 6552 | AF18: =SUM(AC18:AE18) -> 2446915.2 | AI18: =+AF18*5% -> 122345.76 | AK18: =ROUND(SUM(AF18:AJ18),0) -> 2569261 | AN18: TOTAL | AS18: =SUM(AS7:AS17) -> 160 | AT18: =SUM(AT7:AT17) -> 8 | AU18: =SUM(AU7:AU17) -> 0 | AV18: =SUM(AV7:AV17) -> 1027120
A19: 12 | B19: 05.12.25 | E19: 387 | F19: 39-6-OZ | G19: 3 | H19: 0.995 | M19: 140329.83 | N19: 3508.25 | O19: =+N19 -> 3508.25 | S19: =ROUND(SUM(M19:Q19),0) -> 147346 | U19: 13.12.25 | V19: TELANGANA | X19: 397 | Y19: 37X22.5 | Z19: 25 | AB19: =+Z19*290/1000 -> 7.25 | AC19: 932351.25 | AD19: 6250 | AF19: =SUM(AC19:AE19) -> 938601.25 | AI19: =+AF19*5% -> 46930.062 | AK19: =ROUND(SUM(AF19:AJ19),0) -> 985531 | AM19: 11 | AR19: 28 LBS 3 PLY HANK
A20: 13 | B20: 10.12.25 | E20: 393 | F20: 39-6-OZ | G20: 53 | H20: 17.58 | M20: 2449456.6 | N20: 61236.41 | O20: =+N20 -> 61236.41 | S20: =ROUND(SUM(M20:Q20),0) -> 2571929 | U20: 27.12.25 | V20: MP | X20: 403 | Y20: 37X22.5 | Z20: 48 | AB20: =+Z20*290/1000 -> 13.92 | AC20: 1790114.4 | AD20: 12000 | AE20: 5169.6 | AF20: =SUM(AC20:AE20) -> 1807284 | AI20: =+AF20*5% -> 90364.2 | AK20: =ROUND(SUM(AF20:AJ20),0) -> 1897648 | AM20: 12 | AR20: 28 LBS 3 PLY HANK
A21: 14 | B21: 15.12.25 | E21: 400 | F21: 39-6-OZ | G21: 6 | H21: 1.99 | M21: 282593.93 | N21: 7064.85 | O21: =+N21 -> 7064.85 | S21: =ROUND(SUM(M21:Q21),0) -> 296724 | U21: 27.12.25 | V21: MP | X21: 404 | Y21: 37X22.5 | Z21: 48 | AB21: =+Z21*290/1000 -> 13.92 | AC21: 1790114.4 | AD21: 12000 | AE21: 5169.6 | AF21: =SUM(AC21:AE21) -> 1807284 | AI21: =+AF21*5% -> 90364.2 | AK21: =ROUND(SUM(AF21:AJ21),0) -> 1897648 | AM21: 13 | AR21: 28 LBS 3 PLY HANK
A22: 15 | B22: 10.12.25 | E22: 394 | F22: 39-6-OZ | G22: 53 | H22: 17.58 | M22: 2449456.6 | N22: 61236.41 | O22: =+N22 -> 61236.41 | S22: =ROUND(SUM(M22:Q22),0) -> 2571929 | U22: 27.12.25 | V22: PUNJAB | X22: 405 | Y22: 37X22.5 | Z22: 48 | AB22: =+Z22*290/1000 -> 13.92 | AC22: 1989691.2 | AD22: 12000 | AE22: 5169.6 | AF22: =SUM(AC22:AE22) -> 2006860.8 | AI22: =+AF22*5% -> 100343.04 | AK22: =ROUND(SUM(AF22:AJ22),0) -> 2107204 | AM22: 14 | AR22: 28 LBS 3 PLY HANK
A23: 16 | F23: 39-6-OZ | O23: =+N23 -> 0 | S23: =ROUND(SUM(M23:Q23),0) -> 0 | U23: 27.12.25 | V23: PUNJAB | X23: 406 | Y23: 37X22.5 | Z23: 48 | AB23: =+Z23*290/1000 -> 13.92 | AC23: 1989691.2 | AD23: 12000 | AE23: 5169.6 | AF23: =SUM(AC23:AE23) -> 2006860.8 | AI23: =+AF23*5% -> 100343.04 | AK23: =ROUND(SUM(AF23:AJ23),0) -> 2107204 | AM23: 15 | AR23: 28 LBS 3 PLY HANK
A24: 17 | F24: 39-6-OZ | O24: =+N24 -> 0 | S24: =ROUND(SUM(M24:Q24),0) -> 0 | U24: 31.12.25 | V24: PUNJAB | X24: 412 | Y24: 37X22.5 | Z24: 48 | AB24: =+Z24*290/1000 -> 13.92 | AC24: 1989691.2 | AD24: 12000 | AE24: 5169.6 | AF24: =SUM(AC24:AE24) -> 2006860.8 | AI24: =+AF24*5% -> 100343.04 | AK24: =ROUND(SUM(AF24:AJ24),0) -> 2107204 | AM24: 16 | AR24: 28 LBS 3 PLY HANK
A25: 18 | C25: NEXGEN | F25: 39-6-OZ | O25: =+N25 -> 0 | S25: =ROUND(SUM(M25:Q25),0) -> 0 | U25: 31.12.25 | V25: PUNJAB | X25: 413 | Y25: 37X22.5 | Z25: 48 | AB25: =+Z25*290/1000 -> 13.92 | AC25: 1989691.2 | AD25: 12000 | AE25: 5169.6 | AF25: =SUM(AC25:AE25) -> 2006860.8 | AI25: =+AF25*5% -> 100343.04 | AK25: =ROUND(SUM(AF25:AJ25),0) -> 2107204 | AM25: 17 | AR25: 28 LBS 3 PLY HANK
A26: 19 | C26: NEXGEN | F26: 39-6-OZ | I26: 336 | J26: =G26*I26/1000 -> 0 | L26: =K26-J26 -> 0 | O26: =+N26 -> 0 | Y26: 37X22.5 | AB26: =+Z26*290/1000 -> 0 | AF26: =SUM(AC26:AE26) -> 0 | AI26: =+AF26*5% -> 0 | AK26: =ROUND(SUM(AF26:AJ26),0) -> 0 | AM26: 18 | AR26: 28 LBS 3 PLY HANK
A27: 20 | C27: NEXGEN | F27: 39-6-OZ | I27: 336 | J27: =G27*I27/1000 -> 0 | L27: =K27-J27 -> 0 | O27: =+N27 -> 0 | Y27: 37X22.5 | AB27: =+Z27*290/1000 -> 0 | AF27: =SUM(AC27:AE27) -> 0 | AI27: =+AF27*5% -> 0 | AK27: =ROUND(SUM(AF27:AJ27),0) -> 0 | AM27: 19 | AR27: 28 LBS 3 PLY HANK
A28: 21 | C28: NEXGEN | F28: 39-6-OZ | I28: 336 | J28: =G28*I28/1000 -> 0 | L28: =K28-J28 -> 0 | O28: =+N28 -> 0 | Y28: 37X22.5 | AB28: =+Z28*290/1000 -> 0 | AF28: =SUM(AC28:AE28) -> 0 | AI28: =+AF28*5% -> 0 | AK28: =ROUND(SUM(AF28:AJ28),0) -> 0 | AM28: 20 | AR28: 28 LBS 3 PLY HANK
A29: 22 | C29: NEXGEN | F29: 39-6-OZ | I29: 336 | J29: =+G29*I29/1000 -> 0 | L29: =K29-J29 -> 0 | O29: =+N29 -> 0 | Y29: 37X22.5 | AB29: =+Z29*290/1000 -> 0 | AF29: =SUM(AC29:AE29) -> 0 | AI29: =+AF29*5% -> 0 | AK29: =ROUND(SUM(AF29:AJ29),0) -> 0 | AN29: TOTAL | AS29: =SUM(AS19:AS28) -> 0 | AT29: =SUM(AT19:AT28) -> 0 | AU29: =SUM(AU19:AU28) -> 0 | AV29: =SUM(AV19:AV28) -> 0
A30: 23 | C30: NEXGEN | F30: 39-6-OZ | I30: 336 | J30: =G30*I30/1000 -> 0 | L30: =K30-J30 -> 0 | Y30: 37X22.5 | AB30: =+Z30*290/1000 -> 0 | AI30: =+AF30*5% -> 0 | AK30: =ROUND(SUM(AF30:AJ30),0) -> 0 | AM30: 21 | AN30: 03.12.25 | AP30: 383 | AR30: 10 LBS 2 PLY HANKS | AS30: 8 | AT30: 0.394 | AV30: 51734.96 | AW30: 1293.37 | AX30: =+AW30 -> 1293.37 | BB30: =ROUND(SUM(AV30:BA30),0) -> 54322
A31: 24 | F31: 39-6-OZ | I31: 336 | J31: =G31*I31/1000 -> 0 | L31: =K31-J31 -> 0 | O31: =+N31 -> 0 | S31: =ROUND(SUM(M31:Q31),0) -> 0 | Y31: 37X22.5 | AB31: =+Z31*290/1000 -> 0 | AF31: =SUM(AC31:AE31) -> 0 | AI31: =+AF31*5% -> 0 | AK31: =ROUND(SUM(AF31:AJ31),0) -> 0 | AM31: 22 | AN31: 27.12.25 | AP31: 408 | AR31: 10 LBS 2 PLY HANKS | AS31: 160 | AT31: 8 | AV31: 1042680 | AW31: 26067 | AX31: =+AW31 -> 26067 | BB31: =ROUND(SUM(AV31:BA31),0) -> 1094814 | BK31: =BI31*BJ31/1000 -> 0 | BQ31: =SUM(BL31:BO31) -> 0 | BX31: 300 | CC31: =BW31*BX31+BY31 -> 0 | CR31: =SUM(CL31*CM31)+CP31 -> 0 | DJ31: =SUM(DD31:DH31) -> 0 | DZ31: =SUM(DT31:DX31) -> 0
A32: 25 | B32: TOTAL | G32: =SUM(G19:G31) -> 115 | H32: =SUM(H19:H31) -> 38.145 | M32: =SUM(M19:M31) -> 5321836.9 | O32: =+N32 -> 0 | S32: =ROUND(SUM(M32:Q32),0) -> 5321837 | Y32: 37X22.5 | AB32: =+Z32*290/1000 -> 0 | AF32: =SUM(AC32:AE32) -> 0 | AI32: =+AF32*5% -> 0 | AK32: =ROUND(SUM(AF32:AJ32),0) -> 0 | AM32: 23 | AR32: 10 LBS 2 PLY HANKS | BB32: =ROUND(SUM(AV32:BA32),0) -> 0 | BK32: =BI32*BJ32/1000 -> 0 | BQ32: =SUM(BL32:BO32) -> 0 | BX32: 300 | CC32: =BW32*BX32+BY32 -> 0 | CM32: 600 | CR32: =SUM(CL32*CM32)+CP32 -> 0 | DJ32: =SUM(DD32:DH32) -> 0 | DZ32: =SUM(DT32:DX32) -> 0
A33: 26 | B33: 01.12.25 | E33: 374 | F33: 38-8-12 | G33: 40 | H33: 17.495 | M33: 2552485.5 | N33: 63812.14 | O33: =+N33 -> 63812.14 | S33: =ROUND(SUM(M33:Q33),0) -> 2680110 | Y33: 37X22.5 | AB33: =+Z33*290/1000 -> 0 | AF33: =SUM(AC33:AE33) -> 0 | AI33: =+AF33*5% -> 0 | AK33: =ROUND(SUM(AF33:AJ33),0) -> 0 | AM33: 24 | AR33: 10 LBS 2 PLY HANKS | BB33: =ROUND(SUM(AV33:BA33),0) -> 0 | BQ33: =SUM(BL33:BO33) -> 0 | BX33: 300 | CC33: =BW33*BX33+BY33 -> 0 | CM33: 600 | CR33: =SUM(CL33*CM33)+CP33 -> 0 | DJ33: =SUM(DD33:DH33) -> 0 | DZ33: =SUM(DT33:DX33) -> 0
A34: 27 | B34: 05.12.25 | E34: 388 | F34: 38-8-12 | G34: 12 | H34: 5.249 | M34: 786237.21 | N34: 19655.93 | O34: =+N34 -> 19655.93 | S34: =ROUND(SUM(M34:Q34),0) -> 825549 | Y34: 37X22.5 | AB34: =+Z34*290/1000 -> 0 | AF34: =SUM(AC34:AE34) -> 0 | AI34: =+AF34*5% -> 0 | AK34: =ROUND(SUM(AF34:AJ34),0) -> 0 | AM34: 25 | AR34: 10 LBS 2 PLY HANKS | BB34: =ROUND(SUM(AV34:BA34),0) -> 0 | BQ34: =SUM(BL34:BO34) -> 0 | BX34: 300 | CC34: =BW34*BX34+BY34 -> 0 | CM34: 600 | CR34: =SUM(CL34*CM34)+CP34 -> 0 | DJ34: =SUM(DD34:DH34) -> 0 | DZ34: =SUM(DT34:DX34) -> 0
A35: 28 | B35: 10.12.25 | E35: 392 | F35: 38-8-12 | G35: 22 | H35: 9.622 | M35: 1455298.6 | N35: 36382.47 | O35: =+N35 -> 36382.47 | S35: =ROUND(SUM(M35:Q35),0) -> 1528064 | Y35: 37X22.5 | AB35: =+Z35*290/1000 -> 0 | AF35: =SUM(AC35:AE35) -> 0 | AI35: =+AF35*5% -> 0 | AK35: =ROUND(SUM(AF35:AJ35),0) -> 0 | AM35: 26 | AR35: 10 LBS 2 PLY HANKS | BB35: =ROUND(SUM(AV35:BA35),0) -> 0 | BX35: 300 | CC35: =BW35*BX35+BY35 -> 0 | CM35: 600 | CR35: =SUM(CL35*CM35)+CP35 -> 0 | DJ35: =SUM(DD35:DH35) -> 0 | DZ35: =SUM(DT35:DX35) -> 0
A36: 29 | B36: 15.12.25 | E36: 399 | F36: 38-8-12 | G36: 5 | H36: 2.187 | M36: 333970.21 | N36: 8349.26 | O36: =+N36 -> 8349.26 | S36: =ROUND(SUM(M36:Q36),0) -> 350669 | Y36: 37X22.5 | AB36: =+Z36*290/1000 -> 0 | AF36: =SUM(AC36:AE36) -> 0 | AI36: =+AF36*5% -> 0 | AK36: =ROUND(SUM(AF36:AJ36),0) -> 0 | AM36: 27 | AR36: 10 LBS 2 PLY HANKS | BB36: =ROUND(SUM(AV36:BA36),0) -> 0 | BX36: 300 | CC36: =BW36*BX36+BY36 -> 0 | CM36: 600 | CR36: =SUM(CL36*CM36)+CP36 -> 0 | DJ36: =SUM(DD36:DH36) -> 0 | DZ36: =SUM(DT36:DX36) -> 0
A37: 30 | B37: 26.12.25 | E37: 402 | F37: 38-8-12 | G37: 12 | H37: 5.249 | M37: 793895.5 | N37: 19847.39 | O37: =+N37 -> 19847.39 | S37: =ROUND(SUM(M37:Q37),0) -> 833590 | Y37: 37X22.5 | AB37: =+Z37*290/1000 -> 0 | AF37: =SUM(AC37:AE37) -> 0 | AI37: =+AF37*5% -> 0 | AK37: =ROUND(SUM(AF37:AJ37),0) -> 0 | AM37: 28 | AR37: 10 LBS 2 PLY HANKS | BB37: =ROUND(SUM(AV37:BA37),0) -> 0 | BX37: 300 | BZ37: 0.287 GRM | CC37: =BW37*BX37+BY37 -> 0 | CM37: 600 | CO37: .168 GRM | CR37: =SUM(CL37*CM37)+CP37 -> 0 | DJ37: =SUM(DD37:DH37) -> 0 | DZ37: =SUM(DT37:DX37) -> 0
A38: 31 | B38: 27.12.25 | E38: 407 | F38: 38-8-12 | H38: 0.005 | M38: 800 | N38: 20 | O38: =+N38 -> 20 | S38: =ROUND(SUM(M38:Q38),0) -> 840 | Y38: 37X22.5 | AB38: =+Z38*290/1000 -> 0 | AF38: =SUM(AC38:AE38) -> 0 | AI38: =+AF38*5% -> 0 | AK38: =ROUND(SUM(AF38:AJ38),0) -> 0 | AM38: 29 | AR38: 10 LBS 2 PLY HANKS | BB38: =ROUND(SUM(AV38:BA38),0) -> 0 | BX38: 300 | BZ38: 85 KG BALE | CC38: =BW38*BX38+BY38 -> 0 | CM38: 600 | CO38: 55 KG BALE | CR38: =SUM(CL38*CM38)+CP38 -> 0 | DJ38: =SUM(DD38:DH38) -> 0 | DZ38: =SUM(DT38:DX38) -> 0
A39: 32 | B39: 27.12.25 | E39: 411 | F39: 38-8-12 | G39: 10 | H39: 4.374 | M39: 667940.42 | N39: 16698.51 | O39: =+N39 -> 16698.51 | S39: =ROUND(SUM(M39:Q39),0) -> 701337 | Y39: 37X22.5 | AB39: =+Z39*290/1000 -> 0 | AF39: =SUM(AC39:AE39) -> 0 | AI39: =+AF39*5% -> 0 | AK39: =ROUND(SUM(AF39:AJ39),0) -> 0 | AM39: 30 | AR39: 10 LBS 2 PLY HANKS | BB39: =ROUND(SUM(AV39:BA39),0) -> 0 | BX39: 300 | CC39: =BW39*BX39+BY39 -> 0 | CM39: 600 | CR39: =SUM(CL39*CM39)+CP39 -> 0 | DJ39: =SUM(DD39:DH39) -> 0 | DZ39: =SUM(DT39:DX39) -> 0
A40: 33 | F40: 38-8-12 | I40: 440.664 | J40: =G40*I40/1000 -> 0 | L40: =K40-J40 -> 0 | O40: =+N40 -> 0 | S40: =ROUND(SUM(M40:Q40),0) -> 0 | Y40: 37X22.5 | AB40: =+Z40*290/1000 -> 0 | AF40: =SUM(AC40:AE40) -> 0 | AI40: =+AF40*5% -> 0 | AK40: =ROUND(SUM(AF40:AJ40),0) -> 0 | AN40: TOTAL | AS40: =SUM(AS30:AS39) -> 168 | AT40: =SUM(AT30:AT39) -> 8.394 | AU40: =SUM(AU30:AU39) -> 0 | AV40: =SUM(AV30:AV39) -> 1094415 | BB40: =ROUND(SUM(AV40:BA40),0) -> 1094415 | BX40: 300 | CC40: =BW40*BX40+BY40 -> 0 | CM40: 600 | CR40: =SUM(CL40*CM40)+CP40 -> 0 | DJ40: =SUM(DD40:DH40) -> 0 | DZ40: =SUM(DT40:DX40) -> 0
A41: 34 | F41: 38-8-12 | I41: 440.664 | J41: =G41*I41/1000 -> 0 | L41: =K41-J41 -> 0 | O41: =+N41 -> 0 | S41: =ROUND(SUM(M41:Q41),0) -> 0 | Y41: 37X22.5 | AB41: =+Z41*290/1000 -> 0 | AF41: =SUM(AC41:AE41) -> 0 | AI41: =+AF41*5% -> 0 | AK41: =ROUND(SUM(AF41:AJ41),0) -> 0 | AM41: 31 | AR41: 18 LBS COP | BB41: =ROUND(SUM(AV41:BA41),0) -> 0 | BX41: 300 | CC41: =BW41*BX41+BY41 -> 0 | CM41: 600 | CR41: =SUM(CL41*CM41)+CP41 -> 0 | DJ41: =SUM(DD41:DH41) -> 0 | DZ41: =SUM(DT41:DX41) -> 0
A42: 35 | F42: 38-8-12 | I42: 440.664 | J42: =G42*I42/1000 -> 0 | L42: =K42-J42 -> 0 | O42: =+N42 -> 0 | S42: =ROUND(SUM(M42:Q42),0) -> 0 | Y42: 37X22.5 | AB42: =+Z42*290/1000 -> 0 | AF42: =SUM(AC42:AE42) -> 0 | AI42: =+AF42*5% -> 0 | AK42: =ROUND(SUM(AF42:AJ42),0) -> 0 | AM42: 32 | AR42: 18 LBS COP | BB42: =ROUND(SUM(AV42:BA42),0) -> 0 | BX42: 300 | CC42: =BW42*BX42+BY42 -> 0 | CM42: 600 | CR42: =SUM(CL42*CM42)+CP42 -> 0 | DJ42: =SUM(DD42:DH42) -> 0 | DZ42: =SUM(DT42:DX42) -> 0
A43: 36 | F43: 38-8-12 | I43: 440.664 | J43: =G43*I43/1000 -> 0 | L43: =K43-J43 -> 0 | O43: =+N43 -> 0 | S43: =ROUND(SUM(M43:Q43),0) -> 0 | Y43: 37X22.5 | AB43: =+Z43*290/1000 -> 0 | AF43: =SUM(AC43:AE43) -> 0 | AI43: =+AF43*5% -> 0 | AK43: =ROUND(SUM(AF43:AJ43),0) -> 0 | AM43: 33 | AR43: 18 LBS COP | BB43: =ROUND(SUM(AV43:BA43),0) -> 0 | BX43: 300 | CC43: =BW43*BX43+BY43 -> 0 | CM43: 600 | CR43: =SUM(CL43*CM43)+CP43 -> 0 | DJ43: =SUM(DD43:DH43) -> 0 | DZ43: =SUM(DT43:DX43) -> 0
A44: 37 | F44: 38-8-12 | I44: 440.664 | J44: =G44*I44/1000 -> 0 | L44: =K44-J44 -> 0 | S44: =ROUND(SUM(M44:Q44),0) -> 0 | Y44: 37X22.5 | AB44: =+Z44*290/1000 -> 0 | AF44: =SUM(AC44:AE44) -> 0 | AI44: =+AF44*5% -> 0 | AK44: =ROUND(SUM(AF44:AJ44),0) -> 0 | AM44: 34 | AR44: 18 LBS COP | BB44: =ROUND(SUM(AV44:BA44),0) -> 0 | BX44: 300 | CC44: =BW44*BX44+BY44 -> 0 | CM44: 600 | CR44: =SUM(CL44*CM44)+CP44 -> 0 | DJ44: =SUM(DD44:DH44) -> 0 | DZ44: =SUM(DT44:DX44) -> 0
A45: 38 | F45: 38-8-12 | I45: 440.664 | J45: =G45*I45/1000 -> 0 | L45: =K45-J45 -> 0 | S45: =ROUND(SUM(M45:Q45),0) -> 0 | Y45: 37X22.5 | AB45: =+Z45*290/1000 -> 0 | AF45: =SUM(AC45:AE45) -> 0 | AI45: =+AF45*5% -> 0 | AK45: =ROUND(SUM(AF45:AJ45),0) -> 0 | AN45: TOTAL | AS45: =SUM(AS41:AS44) -> 0 | AT45: =SUM(AT41:AT44) -> 0 | AU45: =SUM(AU41:AU44) -> 0 | AV45: =SUM(AV41:AV44) -> 0 | BB45: =ROUND(SUM(AV45:BA45),0) -> 0 | BK45: =BI45*BJ45/1000 -> 0 | BQ45: =SUM(BL45:BO45) -> 0 | BX45: 300 | CC45: =BW45*BX45+BY45 -> 0 | CM45: 600 | CR45: =SUM(CL45*CM45)+CP45 -> 0 | DJ45: =SUM(DD45:DH45) -> 0 | DZ45: =SUM(DT45:DX45) -> 0
A46: 39 | F46: 38-8-12 | I46: 440.664 | J46: =G46*I46/1000 -> 0 | L46: =K46-J46 -> 0 | S46: =ROUND(SUM(M46:Q46),0) -> 0 | Y46: 37X22.5 | AB46: =+Z46*290/1000 -> 0 | AF46: =SUM(AC46:AE46) -> 0 | AI46: =+AF46*5% -> 0 | AK46: =ROUND(SUM(AF46:AJ46),0) -> 0 | AM46: 35 | AN46: 05.12.25 | AP46: 385 | AR46: 10 LBS 1 PLY PW SPOOL | AS46: 10 | AT46: 0.53 | AV46: 69592.71 | AW46: 1739.82 | AX46: =+AW46 -> 1739.82 | BB46: =ROUND(SUM(AV46:BA46),0) -> 73072 | BK46: =BI46*BJ46/1000 -> 0 | BQ46: =SUM(BL46:BO46) -> 0 | BX46: 200 | CC46: =BW46*BX46+BY46 -> 0 | CM46: 600 | CR46: =SUM(CL46*CM46)+CP46 -> 0 | DJ46: =SUM(DD46:DH46) -> 0 | DZ46: =SUM(DT46:DX46) -> 0
A47: 40 | F47: 38-8-12 | I47: 440.664 | J47: =G47*I47/1000 -> 0 | L47: =K47-J47 -> 0 | S47: =ROUND(SUM(M47:Q47),0) -> 0 | Y47: 37X22.5 | AB47: =+Z47*290/1000 -> 0 | AF47: =SUM(AC47:AE47) -> 0 | AI47: =+AF47*5% -> 0 | AK47: =ROUND(SUM(AF47:AJ47),0) -> 0 | AM47: 36 | AR47: 10 LBS 1 PLY PW SPOOL | BB47: =ROUND(SUM(AV47:BA47),0) -> 0 | BK47: =BI47*BJ47/1000 -> 0 | BQ47: =SUM(BL47:BO47) -> 0 | BX47: 200 | CC47: =BW47*BX47+BY47 -> 0 | CM47: 600 | CR47: =SUM(CL47*CM47)+CP47 -> 0 | DJ47: =SUM(DD47:DH47) -> 0 | DZ47: =SUM(DT47:DX47) -> 0
A48: 41 | F48: 38-8-12 | I48: 440.664 | J48: =G48*I48/1000 -> 0 | L48: =K48-J48 -> 0 | S48: =ROUND(SUM(M48:Q48),0) -> 0 | Y48: 37X22.5 | AB48: =+Z48*290/1000 -> 0 | AF48: =SUM(AC48:AE48) -> 0 | AI48: =+AF48*5% -> 0 | AK48: =ROUND(SUM(AF48:AJ48),0) -> 0 | AM48: 37 | AR48: 10 LBS 1 PLY PW SPOOL | BB48: =ROUND(SUM(AV48:BA48),0) -> 0 | BK48: =BI48*BJ48/1000 -> 0 | BQ48: =SUM(BL48:BO48) -> 0 | BX48: 200 | CC48: =BW48*BX48+BY48 -> 0 | CM48: 600 | CR48: =SUM(CL48*CM48)+CP48 -> 0 | DJ48: =SUM(DD48:DH48) -> 0 | DZ48: =SUM(DT48:DX48) -> 0
A49: 42 | F49: 38-8-12 | I49: 440.664 | J49: =G49*I49/1000 -> 0 | L49: =K49-J49 -> 0 | S49: =ROUND(SUM(M49:Q49),0) -> 0 | Y49: 37X22.5 | AB49: =+Z49*290/1000 -> 0 | AF49: =SUM(AC49:AE49) -> 0 | AI49: =+AF49*5% -> 0 | AK49: =ROUND(SUM(AF49:AJ49),0) -> 0 | AM49: 38 | AR49: 10 LBS 1 PLY PW SPOOL | BB49: =ROUND(SUM(AV49:BA49),0) -> 0 | BK49: =BI49*BJ49/1000 -> 0 | BQ49: =SUM(BL49:BO49) -> 0 | BX49: 200 | CC49: =BW49*BX49+BY49 -> 0 | CM49: 600 | CR49: =SUM(CL49*CM49)+CP49 -> 0 | DJ49: =SUM(DD49:DH49) -> 0 | DZ49: =SUM(DT49:DX49) -> 0
A50: 43 | F50: 38-8-12 | I50: 440.664 | J50: =G50*I50/1000 -> 0 | L50: =K50-J50 -> 0 | S50: =ROUND(SUM(M50:Q50),0) -> 0 | Y50: 37 X22.5 | AB50: =+Z50*290/1000 -> 0 | AF50: =SUM(AC50:AE50) -> 0 | AI50: =+AF50*5% -> 0 | AK50: =ROUND(SUM(AF50:AJ50),0) -> 0 | AM50: 39 | AR50: 10 LBS 1 PLY PW SPOOL | BB50: =ROUND(SUM(AV50:BA50),0) -> 0 | BK50: =BI50*BJ50/1000 -> 0 | BQ50: =SUM(BL50:BO50) -> 0 | BX50: 200 | CC50: =BW50*BX50+BY50 -> 0 | CM50: 600 | CR50: =SUM(CL50*CM50)+CP50 -> 0 | DJ50: =SUM(DD50:DH50) -> 0 | DZ50: =SUM(DT50:DX50) -> 0
A51: 44 | F51: 38-8-12 | I51: 440.664 | J51: =G51*I51/1000 -> 0 | L51: =K51-J51 -> 0 | S51: =ROUND(SUM(M51:Q51),0) -> 0 | Y51: 37 X22.5 | AB51: =+Z51*290/1000 -> 0 | AF51: =SUM(AC51:AE51) -> 0 | AI51: =+AF51*5% -> 0 | AK51: =ROUND(SUM(AF51:AJ51),0) -> 0 | AM51: 40 | AR51: 10 LBS 1 PLY PW SPOOL | BB51: =ROUND(SUM(AV51:BA51),0) -> 0 | BK51: =BI51*BJ51/1000 -> 0 | BQ51: =SUM(BL51:BO51) -> 0 | BX51: 200 | CC51: =BW51*BX51+BY51 -> 0 | CM51: 600 | CR51: =SUM(CL51*CM51)+CP51 -> 0 | DJ51: =SUM(DD51:DH51) -> 0 | DZ51: =SUM(DT51:DX51) -> 0
A52: 45 | B52: TOTAL | G52: =SUM(G33:G51) -> 101 | H52: =SUM(H33:H51) -> 44.181 | M52: =SUM(M33:M51) -> 6590627.5 | S52: =ROUND(SUM(M52:Q52),0) -> 6590627 | Y52: 37 X22.5 | AB52: =+Z52*290/1000 -> 0 | AF52: =SUM(AC52:AE52) -> 0 | AI52: =+AF52*5% -> 0 | AK52: =ROUND(SUM(AF52:AJ52),0) -> 0 | AM52: 41 | AR52: 10 LBS 1 PLY PW SPOOL | BB52: =ROUND(SUM(AV52:BA52),0) -> 0 | BK52: =BI52*BJ52/1000 -> 0 | BQ52: =SUM(BL52:BO52) -> 0 | BX52: 200 | CC52: =BW52*BX52+BY52 -> 0 | CM52: 600 | CR52: =SUM(CL52*CM52)+CP52 -> 0 | DJ52: =SUM(DD52:DH52) -> 0 | DZ52: =SUM(DT52:DX52) -> 0
A53: 46 | F53: D.W JUTE CANVAS | S53: =ROUND(SUM(M53:Q53),0) -> 0 | Y53: 37 X22.5 | AB53: =+Z53*290/1000 -> 0 | AF53: =SUM(AC53:AE53) -> 0 | AI53: =+AF53*5% -> 0 | AK53: =ROUND(SUM(AF53:AJ53),0) -> 0 | AM53: 42 | AR53: 10 LBS 1 PLY PW SPOOL | BB53: =ROUND(SUM(AV53:BA53),0) -> 0 | BK53: =BI53*BJ53/1000 -> 0 | BQ53: =SUM(BL53:BO53) -> 0 | BX53: 200 | CC53: =BW53*BX53+BY53 -> 0 | CM53: 600 | CR53: =SUM(CL53*CM53)+CP53 -> 0 | DJ53: =SUM(DD53:DH53) -> 0 | DZ53: =SUM(DT53:DX53) -> 0
A54: 47 | F54: D.W JUTE CANVAS | S54: =ROUND(SUM(M54:Q54),0) -> 0 | Y54: 37 X22.5 | AB54: =+Z54*290/1000 -> 0 | AF54: =SUM(AC54:AE54) -> 0 | AI54: =+AF54*5% -> 0 | AK54: =ROUND(SUM(AF54:AJ54),0) -> 0 | AM54: 43 | AR54: 10 LBS 1 PLY PW SPOOL | BB54: =ROUND(SUM(AV54:BA54),0) -> 0 | BK54: =BI54*BJ54/1000 -> 0 | BQ54: =SUM(BL54:BO54) -> 0 | BX54: 200 | CC54: =BW54*BX54+BY54 -> 0 | CM54: 600 | CR54: =SUM(CL54*CM54)+CP54 -> 0 | DJ54: =SUM(DD54:DH54) -> 0 | DZ54: =SUM(DT54:DX54) -> 0
A55: 48 | F55: D.W JUTE CANVAS | S55: =ROUND(SUM(M55:Q55),0) -> 0 | AF55: =SUM(AC55:AE55) -> 0 | AI55: =+AF55*5% -> 0 | AK55: =ROUND(SUM(AF55:AJ55),0) -> 0 | AM55: 44 | AR55: 10 LBS 1 PLY PW SPOOL | BB55: =ROUND(SUM(AV55:BA55),0) -> 0
A56: 49 | F56: D.W JUTE CANVAS | S56: =ROUND(SUM(M56:Q56),0) -> 0 | AF56: =SUM(AC56:AE56) -> 0 | AI56: =+AF56*5% -> 0 | AK56: =ROUND(SUM(AF56:AJ56),0) -> 0 | AN56: TOTAL | AS56: =SUM(AS46:AS55) -> 10 | AT56: =SUM(AT46:AT55) -> 0.53 | AU56: =SUM(AU46:AU55) -> 0 | AV56: =SUM(AV46:AV55) -> 69592.71 | BB56: =ROUND(SUM(AV56:BA56),0) -> 69593
A57: 50 | B57: TOTAL | G57: =SUM(G53:G56) -> 0 | H57: =SUM(H53:H56) -> 0 | M57: =SUM(M53:M56) -> 0 | S57: =ROUND(SUM(M57:Q57),0) -> 0 | AF57: =SUM(AC57:AE57) -> 0 | AI57: =+AF57*5% -> 0 | AK57: =ROUND(SUM(AF57:AJ57),0) -> 0 | AM57: 50 | AR57: 10 LBS 2 PLY PW SPOOL | BB57: =ROUND(SUM(AV57:BA57),0) -> 0
A58: 51 | F58: 51X51 LENO SELVEDGE | S58: =ROUND(SUM(M58:Q58),0) -> 0 | Y58: 37 X22.5 | AB58: =+Z58*290/1000 -> 0 | AF58: =SUM(AC58:AE58) -> 0 | AI58: =+AF58*5% -> 0 | AK58: =ROUND(SUM(AF58:AJ58),0) -> 0 | AM58: 51 | AR58: 12 LBS 2 PLY PW SPOOL | BB58: =ROUND(SUM(AV58:BA58),0) -> 0 | BK58: =BI58*BJ58/1000 -> 0 | BQ58: =SUM(BL58:BO58) -> 0 | BX58: 200 | CC58: =BW58*BX58+BY58 -> 0 | CM58: 600 | CR58: =SUM(CL58*CM58)+CP58 -> 0 | DJ58: =SUM(DD58:DH58) -> 0 | DZ58: =SUM(DT58:DX58) -> 0
A59: 52 | S59: =ROUND(SUM(M59:Q59),0) -> 0 | AF59: =SUM(AC59:AE59) -> 0 | AI59: =+AF59*5% -> 0 | AK59: =ROUND(SUM(AF59:AJ59),0) -> 0 | AM59: 52 | AR59: 10 LBS 2 PLY PW SPOOL | BB59: =ROUND(SUM(AV59:BA59),0) -> 0
A60: 53 | S60: =ROUND(SUM(M60:Q60),0) -> 0 | AF60: =SUM(AC60:AE60) -> 0 | AI60: =+AF60*5% -> 0 | AK60: =ROUND(SUM(AF60:AJ60),0) -> 0 | AM60: 53 | AR60: 10 LBS 2 PLY PW SPOOL | BB60: =ROUND(SUM(AV60:BA60),0) -> 0
A61: 54 | S61: =ROUND(SUM(M61:Q61),0) -> 0 | AF61: =SUM(AC61:AE61) -> 0 | AI61: =+AF61*5% -> 0 | AK61: =ROUND(SUM(AF61:AJ61),0) -> 0 | AM61: 54 | AR61: 10 LBS 2 PLY PW SPOOL | BB61: =ROUND(SUM(AV61:BA61),0) -> 0
A62: 55 | S62: =ROUND(SUM(M62:Q62),0) -> 0 | AF62: =SUM(AC62:AE62) -> 0 | AI62: =+AF62*5% -> 0 | AK62: =ROUND(SUM(AF62:AJ62),0) -> 0 | AN62: TOTAL | AS62: =SUM(AS57:AS61) -> 0 | AT62: =SUM(AT57:AT61) -> 0 | AU62: =SUM(AU57:AU61) -> 0 | AV62: =SUM(AV57:AV61) -> 0 | BB62: =ROUND(SUM(AV62:BA62),0) -> 0
A63: 56 | B63: TOTAL | G63: =SUM(G53:G62) -> 0 | H63: =SUM(H58:H62) -> 0 | M63: =SUM(M58:M62) -> 0 | S63: =ROUND(SUM(M63:Q63),0) -> 0 | AF63: =SUM(AC63:AE63) -> 0 | AI63: =+AF63*5% -> 0 | AK63: =ROUND(SUM(AF63:AJ63),0) -> 0 | AM63: 55 | AN63: 03.12.25 | AP63: 384 | AR63: 10 LBS 3 PLY PW | AS63: 106 | AT63: 5.484 | AV63: 720087.59 | AW63: 18002.19 | AX63: =+AW63 -> 18002.19 | BB63: =ROUND(SUM(AV63:BA63),0) -> 756092
A64: 57 | B64: 05.12.25 | E64: 389 | F64: 40-6.5 OZ | G64: 7 | H64: 2.58 | M64: 383945.28 | N64: 9598.63 | O64: =+N64 -> 9598.63 | S64: =ROUND(SUM(M64:Q64),0) -> 403143 | AF64: =SUM(AC64:AE64) -> 0 | AI64: =+AF64*5% -> 0 | AK64: =ROUND(SUM(AF64:AJ64),0) -> 0 | AM64: 56 | AR64: 10 LBS 3 PLY PW | BB64: =ROUND(SUM(AV64:BA64),0) -> 0
A65: 58 | B65: 15.12.25 | E65: 398 | F65: 40-6.5 OZ | G65: 36 | H65: 13.268 | M65: 1987387.2 | N65: 49684.68 | O65: =+N65 -> 49684.68 | S65: =ROUND(SUM(M65:Q65),0) -> 2086757 | Y65: 37 X22.5 | AB65: =+Z65*290/1000 -> 0 | AF65: =SUM(AC65:AE65) -> 0 | AI65: =+AF65*5% -> 0 | AK65: =ROUND(SUM(AF65:AJ65),0) -> 0 | AM65: 57 | AR65: 10 LBS 3 PLY PW | BB65: =ROUND(SUM(AV65:BA65),0) -> 0 | BK65: =BI65*BJ65/1000 -> 0 | BQ65: =SUM(BL65:BO65) -> 0 | BX65: 200 | CC65: =BW65*BX65+BY65 -> 0 | CM65: 600 | CR65: =SUM(CL65*CM65)+CP65 -> 0 | DJ65: =SUM(DD65:DH65) -> 0 | DZ65: =SUM(DT65:DX65) -> 0
B66: 26.12.25 | E66: 401 | F66: 40-6.5 OZ | G66: 23 | H66: 8.477 | M66: 1269752.9 | N66: 31743.82 | O66: =+N66 -> 31743.82 | S66: =ROUND(SUM(M66:Q66),0) -> 1333241 | AF66: =SUM(AC66:AE66) -> 0 | AI66: =+AF66*5% -> 0 | AK66: =ROUND(SUM(AF66:AJ66),0) -> 0
B67: 27.12.25 | E67: 410 | F67: 40-6.5 OZ | G67: 7 | H67: 2.58 | M67: 386453.04 | N67: 9661.33 | O67: =+N67 -> 9661.33 | S67: =ROUND(SUM(M67:Q67),0) -> 405776 | AF67: =SUM(AC67:AE67) -> 0 | AI67: =+AF67*5% -> 0 | AK67: =ROUND(SUM(AF67:AJ67),0) -> 0
A68: 59 | F68: 40-6.5 OZ | S68: =ROUND(SUM(M68:Q68),0) -> 0 | Y68: 37 X22.5 | AB68: =+Z68*290/1000 -> 0 | AF68: =SUM(AC68:AE68) -> 0 | AI68: =+AF68*5% -> 0 | AK68: =ROUND(SUM(AF68:AJ68),0) -> 0 | AM68: 58 | AR68: 10 LBS 3 PLY PW | AX68: =+AW68 -> 0 | BB68: =ROUND(SUM(AV68:BA68),0) -> 0 | BK68: =BI68*BJ68/1000 -> 0 | BQ68: =SUM(BL68:BO68) -> 0 | BX68: 200 | CC68: =BW68*BX68+BY68 -> 0 | CM68: 600 | CR68: =SUM(CL68*CM68)+CP68 -> 0 | DJ68: =SUM(DD68:DH68) -> 0 | DZ68: =SUM(DT68:DX68) -> 0
A69: 60 | F69: 40-6.5 OZ | S69: =ROUND(SUM(M69:Q69),0) -> 0 | Y69: 37 X22.5 | AB69: =+Z69*290/1000 -> 0 | AF69: =SUM(AC69:AE69) -> 0 | AI69: =+AF69*5% -> 0 | AK69: =ROUND(SUM(AF69:AJ69),0) -> 0 | AM69: 59 | AR69: 10 LBS 3 PLY PW | BB69: =ROUND(SUM(AV69:BA69),0) -> 0 | BK69: =BI69*BJ69/1000 -> 0 | BQ69: =SUM(BL69:BO69) -> 0 | BX69: 200 | CC69: =BW69*BX69+BY69 -> 0 | CM69: 600 | CR69: =SUM(CL69*CM69)+CP69 -> 0 | DJ69: =SUM(DD69:DH69) -> 0 | DZ69: =SUM(DT69:DX69) -> 0
A70: 61 | B70: TOTAL | G70: =SUM(G64:G69) -> 73 | H70: =SUM(H64:H69) -> 26.905 | M70: =SUM(M64:M69) -> 4027538.4 | S70: =ROUND(SUM(M70:Q70),0) -> 4027538 | Y70: 37 X22.5 | AB70: =+Z70*290/1000 -> 0 | AF70: =SUM(AC70:AE70) -> 0 | AI70: =+AF70*5% -> 0 | AK70: =ROUND(SUM(AF70:AJ70),0) -> 0 | AM70: 60 | AR70: 10 LBS 3 PLY PW | BB70: =ROUND(SUM(AV70:BA70),0) -> 0 | BK70: =BI70*BJ70/1000 -> 0 | BQ70: =SUM(BL70:BO70) -> 0 | BX70: 200 | CC70: =BW70*BX70+BY70 -> 0 | CM70: 600 | CR70: =SUM(CL70*CM70)+CP70 -> 0 | DJ70: =SUM(DD70:DH70) -> 0 | DZ70: =SUM(DT70:DX70) -> 0
A71: 62 | F71: 44-5 OZ | S71: =ROUND(SUM(M71:Q71),0) -> 0 | AF71: =SUM(AC71:AE71) -> 0 | AI71: =+AF71*5% -> 0 | AK71: =ROUND(SUM(AF71:AJ71),0) -> 0 | AN71: TOTAL | AS71: =SUM(AS63:AS70) -> 106 | AT71: =SUM(AT63:AT70) -> 5.484 | AU71: =SUM(AU63:AU70) -> 0 | AV71: =SUM(AV63:AV70) -> 720087.59 | BB71: =ROUND(SUM(AV71:BA71),0) -> 720088
A72: 63 | F72: 44-5 OZ | S72: =ROUND(SUM(M72:Q72),0) -> 0 | AF72: =SUM(AC72:AE72) -> 0 | AK72: =ROUND(SUM(AF72:AJ72),0) -> 0 | AM72: 61 | AR72: 10.5 LBS 1 PLY MACROLL | BB72: =ROUND(SUM(AV72:BA72),0) -> 0
A73: 64 | F73: 44-5 OZ | S73: =ROUND(SUM(M73:Q73),0) -> 0 | Y73: 37 X22.5 | AB73: =+Z73*290/1000 -> 0 | AF73: =SUM(AC73:AE73) -> 0 | AK73: =ROUND(SUM(AF73:AJ73),0) -> 0 | AM73: 62 | AR73: 10.5 LBS 1 PLY MACROLL | BB73: =ROUND(SUM(AV73:BA73),0) -> 0 | BK73: =BI73*BJ73/1000 -> 0 | BQ73: =SUM(BL73:BO73) -> 0 | BX73: 200 | CC73: =BW73*BX73+BY73 -> 0 | CM73: 750 | CR73: =SUM(CL73*CM73)+CP73 -> 0 | DJ73: =SUM(DD73:DH73) -> 0 | DZ73: =SUM(DT73:DX73) -> 0
A74: 65 | F74: 44-5 OZ | S74: =ROUND(SUM(M74:Q74),0) -> 0 | AF74: =SUM(AC74:AE74) -> 0 | AK74: =ROUND(SUM(AF74:AJ74),0) -> 0 | AM74: 63 | AR74: 10.5 LBS 1 PLY MACROLL | BB74: =ROUND(SUM(AV74:BA74),0) -> 0
A75: 66 | B75: TOTAL | G75: =SUM(G71:G74) -> 0 | H75: =SUM(H71:H74) -> 0 | M75: =SUM(M71:M74) -> 0 | S75: =ROUND(SUM(M75:Q75),0) -> 0 | AF75: =SUM(AC75:AE75) -> 0 | AK75: =ROUND(SUM(AF75:AJ75),0) -> 0 | AM75: 64 | AR75: 10.5 LBS 1 PLY MACROLL | BB75: =ROUND(SUM(AV75:BA75),0) -> 0
A76: 67 | F76: 20 " X10 | S76: =ROUND(SUM(M76:Q76),0) -> 0 | AF76: =SUM(AC76:AE76) -> 0 | AK76: =ROUND(SUM(AF76:AJ76),0) -> 0 | AM76: 65 | AR76: 10.5 LBS 1 PLY MACROLL | BB76: =ROUND(SUM(AV76:BA76),0) -> 0
A77: 68 | F77: 20 " X10 | S77: =ROUND(SUM(M77:Q77),0) -> 0 | AF77: =SUM(AC77:AE77) -> 0 | AK77: =ROUND(SUM(AF77:AJ77),0) -> 0 | AN77: TOTAL | AS77: =SUM(AS72:AS76) -> 0 | AT77: =SUM(AT72:AT76) -> 0 | AU77: =SUM(AU72:AU76) -> 0 | AV77: =SUM(AV72:AV76) -> 0 | BB77: =ROUND(SUM(AV77:BA77),0) -> 0
A78: 69 | F78: 20 " X10 | S78: =ROUND(SUM(M78:Q78),0) -> 0 | Y78: 48X26.5 HD 767GMS 500 PCS | AB78: =+Z78*383.5/1000 -> 0 | AF78: =SUM(AC78:AE78) -> 0 | AK78: =ROUND(SUM(AF78:AJ78),0) -> 0 | AR78: SKG GRAND TOTAL | AS78: =+AS77+AS71+AS62+AS56+AS45+AS40+AS29+AS18 -> 444 | AT78: =+AT77+AT71+AT62+AT56+AT45+AT40+AT29+AT18 -> 22.408 | AU78: =+AU77+AU71+AU62+AU56+AU45+AU40+AU29+AU18 -> 0 | AV78: =+AV77+AV71+AV62+AV56+AV45+AV40+AV29+AV18 -> 2911215.3 | AX78: =+AW78 -> 0 | BB78: =ROUND(SUM(AV78:BA78),0) -> 2911215 | BK78: =BI78*BJ78/1000 -> 0 | BQ78: =SUM(BL78:BO78) -> 0 | BX78: 200 | CC78: =BW78*BX78+BY78 -> 0 | CM78: 750 | CR78: =SUM(CL78*CM78)+CP78 -> 0 | DJ78: =SUM(DD78:DH78) -> 0 | DZ78: =SUM(DT78:DX78) -> 0
A79: 70 | F79: 20 " X10 | S79: =ROUND(SUM(M79:Q79),0) -> 0 | Y79: 48X26.5 HD 767GMS 500 PCS | AB79: =+Z79*383.5/1000 -> 0 | AF79: =SUM(AC79:AE79) -> 0 | AK79: =ROUND(SUM(AF79:AJ79),0) -> 0 | AM79: 66 | AR79: 8 LBS 1 PLY PW SPOOL | AX79: =+AW79 -> 0 | BB79: =SUM(AV79:BA79) -> 0 | BK79: =BI79*BJ79/1000 -> 0 | BQ79: =SUM(BL79:BO79) -> 0 | BX79: 200 | CC79: =BW79*BX79+BY79 -> 0 | CM79: 750 | CR79: =SUM(CL79*CM79)+CP79 -> 0 | DJ79: =SUM(DD79:DH79) -> 0 | DZ79: =SUM(DT79:DX79) -> 0
A80: 71 | F80: 20 " X10 | S80: =ROUND(SUM(M80:Q80),0) -> 0 | Y80: 48X26.5 HD 767GMS 500 PCS | AB80: =+Z80*383.5/1000 -> 0 | AF80: =SUM(AC80:AE80) -> 0 | AK80: =ROUND(SUM(AF80:AJ80),0) -> 0 | AM80: 67 | AR80: 8 LBS 1 PLY PW SPOOL | AX80: =+AW80 -> 0 | BB80: =SUM(AV80:BA80) -> 0 | BK80: =BI80*BJ80/1000 -> 0 | BQ80: =SUM(BL80:BO80) -> 0 | BX80: 200 | CC80: =BW80*BX80+BY80 -> 0 | CM80: 750 | CR80: =SUM(CL80*CM80)+CP80 -> 0 | DJ80: =SUM(DD80:DH80) -> 0 | DZ80: =SUM(DT80:DX80) -> 0
A81: 72 | B81: TOTAL | G81: =SUM(G76:G80) -> 0 | H81: =SUM(H76:H80) -> 0 | M81: =SUM(M76:M80) -> 0 | S81: =ROUND(SUM(M81:Q81),0) -> 0 | Y81: 48X26.5 HD 767GMS 500 PCS | AB81: =+Z81*383.5/1000 -> 0 | AF81: =SUM(AC81:AE81) -> 0 | AK81: =ROUND(SUM(AF81:AJ81),0) -> 0 | AM81: 68 | AR81: 8 LBS 1 PLY PW SPOOL | AX81: =+AW81 -> 0 | BB81: =SUM(AV81:BA81) -> 0 | BK81: =BI81*BJ81/1000 -> 0 | BQ81: =SUM(BL81:BO81) -> 0 | CM81: 750 | CR81: =SUM(CL81*CM81)+CP81 -> 0 | DJ81: =SUM(DD81:DH81) -> 0 | DZ81: =SUM(DT81:DX81) -> 0
A82: 73 | S82: =ROUND(SUM(M82:Q82),0) -> 0 | Y82: 48X26.5 HD 767GMS 500 PCS | AB82: =+Z82*383.5/1000 -> 0 | AF82: =SUM(AC82:AE82) -> 0 | AK82: =ROUND(SUM(AF82:AJ82),0) -> 0 | AM82: 69 | AR82: 8 LBS 1 PLY PW SPOOL | AX82: =+AW82 -> 0 | BB82: =SUM(AV82:BA82) -> 0 | BK82: =BI82*BJ82/1000 -> 0 | BQ82: =SUM(BL82:BO82) -> 0 | CM82: 750 | CR82: =SUM(CL82*CM82)+CP82 -> 0 | DJ82: =SUM(DD82:DH82) -> 0 | DZ82: =SUM(DT82:DX82) -> 0
A83: 74 | S83: =ROUND(SUM(M83:Q83),0) -> 0 | Y83: 48X26.5 HD 767GMS 500 PCS | AB83: =+Z83*383.5/1000 -> 0 | AF83: =SUM(AC83:AE83) -> 0 | AK83: =ROUND(SUM(AF83:AJ83),0) -> 0 | AM83: 70 | AR83: 8 LBS 1 PLY PW SPOOL | AX83: =+AW83 -> 0 | BB83: =SUM(AV83:BA83) -> 0 | BK83: =BI83*BJ83/1000 -> 0 | BQ83: =SUM(BL83:BO83) -> 0 | CM83: 750 | CR83: =SUM(CL83*CM83)+CP83 -> 0 | DJ83: =SUM(DD83:DH83) -> 0 | DZ83: =SUM(DT83:DX83) -> 0
A84: 75 | S84: =ROUND(SUM(M84:Q84),0) -> 0 | Y84: 48X26.5 HD 767GMS 500 PCS | AB84: =+Z84*383.5/1000 -> 0 | AF84: =SUM(AC84:AE84) -> 0 | AK84: =ROUND(SUM(AF84:AJ84),0) -> 0 | AM84: 71 | AR84: 8 LBS 1 PLY PW SPOOL | AX84: =+AW84 -> 0 | BB84: =SUM(AV84:BA84) -> 0 | BK84: =BI84*BJ84/1000 -> 0 | BQ84: =SUM(BL84:BO84) -> 0 | CM84: 750 | CR84: =SUM(CL84*CM84)+CP84 -> 0 | DJ84: =SUM(DD84:DH84) -> 0 | DZ84: =SUM(DT84:DX84) -> 0
A85: 76 | S85: =ROUND(SUM(M85:Q85),0) -> 0 | Y85: 48X26.5 HD 767GMS 500 PCS | AB85: =+Z85*383.5/1000 -> 0 | AF85: =SUM(AC85:AE85) -> 0 | AK85: =ROUND(SUM(AF85:AJ85),0) -> 0 | AM85: 72 | AR85: 8 LBS 1 PLY PW SPOOL | AX85: =+AW85 -> 0 | BB85: =SUM(AV85:BA85) -> 0 | BK85: =BI85*BJ85/1000 -> 0 | BQ85: =SUM(BL85:BO85) -> 0 | CM85: 750 | CR85: =SUM(CL85*CM85)+CP85 -> 0 | DJ85: =SUM(DD85:DH85) -> 0 | DZ85: =SUM(DT85:DX85) -> 0
A86: 77 | S86: =ROUND(SUM(M86:Q86),0) -> 0 | Y86: 48X26.5 HD 767GMS 500 PCS | AB86: =+Z86*383.5/1000 -> 0 | AF86: =SUM(AC86:AE86) -> 0 | AK86: =ROUND(SUM(AF86:AJ86),0) -> 0 | AN86: TOTAL | AS86: =SUM(AS79:AS85) -> 0 | AT86: =SUM(AT79:AT85) -> 0 | AU86: =SUM(AU79:AU85) -> 0 | AV86: =SUM(AV79:AV85) -> 0 | AX86: =+AW86 -> 0 | BB86: =SUM(AV86:BA86) -> 0 | BK86: =BI86*BJ86/1000 -> 0 | BQ86: =SUM(BL86:BO86) -> 0 | CM86: 750 | CR86: =SUM(CL86*CM86)+CP86 -> 0 | DJ86: =SUM(DD86:DH86) -> 0 | DZ86: =SUM(DT86:DX86) -> 0
A87: 78 | S87: =ROUND(SUM(M87:Q87),0) -> 0 | Y87: 48X26.5 HD 767GMS 500 PCS | AB87: =+Z87*383.5/1000 -> 0 | AF87: =SUM(AC87:AE87) -> 0 | AK87: =ROUND(SUM(AF87:AJ87),0) -> 0 | AM87: 73 | AR87: 6 LBS 1 PLY PW SPOOL | AX87: =+AW87 -> 0 | BB87: =SUM(AV87:BA87) -> 0 | BK87: =BI87*BJ87/1000 -> 0 | BQ87: =SUM(BL87:BO87) -> 0 | BX87: 200 | CC87: =BW87*BX87+BY87 -> 0 | CM87: 750 | CR87: =SUM(CL87*CM87)+CP87 -> 0 | DJ87: =SUM(DD87:DH87) -> 0 | DZ87: =SUM(DT87:DX87) -> 0
A88: 79 | B88: TOTAL | H88: =SUM(H82:H87) -> 0 | M88: =SUM(M82:M87) -> 0 | S88: =ROUND(SUM(M88:Q88),0) -> 0 | Y88: 48X26.5 HD 767GMS 500 PCS | AB88: =+Z88*383.5/1000 -> 0 | AF88: =SUM(AC88:AE88) -> 0 | AK88: =ROUND(SUM(AF88:AJ88),0) -> 0 | AM88: 74 | AR88: 6 LBS 1 PLY PW SPOOL | AX88: =+AW88 -> 0 | BB88: =SUM(AV88:BA88) -> 0 | BK88: =BI88*BJ88/1000 -> 0 | BQ88: =SUM(BL88:BO88) -> 0 | CM88: 750 | CR88: =SUM(CL88*CM88)+CP88 -> 0 | DJ88: =SUM(DD88:DH88) -> 0 | DZ88: =SUM(DT88:DX88) -> 0
A89: 80 | F89: 20X10 | S89: =ROUND(SUM(M89:Q89),0) -> 0 | Y89: 48X26.5 HD 767GMS 500 PCS | AB89: =+Z89*383.5/1000 -> 0 | AF89: =SUM(AC89:AE89) -> 0 | AK89: =ROUND(SUM(AF89:AJ89),0) -> 0 | AM89: 75 | AR89: 6 LBS 1 PLY PW SPOOL | AX89: =+AW89 -> 0 | BB89: =SUM(AV89:BA89) -> 0 | BK89: =BI89*BJ89/1000 -> 0 | BQ89: =SUM(BL89:BO89) -> 0 | CM89: 750 | CR89: =SUM(CL89*CM89)+CP89 -> 0 | DJ89: =SUM(DD89:DH89) -> 0 | DZ89: =SUM(DT89:DX89) -> 0
A90: 81 | S90: =ROUND(SUM(M90:Q90),0) -> 0 | Y90: 48X26.5 HD 767GMS 500 PCS | AB90: =+Z90*383.5/1000 -> 0 | AF90: =SUM(AC90:AE90) -> 0 | AK90: =ROUND(SUM(AF90:AJ90),0) -> 0 | AM90: 76 | AR90: 6 LBS 1 PLY PW SPOOL | AX90: =+AW90 -> 0 | BB90: =SUM(AV90:BA90) -> 0 | BK90: =BI90*BJ90/1000 -> 0 | BQ90: =SUM(BL90:BO90) -> 0 | CM90: 750 | CR90: =SUM(CL90*CM90)+CP90 -> 0 | DJ90: =SUM(DD90:DH90) -> 0 | DZ90: =SUM(DT90:DX90) -> 0
A91: 82 | S91: =ROUND(SUM(M91:Q91),0) -> 0 | AB91: =+Z91*383.5/1000 -> 0 | AF91: =SUM(AC91:AE91) -> 0 | AK91: =ROUND(SUM(AF91:AJ91),0) -> 0 | AM91: 77 | AR91: 6 LBS 1 PLY PW SPOOL | AX91: =+AW91 -> 0 | BB91: =SUM(AV91:BA91) -> 0 | BK91: =BI91*BJ91/1000 -> 0 | BQ91: =SUM(BL91:BO91) -> 0 | CM91: 750 | CR91: =SUM(CL91*CM91)+CP91 -> 0 | DJ91: =SUM(DD91:DH91) -> 0 | DZ91: =SUM(DT91:DX91) -> 0
A92: 83 | S92: =ROUND(SUM(M92:Q92),0) -> 0 | AB92: =+Z92*383.5/1000 -> 0 | AF92: =SUM(AC92:AE92) -> 0 | AK92: =ROUND(SUM(AF92:AJ92),0) -> 0 | AN92: TOTAL | AS92: =SUM(AS87:AS91) -> 0 | AT92: =SUM(AT87:AT91) -> 0 | AU92: =SUM(AU87:AU91) -> 0 | AV92: =SUM(AV87:AV91) -> 0 | AX92: =+AW92 -> 0 | BB92: =SUM(AV92:BA92) -> 0 | BK92: =BI92*BJ92/1000 -> 0 | BQ92: =SUM(BL92:BO92) -> 0 | CM92: 750 | CR92: =SUM(CL92*CM92)+CP92 -> 0 | DJ92: =SUM(DD92:DH92) -> 0 | DZ92: =SUM(DT92:DX92) -> 0
A93: 84 | B93: TOTAL | H93: =SUM(H89:H92) -> 0 | M93: =SUM(M89:M92) -> 0 | S93: =ROUND(SUM(M93:Q93),0) -> 0 | AB93: =+Z93*383.5/1000 -> 0 | AF93: =SUM(AC93:AE93) -> 0 | AK93: =ROUND(SUM(AF93:AJ93),0) -> 0 | AR93: HESS GRAND TOTAL WEIGHT | AS93: =+AS92+AS86 -> 0 | AT93: =+AT92+AT86 -> 0 | AU93: =+AU92+AU86 -> 0 | AV93: =+AV92+AV86 -> 0 | AX93: =+AW93 -> 0 | BB93: =SUM(AV93:BA93) -> 0 | BQ93: =SUM(BL93:BO93) -> 0 | BX93: 200 | CC93: =BW93*BX93+BY93 -> 0 | CM93: 750 | CR93: =SUM(CL93*CM93)+CP93 -> 0
A94: TOTAL | G94: =+G81+G75+G70+G63+G57+G52+G32+G18+G12 -> 289 | H94: =+H93+H88+H81+H75+H70+H63+H57+H52+H32+H18+H12 -> 109.231 | J94: =SUM(J8:J93) -> 0 | M94: =+M93+M88+M81+M75+M70+M63+M57+M52+M32+M18+M12 -> 15940003 | N94: =SUM(N7:N93) -> 398500.08 | O94: =SUM(O7:O93) -> 398500.08 | P94: =SUM(P7:P93) -> 0 | Q94: =SUM(Q7:Q93) -> 0 | R94: =SUM(R7:R93) -> 0 | S94: =SUM(S7:S93) -> 32677006 | U94: TOTAL | Z94: =SUM(Z7:Z93) -> 957 | AB94: =SUM(AB7:AB93) -> 277.53 | AC94: =SUM(AC7:AC93) -> 36488713 | AD94: =SUM(AD7:AD93) -> 239250 | AE94: =SUM(AE7:AE93) -> 98582.4 | AF94: =SUM(AF7:AF93) -> 36826545 | AG94: =SUM(AG7:AG93) -> 0 | AH94: =SUM(AH7:AH93) -> 0 | AI94: =SUM(AI7:AI93) -> 1841327.3 | ... AK94: =SUM(AK7:AK93) -> 38667871 | AN94: TOTAL | AS94: =+AS93+AS78 -> 444 | AT94: =+AT93+AT78 -> 22.408 | AU94: =+AU93+AU78 -> 0 | AV94: =+AV93+AV78 -> 2911215.3 | AW94: =SUM(AW7:AW93) -> 72780.38 | AX94: =SUM(AX7:AX93) -> 72780.38 | AY94: =SUM(AY7:AY93) -> 0 | AZ94: =SUM(AZ7:AZ93) -> 0 | BA94: =SUM(BA7:BA93) -> 0 | BB94: =SUM(BB7:BB93) -> 7852087 | BD94: TOTAL | BI94: =SUM(BI7:BI93) -> 67 | BK94: =SUM(BK7:BK93) -> 0.027 | BL94: =SUM(BL7:BL93) -> 9045 | BM94: =SUM(BM7:BM93) -> 226.13 | BN94: =SUM(BN7:BN93) -> 226.13 | BO94: =SUM(BO7:BO93) -> 0 | BP94: =SUM(BP7:BP93) -> 0 | BQ94: =SUM(BQ7:BQ93) -> 9497.26 | BS94: TOTAL | BV94: =SUM(BV8:BV93) -> 0 | BW94: =SUM(BW7:BW93) -> 19.86 | CC94: =SUM(CC7:CC93) -> 5068 | CD94: =SUM(CD8:CD93) -> 0 | CE94: =SUM(CE8:CE93) -> 0 | CF94: =SUM(CF8:CF93) -> 0 | CH94: TOTAL | CK94: =SUM(CK8:CK93) -> 0 | CL94: =SUM(CL7:CL93) -> 12.48 | CN94: =SUM(CN7:CN93) -> 0 | CR94: =SUM(CR7:CR93) -> 8488 | CW94: TOTAL | DB94: =SUM(DB8:DB93) -> 0 | DC94: =SUM(DC7:DC93) -> 0 | DD94: =SUM(DD7:DD93) -> 0 | DF94: =SUM(DF7:DF93) -> 0 | DG94: =SUM(DG7:DG93) -> 0 | DH94: =SUM(DH7:DH93) -> 0 | DI94: =SUM(DI7:DI93) -> 0 | DJ94: =SUM(DJ7:DJ93) -> 0 | DM94: TOTAL | DR94: =SUM(DR8:DR93) -> 0 | DS94: =SUM(DS7:DS93) -> 0 | DT94: =SUM(DT7:DT93) -> 0 | DV94: =SUM(DV7:DV93) -> 0 | DW94: =SUM(DW7:DW93) -> 0 | DX94: =SUM(DX7:DX93) -> 0 | DY94: =SUM(DY7:DY93) -> 0 | DZ94: =SUM(DZ7:DZ93) -> 0
F95: SUMMARY
F96: JUCO CLOTH | H96: =+BK94 -> 0.027 | J96: HESSIAN | M96: =+M94 -> 15940003 | N96: =+N94 -> 398500.08 | O96: =+O94 -> 398500.08 | P96: =+P94 -> 0 | Q96: =+Q94 -> 0 | CH96: CADDIES +CADDIES WTG | CL96: =CL94+CN94 -> 12.48
F97: BLEACH | H97: =+DC94 -> 0
F98: TOTAL NET WT | H98: =SUM(H94:H97) -> 109.258 | J98: JUCO CLOTH | M98: =+BL94 -> 9045 | N98: =+BM94 -> 226.13 | O98: =+BN94 -> 226.13 | P98: =+BO94 -> 0 | Q98: =+BP94 -> 0
F100: HESSIAN +JUCO | I100: JCI | J100: HESS+ JUCO | M100: =SUM(M96+M98) -> 15949048 | N100: =SUM(N96+N98) -> 398726.21 | O100: =SUM(O96+O98) -> 398726.21 | P100: =SUM(P96+P98) -> 0 | Q100: =SUM(Q96+Q98) -> 0
F102: SKG | G102: =+Z94 -> 957 | H102: =+AB94 -> 277.53 | I102: JCI | J102: SACKING | M102: =+AF94 -> 36826545 | N102: =+AG94 -> 0 | O102: =+AH94 -> 0 | P102: =+AI94 -> 1841327.3 | Q102: =+AJ94 -> 0
F104: YARN | H104: =+AT94 -> 22.408 | I104: JCI | J104: SALE YARN | M104: =+AV94 -> 2911215.3 | N104: =+AW94 -> 72780.38 | O104: =+AX94 -> 72780.38 | P104: =+AY94 -> 0 | Q104: =+BA94 -> 0 | R104: =+AZ94 -> 0
F106: BLEACH | I106: JCI | J106: BLEACHED | M106: =+DD94 -> 0 | Q106: =+DH94 -> 0
I108: JCI | J108: GRAND TOTAL | M108: =SUM(M100+M102+M104+M106)/100000 -> 556.86808 | N108: =SUM(N100+N102+N104+N106) -> 471506.59 | O108: =SUM(O100+O102+O104+O106) -> 471506.59 | P108: =SUM(P100+P102+P104+P106) -> 1841327.3 | Q108: =SUM(Q100+Q102+Q104+Q106) -> 0 | R108: =SUM(R100+R102+R104+R106) -> 0

Sheet JCIR
A1: JUTE GOODS | D1: DECEMBER-2025
A2: Sl.No | B2: Category name | C2: FABRIC QUALITY | D2: HS Code | E2: Op.Stock | F2: Prod (RG1) GROSS | G2: Despatch for domestic consumption GROSS | H2: Export Qty | I2: Export Value (Rs.) | J2: Import B.desh | K2: Import Other | L2: Import Value (Rs.) | M2: End Stock
A3: 1 | B3: Cloth /Fabric | D3: 5310
A4: 2 | B4: Carpet Backing fabric | D4: 5310 10 11
A5: 3 | B5: sacking Fabric | D5: 5310 10 12
A6: 4 | B6: Hessain Fabric | D6: 5310 10 13 | E6: =+GROSS!F33 -> 34.595627 | F6: =+GROSS!I33+'EXCISE SALES DETAILS'!BK94 -> 96.148433 | G6: =+GROSS!L33+'EXCISE SALES DETAILS'!BK94 -> 110.07603 | M6: =E6+F6-G6 -> 20.668029
A7: 5 | B7: Canvas Fabric | D7: 4310 10 14
A8: 6 | B8: Bleached Fabric | D8: 5310 90
A9: 7 | B9: Others
A10: 8 | B10: Yarn for sale | D10: 5307 | F10: =+'EXCISE SALES DETAILS'!AT94 -> 22.408 | G10: =+'EXCISE SALES DETAILS'!AT94 -> 22.408 | M10: =F10-G10 -> 0
A11: 9 | B11: Imported Yarn
A12: 10 | B12: Bags
A13: 11 | B13: Hessain Bags | D13: 6305 10 30 | E13: =+GROSS!F24 -> 0 | F13: =+GROSS!I24 -> 0 | G13: =+GROSS!L24 -> 0 | M13: =E13+F13-G13 -> 0
A14: 12 | B14: 50 kg Sugar bags
B15: 15138- 2010
A16: 13 | B16: Other Hessain bags
A17: 14 | B17: Sacking Bags | D17: 6305 10 40
B18: 50 kg B twill (580 grm) | D18: 6305.104 | E18: =+GROSS!F36 -> 106.64387 | F18: =+GROSS!I36 -> 191.08245 | G18: =+GROSS!L36 -> 279.61148 | M18: =E18+F18-G18 -> 18.11485
A19: 15 | B19: (is 16186:2014) for Gov
B20: TYPE A
B21: 50 kg B twill (580 grm)
A22: 16 | B22: B.TWILL BAGS 48X26.5HD 767 GM/BAG 500 PCS | D22: 6305.104 | E22: =+GROSS!F35 -> 0 | F22: =+GROSS!I35 -> 0 | G22: =+GROSS!L35 -> 0 | M22: =E22+F22-G22 -> 0
B23: TYPE B
A24: 17 | B24: A twill (is 1943:1955)
B25: 50 kg Sugar bags
A26: 18 | B26: A twill for others
